Workbook
Name A_Att: Attendance_Leave!$K$2:$K$501
Name A_Dept: Attendance_Leave!$C$2:$C$501
Name A_Flag: Attendance_Leave!$O$2:$O$501
Name A_OT: Attendance_Leave!$N$2:$N$501
Name A_Planned: Attendance_Leave!$F$2:$F$501
Name A_Sick: Attendance_Leave!$G$2:$G$501
Name A_Status: Attendance_Leave!$D$2:$D$501
Name A_Unpl: Attendance_Leave!$H$2:$H$501
Name A_WFH: Attendance_Leave!$L$2:$L$501
Name AsOf: Settings!$B$4
Name BandLevels: Settings!$A$14:$A$20
Name BandMax: Settings!$E$14:$E$20
Name BandMid: Settings!$D$14:$D$20
Name BandMin: Settings!$C$14:$C$20
Name C_Bonus: Compensation!$P$2:$P$501
Name C_Compa: Compensation!$J$2:$J$501
Name C_CTC: Compensation!$F$2:$F$501
Name C_Dept: Compensation!$C$2:$C$501
Name C_Hike: Compensation!$M$2:$M$501
Name C_Level: Compensation!$D$2:$D$501
Name C_Pos: Compensation!$K$2:$K$501
Name C_Rev: Compensation!$N$2:$N$501
Name C_Status: Compensation!$E$2:$E$501
Name CompaThreshold: Settings!$B$9
Name DeptList: Settings!$A$23:$A$33
Name E_Cat: Engagement!$O$2:$O$501
Name E_Dept: Engagement!$C$2:$C$501
Name E_Dim1: Engagement!$G$2:$G$501
Name E_Dim2: Engagement!$H$2:$H$501
Name E_Dim3: Engagement!$I$2:$I$501
Name E_Dim4: Engagement!$J$2:$J$501
Name E_Dim5: Engagement!$K$2:$K$501
Name E_Dim6: Engagement!$L$2:$L$501
Name E_eNPS: Engagement!$N$2:$N$501
Name E_Overall: Engagement!$M$2:$M$501
Name E_Rating: Engagement!$P$2:$P$501
Name E_Risk: Engagement!$S$2:$S$501
Name E_Status: Engagement!$E$2:$E$501
Name E_Survey: Engagement!$F$2:$F$501
Name EmpList: OFFSET(Calc_Engine!$J$2,0,0,MAX(1,COUNT(Calc_Engine!$H$2:$H$501)),1)
Name EngThreshold: Settings!$B$8
Name M_Dept: Employee_Master!$I$2:$I$501
Name M_DOJ: Employee_Master!$M$2:$M$501
Name M_Email: Employee_Master!$C$2:$C$501
Name M_Exit: Employee_Master!$P$2:$P$501
Name M_Gender: Employee_Master!$J$2:$J$501
Name M_ID: Employee_Master!$A$2:$A$501
Name M_Level: Employee_Master!$G$2:$G$501
Name M_LevelNo: Employee_Master!$H$2:$H$501
Name M_Loc: Employee_Master!$K$2:$K$501
Name M_Mgr: Employee_Master!$D$2:$D$501
Name M_Name: Employee_Master!$B$2:$B$501
Name M_Reports: Employee_Master!$S$2:$S$501
Name M_Status: Employee_Master!$O$2:$O$501
Name M_TBand: Employee_Master!$R$2:$R$501
Name M_Tenure: Employee_Master!$Q$2:$Q$501
Name M_Title: Employee_Master!$F$2:$F$501
Name M_Type: Employee_Master!$L$2:$L$501
Name MaxLvl: Settings!$B$7
Name MinRating: Settings!$B$5

Sheet Read_Me
B1: HR Analytics Showcase Workbook
B2: Built by Sonali K · Excel formulas, named ranges, dynamic dropdowns, conditional formatting, charts and VBA macros · all data is fictional
B5: HOW TO USE
B6: 1. Dashboard | C6: Pick a Department in the yellow box (or All Departments for the whole organisation). All 21 KPI tiles, 12 charts, the 9-box grid and the scorecard recalculate instantly.
B7: 2. Employee profile | C7: Pick an Employee in the second yellow box. The list only shows people in the selected department. The profile card pulls data from all eight data sheets.
B8: 3. Employee_Explorer | C8: Lists every employee in the selected department with key metrics. Filter or sort with the header arrows.
B9: 4. Settings | C9: Change the promotion rules, pay bands, flight-risk thresholds or the as-of date. Every formula uses these values.
B10: 5. Macros (optional) | C10: Import HR_Dashboard_Macros.bas (Alt+F11 > File > Import File), save as .xlsm, then run BuildDashboardButtons once to add buttons. Macros add: next/previous employee, search by name, promotion list, department report export, flight-risk list, PDF export and reset.
B12: SHEETS
B13: Employee_Master | C13: 500 employees: ID, name, email, manager, manager ID, designation, level, department, gender, location, type, joining date, age. Status, exit date, tenure and direct reports are formulas.
B14: Performance | C14: Rating (1-5), label, previous rating and trend, goals achieved, competency, potential, 9-box category, time in level and a rules-based Promotion Eligibility with the reason.
B15: Compensation | C15: Annual CTC against level pay bands, compa-ratio, band position, increment %, revised CTC, bonus and ESOP eligibility.
B16: Attendance_Leave | C16: Working days, planned/sick/unplanned leave, attendance %, WFH, late marks, overtime and an absence flag.
B17: Training | C17: Programs, courses, hours, cost, assessment score, POSH and InfoSec completion, compliance status, certifications.
B18: Engagement | C18: Six survey dimensions, overall engagement, eNPS and category, plus a formula-based flight-risk score.
B19: Exits_Attrition | C19: 64 exits in the last 12 months: type, reason, regrettable loss, notice, rehire eligibility, exit interview.
B20: Recruitment | C20: 140 requisitions: funnel (applicants to offers), status, source, time to fill, offer acceptance and cost per hire.
B21: Calc_Engine | C21: Behind-the-scenes helper: selection criteria, the filtered employee list for the dropdown, and the data behind every chart.
B23: SKILLS SHOWN
B24: Excel techniques | C24: INDEX/MATCH lookups across sheets, COUNTIFS/AVERAGEIFS/SUMIFS with a wildcard 'All' filter, 60+ named ranges, dependent dropdown via OFFSET, 9-box matrix lookup, dynamic chart titles, conditional formatting (colour scales, data bars, formula rules), single-parameter model in Settings.
B25: HR analytics | C25: Headcount, attrition (average-headcount basis), regrettable loss, hiring funnel and source effectiveness, time to fill, pay equity (compa-ratio), promotion readiness, talent 9-box, engagement and eNPS, flight-risk scoring, compliance training coverage.
B27: COLOUR KEY
B28: Blue text / yellow fill | C28: Inputs you can change.
B29: Teal column headers | C29: Columns calculated by formulas (do not type over them).
B30: Green text | C30: Values pulled from another sheet.

Sheet Dashboard
B1: HR ANALYTICS DASHBOARD
B2: =" SampleCorp (fictional sample data) · 500 employees · As of "&TEXT(AsOf,"dd-mmm-yyyy")&" · Viewing: "&SelLabel -> SampleCorp (fictional sample data) · 500 employees · As of 30-Sep-2026 · Viewing: All Departments
B4: Department ▸ | D4: All Departments | H4: Employee ▸ | J4: EMP1001 | Vidya Kulkarni | O4: Pick a department, then an employee. Every tile, chart and the profile card update instantly (no macro needed).
B5: Macro buttons appear on this strip after you import HR_Dashboard_Macros.bas and run BuildDashboardButtons once (see Read_Me).
B6: Total Employees (12M) | E6: Active Headcount | H6: Exits (Last 12M) | K6: Attrition Rate (12M) | N6: New Hires (12M) | Q6: Avg Tenure (Yrs) | T6: Female Representation
B7: =COUNTIFS(M_Dept,SelCrit) -> 500 | E7: =COUNTIFS(M_Dept,SelCrit,M_Status,"Active") -> 436 | H7: =COUNTIFS(X_Dept,SelCrit) -> 64 | K7: =IFERROR(COUNTIFS(X_Dept,SelCrit)/((COUNTIFS(M_Dept,SelCrit,M_DOJ,"<"&PeriodStart)+COUNTIFS(M_Dept,SelCrit,M_Status,"Active"))/2),0) -> 0.15705521 | N7: =COUNTIFS(M_Dept,SelCrit,M_DOJ,">="&PeriodStart) -> 121 | Q7: =IFERROR(AVERAGEIFS(M_Tenure,M_Dept,SelCrit,M_Status,"Active"),0) -> 2.6311927 | T7: =IFERROR(COUNTIFS(M_Dept,SelCrit,M_Gender,"Female",M_Status,"Active")/COUNTIFS(M_Dept,SelCrit,M_Status,"Active"),0) -> 0.46559633
B8: ="Includes "&COUNTIFS(X_Dept,SelCrit)&" who exited" -> Includes 64 who exited | E8: ="Contract staff: "&COUNTIFS(M_Dept,SelCrit,M_Status,"Active",M_Type,"Contract") -> Contract staff: 28 | H8: ="Voluntary "&COUNTIFS(X_Dept,SelCrit,X_Type,"Voluntary")&" · Regrettable "&COUNTIFS(X_Dept,SelCrit,X_Regret,"Yes") -> Voluntary 52 · Regrettable 28 | K8: ="Exits ÷ average headcount" -> Exits ÷ average headcount | N8: ="Joined since "&TEXT(PeriodStart,"dd-mmm-yy") -> Joined since 30-Sep-25 | Q8: ="Under 1 year: "&COUNTIFS(M_Dept,SelCrit,M_TBand,"Under 1 Yr",M_Status,"Active")&" people" -> Under 1 year: 101 people | T8: ="Women "&COUNTIFS(M_Dept,SelCrit,M_Gender,"Female",M_Status,"Active")&" · Men "&COUNTIFS(M_Dept,SelCrit,M_Gender,"Male",M_Status,"Active") -> Women 203 · Men 233
B10: Avg Performance Rating | E10: Promotion Eligible | H10: High Performers (4-5) | K10: Avg Annual CTC (₹ L) | N10: Avg Compa-Ratio | Q10: Attendance Rate | T10: Employee NPS (eNPS)
B11: =IFERROR(AVERAGEIFS(P_Rating,P_Dept,SelCrit),0) -> 3.234 | E11: =COUNTIFS(P_Dept,SelCrit,P_Elig,"Eligible") -> 82 | H11: =IFERROR(COUNTIFS(P_Dept,SelCrit,P_Rating,">=4",P_Status,"Active")/COUNTIFS(M_Dept,SelCrit,M_Status,"Active"),0) -> 0.39220183 | K11: =IFERROR(AVERAGEIFS(C_CTC,C_Dept,SelCrit,C_Status,"Active")/100000,0) -> 16.457752 | N11: =IFERROR(AVERAGEIFS(C_Compa,C_Dept,SelCrit,C_Status,"Active"),0) -> 0.9687156 | Q11: =IFERROR(AVERAGEIFS(A_Att,A_Dept,SelCrit,A_Status,"Active"),0) -> 0.89245868 | T11: =IFERROR((COUNTIFS(E_Dept,SelCrit,E_Cat,"Promoter",E_Status,"Active",E_Survey,"Yes")-COUNTIFS(E_Dept,SelCrit,E_Cat,"Detractor",E_Status,"Active",E_Survey,"Yes"))/COUNTIFS(E_Dept,SelCrit,E_Status,"Active",E_Survey,"Yes")*100,0) -> 22.727273
B12: ="Low performers (1-2): "&COUNTIFS(P_Dept,SelCrit,P_Rating,"<=2") -> Low performers (1-2): 95 | E12: =TEXT(IFERROR(COUNTIFS(P_Dept,SelCrit,P_Elig,"Eligible")/COUNTIFS(M_Dept,SelCrit,M_Status,"Active"),0),"0.0%")&" of active headcount" -> 18.8% of active headcount | H12: =COUNTIFS(P_Dept,SelCrit,P_Rating,">=4",P_Status,"Active")&" active employees" -> 171 active employees | K12: ="Annual payroll ₹"&TEXT(SUMIFS(C_CTC,C_Dept,SelCrit,C_Status,"Active")/10000000,"0.00")&" Cr" -> Annual payroll ₹71.76 Cr | N12: ="Below band: "&COUNTIFS(C_Dept,SelCrit,C_Pos,"Below Band",C_Status,"Active")&" · Above: "&COUNTIFS(C_Dept,SelCrit,C_Pos,"Above Band",C_Status,"Active") -> Below band: 10 · Above: 6 | Q12: ="Avg unplanned leave "&TEXT(IFERROR(AVERAGEIFS(A_Unpl,A_Dept,SelCrit,A_Status,"Active"),0),"0.0")&" days" -> Avg unplanned leave 3.1 days | T12: ="Promoters "&COUNTIFS(E_Dept,SelCrit,E_Cat,"Promoter",E_Status,"Active",E_Survey,"Yes")&" · Detractors "&COUNTIFS(E_Dept,SelCrit,E_Cat,"Detractor",E_Status,"Active",E_Survey,"Yes") -> Promoters 148 · Detractors 63
B14: Avg Training Hours | E14: Compliance Training | H14: Engagement Score (/5) | K14: High Flight Risk | N14: Open Requisitions | Q14: Avg Time to Fill (Days) | T14: Offer Acceptance
B15: =IFERROR(AVERAGEIFS(T_Hours,T_Dept,SelCrit),0) -> 27.746 | E15: =IFERROR(COUNTIFS(T_Dept,SelCrit,T_Comp,"Compliant",T_Status,"Active")/COUNTIFS(M_Dept,SelCrit,M_Status,"Active"),0) -> 0.86926606 | H15: =IFERROR(AVERAGEIFS(E_Overall,E_Dept,SelCrit,E_Status,"Active"),0) -> 3.2512844 | K15: =COUNTIFS(E_Dept,SelCrit,E_Risk,"High") -> 27 | N15: =COUNTIFS(R_Dept,SelCrit,R_Status,"Open") -> 43 | Q15: =IFERROR(AVERAGEIFS(R_TTF,R_Dept,SelCrit,R_Status,"Filled"),0) -> 41.025974 | T15: =IFERROR(SUMIFS(R_Acc,R_Dept,SelCrit)/SUMIFS(R_Offers,R_Dept,SelCrit),0) -> 0.63114754
B16: ="Spend ₹"&TEXT(SUMIFS(T_Cost,T_Dept,SelCrit)/100000,"0.0")&" L · "&TEXT(SUMIFS(T_Hours,T_Dept,SelCrit),"#,##0")&" hrs" -> Spend ₹98.6 L · 13,873 hrs | E16: ="Pending (POSH / InfoSec): "&COUNTIFS(T_Dept,SelCrit,T_Comp,"Pending",T_Status,"Active") -> Pending (POSH / InfoSec): 57 | H16: ="Survey participation "&TEXT(IFERROR(COUNTIFS(E_Dept,SelCrit,E_Survey,"Yes",E_Status,"Active")/COUNTIFS(M_Dept,SelCrit,M_Status,"Active"),0),"0%") -> Survey participation 86% | K16: ="Of which rated 4-5: "&COUNTIFS(E_Dept,SelCrit,E_Risk,"High",E_Rating,">=4") -> Of which rated 4-5: 13 | N16: ="High priority: "&COUNTIFS(R_Dept,SelCrit,R_Status,"Open",R_Prio,"High")&" · On hold: "&COUNTIFS(R_Dept,SelCrit,R_Status,"On Hold") -> High priority: 10 · On hold: 11 | Q16: ="Filled requisitions: "&COUNTIFS(R_Dept,SelCrit,R_Status,"Filled") -> Filled requisitions: 77 | T16: ="Avg cost per hire ₹"&TEXT(IFERROR(AVERAGEIFS(R_Cost,R_Dept,SelCrit,R_Status,"Filled"),0),"#,##0") -> Avg cost per hire ₹29,143
B19: EMPLOYEE PROFILE | M19: 9-BOX TALENT GRID (active employees in view)
B20: Employee ID | D20: =SelEmp -> EMP1001 | G20: Rating | I20: =INDEX(P_Rating,SelRow)&" - "&INDEX(P_Label,SelRow) -> 5 - Outstanding | N20: Low Potential | Q20: Medium Potential | T20: High Potential
B21: Name | D21: =INDEX(M_Name,SelRow) -> Vidya Kulkarni | G21: Previous · Trend | I21: =INDEX(P_Prev,SelRow)&" · "&INDEX(P_Trend,SelRow) -> 5 · Stable | M21: High Performance | N21: ="Trusted Professional"&CHAR(10)&COUNTIFS(P_Dept,SelCrit,P_9Box,"Trusted Professional",P_Status,"Active")&" people" -> Trusted Professional 12 people | Q21: ="High Performer"&CHAR(10)&COUNTIFS(P_Dept,SelCrit,P_9Box,"High Performer",P_Status,"Active")&" people" -> High Performer 77 people | T21: ="Star"&CHAR(10)&COUNTIFS(P_Dept,SelCrit,P_9Box,"Star",P_Status,"Active")&" people" -> Star 82 people
B22: Email | D22: =INDEX(M_Email,SelRow) -> vidya.kulkarni@samplecorp.in | G22: Goals Achieved | I22: =INDEX(P_Goals,SelRow) -> 1.1
B23: Designation | D23: =INDEX(M_Title,SelRow) -> Head of People | G23: Potential · 9-Box | I23: =INDEX(P_Pot,SelRow)&" · "&INDEX(P_9Box,SelRow) -> High · Star
B24: Level | D24: =INDEX(M_Level,SelRow) -> L7 | G24: Promotion Eligibility | I24: =INDEX(P_Elig,SelRow) -> Not Eligible | M24: Mid Performance | N24: ="Effective Contributor"&CHAR(10)&COUNTIFS(P_Dept,SelCrit,P_9Box,"Effective Contributor",P_Status,"Active")&" people" -> Effective Contributor 35 people | Q24: ="Core Player"&CHAR(10)&COUNTIFS(P_Dept,SelCrit,P_9Box,"Core Player",P_Status,"Active")&" people" -> Core Player 115 people | T24: ="Future Star"&CHAR(10)&COUNTIFS(P_Dept,SelCrit,P_9Box,"Future Star",P_Status,"Active")&" people" -> Future Star 33 people
B25: Department | D25: =INDEX(M_Dept,SelRow) -> Human Resources | G25: Reason | I25: =INDEX(P_Reason,SelRow) -> Already at top level
B26: Manager | D26: =INDEX(M_Mgr,SelRow) -> Arvind Rao (CEO) | G26: Annual CTC | I26: =INDEX(C_CTC,SelRow) -> 7632000
B27: Location | D27: =INDEX(M_Loc,SelRow) -> Bengaluru | G27: Compa-Ratio · Band | I27: =TEXT(INDEX(C_Compa,SelRow),"0.00")&" · "&INDEX(C_Pos,SelRow) -> 0.93 · Within Band | M27: Low Performance | N27: ="Underperformer"&CHAR(10)&COUNTIFS(P_Dept,SelCrit,P_9Box,"Underperformer",P_Status,"Active")&" people" -> Underperformer 41 people | Q27: ="Inconsistent Player"&CHAR(10)&COUNTIFS(P_Dept,SelCrit,P_9Box,"Inconsistent Player",P_Status,"Active")&" people" -> Inconsistent Player 35 people | T27: ="Rough Diamond"&CHAR(10)&COUNTIFS(P_Dept,SelCrit,P_9Box,"Rough Diamond",P_Status,"Active")&" people" -> Rough Diamond 6 people
B28: Date of Joining | D28: =INDEX(M_DOJ,SelRow) -> 42718 | G28: Attendance · Leave | I28: =TEXT(INDEX(A_Att,SelRow),"0.0%")&" · "&INDEX(A_Unpl,SelRow)&" days" -> 92.8% · 3 days
B29: Tenure (Yrs) | D29: =INDEX(M_Tenure,SelRow) -> 9.8 | G29: Training · Compliance | I29: =INDEX(T_Hours,SelRow)&" hrs · "&INDEX(T_Comp,SelRow) -> 7 hrs · Compliant
B30: Status | D30: =INDEX(M_Status,SelRow) -> Active | G30: Engagement · eNPS | I30: =TEXT(INDEX(E_Overall,SelRow),"0.00")&" /5 · eNPS "&INDEX(E_eNPS,SelRow)&" ("&INDEX(E_Cat,SelRow)&")" -> 3.73 /5 · eNPS 10 (Promoter) | M30: Grid counts active employees in the selected department. The selected employee's box turns bold italic with an amber outline. Performance band: High = rating 4-5, Mid = 3, Low = 1-2; potential comes from the Performance sheet.
B31: Direct Reports | D31: =INDEX(M_Reports,SelRow) -> 1 | G31: Flight Risk | I31: =INDEX(E_Risk,SelRow) -> Low
B32: =Calc_Engine!$B$7
B34: WORKFORCE ANALYTICS (charts follow the department selection)
B104: DEPARTMENT SCORECARD (all departments; selected department highlighted)
B105: Department | D105: Active HC | E105: Exits 12M | F105: Attrition % | G105: Avg Rating | H105: Promo Eligible | I105: Avg CTC (₹ L) | J105: Avg Compa | K105: Attendance % | L105: Engagement | M105: eNPS | N105: High Flight Risk | O105: Open Reqs | P105: Avg Time to Fill | Q105: Female % | R105: Avg Training Hrs | S105: High Perf % | T105: Compliance % | U105: Avg Tenure
B106: Engineering | D106: =COUNTIFS(M_Dept,$B$106,M_Status,"Active") -> 97 | E106: =COUNTIFS(X_Dept,$B$106) -> 13 | F106: =IFERROR(COUNTIFS(X_Dept,$B$106)/((COUNTIFS(M_Dept,$B$106,M_DOJ,"<"&PeriodStart)+COUNTIFS(M_Dept,$B$106,M_Status,"Active"))/2),0) -> 0.14285714 | G106: =IFERROR(AVERAGEIFS(P_Rating,P_Dept,$B$106),0) -> 3.2818182 | H106: =COUNTIFS(P_Dept,$B$106,P_Elig,"Eligible") -> 14 | I106: =IFERROR(AVERAGEIFS(C_CTC,C_Dept,$B$106,C_Status,"Active")/100000,0) -> 18.470619 | J106: =IFERROR(AVERAGEIFS(C_Compa,C_Dept,$B$106,C_Status,"Active"),0) -> 1.1612371 | K106: =IFERROR(AVERAGEIFS(A_Att,A_Dept,$B$106,A_Status,"Active"),0) -> 0.89673349 | L106: =IFERROR(AVERAGEIFS(E_Overall,E_Dept,$B$106,E_Status,"Active"),0) -> 3.235567 | M106: =IFERROR((COUNTIFS(E_Dept,$B$106,E_Cat,"Promoter",E_Status,"Active",E_Survey,"Yes")-COUNTIFS(E_Dept,$B$106,E_Cat,"Detractor",E_Status,"Active",E_Survey,"Yes"))/COUNTIFS(E_Dept,$B$106,E_Status,"Active",E_Survey,"Yes")*100,0) -> 16.470588 | N106: =COUNTIFS(E_Dept,$B$106,E_Risk,"High") -> 3 | O106: =COUNTIFS(R_Dept,$B$106,R_Status,"Open") -> 8 | P106: =IFERROR(AVERAGEIFS(R_TTF,R_Dept,$B$106,R_Status,"Filled"),0) -> 37.941176 | Q106: =IFERROR(COUNTIFS(M_Dept,$B$106,M_Gender,"Female",M_Status,"Active")/COUNTIFS(M_Dept,$B$106,M_Status,"Active"),0) -> 0.44329897 | R106: =IFERROR(AVERAGEIFS(T_Hours,T_Dept,$B$106),0) -> 27.681818 | S106: =IFERROR(COUNTIFS(P_Dept,$B$106,P_Rating,">=4",P_Status,"Active")/COUNTIFS(M_Dept,$B$106,M_Status,"Active"),0) -> 0.40206186 | T106: =IFERROR(COUNTIFS(T_Dept,$B$106,T_Comp,"Compliant",T_Status,"Active")/COUNTIFS(M_Dept,$B$106,M_Status,"Active"),0) -> 0.89690722 | U106: =IFERROR(AVERAGEIFS(M_Tenure,M_Dept,$B$106,M_Status,"Active"),0) -> 2.7257732
B107: Operations | D107: =COUNTIFS(M_Dept,$B$107,M_Status,"Active") -> 77 | E107: =COUNTIFS(X_Dept,$B$107) -> 13 | F107: =IFERROR(COUNTIFS(X_Dept,$B$107)/((COUNTIFS(M_Dept,$B$107,M_DOJ,"<"&PeriodStart)+COUNTIFS(M_Dept,$B$107,M_Status,"Active"))/2),0) -> 0.17449664 | G107: =IFERROR(AVERAGEIFS(P_Rating,P_Dept,$B$107),0) -> 3.3444444 | H107: =COUNTIFS(P_Dept,$B$107,P_Elig,"Eligible") -> 16 | I107: =IFERROR(AVERAGEIFS(C_CTC,C_Dept,$B$107,C_Status,"Active")/100000,0) -> 13.135714 | J107: =IFERROR(AVERAGEIFS(C_Compa,C_Dept,$B$107,C_Status,"Active"),0) -> 0.83350649 | K107: =IFERROR(AVERAGEIFS(A_Att,A_Dept,$B$107,A_Status,"Active"),0) -> 0.89956698 | L107: =IFERROR(AVERAGEIFS(E_Overall,E_Dept,$B$107,E_Status,"Active"),0) -> 3.2798701 | M107: =IFERROR((COUNTIFS(E_Dept,$B$107,E_Cat,"Promoter",E_Status,"Active",E_Survey,"Yes")-COUNTIFS(E_Dept,$B$107,E_Cat,"Detractor",E_Status,"Active",E_Survey,"Yes"))/COUNTIFS(E_Dept,$B$107,E_Status,"Active",E_Survey,"Yes")*100,0) -> 23.809524 | N107: =COUNTIFS(E_Dept,$B$107,E_Risk,"High") -> 8 | O107: =COUNTIFS(R_Dept,$B$107,R_Status,"Open") -> 8 | P107: =IFERROR(AVERAGEIFS(R_TTF,R_Dept,$B$107,R_Status,"Filled"),0) -> 42 | Q107: =IFERROR(COUNTIFS(M_Dept,$B$107,M_Gender,"Female",M_Status,"Active")/COUNTIFS(M_Dept,$B$107,M_Status,"Active"),0) -> 0.31168831 | R107: =IFERROR(AVERAGEIFS(T_Hours,T_Dept,$B$107),0) -> 24.922222 | S107: =IFERROR(COUNTIFS(P_Dept,$B$107,P_Rating,">=4",P_Status,"Active")/COUNTIFS(M_Dept,$B$107,M_Status,"Active"),0) -> 0.41558442 | T107: =IFERROR(COUNTIFS(T_Dept,$B$107,T_Comp,"Compliant",T_Status,"Active")/COUNTIFS(M_Dept,$B$107,M_Status,"Active"),0) -> 0.85714286 | U107: =IFERROR(AVERAGEIFS(M_Tenure,M_Dept,$B$107,M_Status,"Active"),0) -> 2.8272727
B108: Customer Support | D108: =COUNTIFS(M_Dept,$B$108,M_Status,"Active") -> 61 | E108: =COUNTIFS(X_Dept,$B$108) -> 9 | F108: =IFERROR(COUNTIFS(X_Dept,$B$108)/((COUNTIFS(M_Dept,$B$108,M_DOJ,"<"&PeriodStart)+COUNTIFS(M_Dept,$B$108,M_Status,"Active"))/2),0) -> 0.15929204 | G108: =IFERROR(AVERAGEIFS(P_Rating,P_Dept,$B$108),0) -> 3.2285714 | H108: =COUNTIFS(P_Dept,$B$108,P_Elig,"Eligible") -> 13 | I108: =IFERROR(AVERAGEIFS(C_CTC,C_Dept,$B$108,C_Status,"Active")/100000,0) -> 12.293279 | J108: =IFERROR(AVERAGEIFS(C_Compa,C_Dept,$B$108,C_Status,"Active"),0) -> 0.73180328 | K108: =IFERROR(AVERAGEIFS(A_Att,A_Dept,$B$108,A_Status,"Active"),0) -> 0.8934168 | L108: =IFERROR(AVERAGEIFS(E_Overall,E_Dept,$B$108,E_Status,"Active"),0) -> 3.3244262 | M108: =IFERROR((COUNTIFS(E_Dept,$B$108,E_Cat,"Promoter",E_Status,"Active",E_Survey,"Yes")-COUNTIFS(E_Dept,$B$108,E_Cat,"Detractor",E_Status,"Active",E_Survey,"Yes"))/COUNTIFS(E_Dept,$B$108,E_Status,"Active",E_Survey,"Yes")*100,0) -> 31.372549 | N108: =COUNTIFS(E_Dept,$B$108,E_Risk,"High") -> 7 | O108: =COUNTIFS(R_Dept,$B$108,R_Status,"Open") -> 6 | P108: =IFERROR(AVERAGEIFS(R_TTF,R_Dept,$B$108,R_Status,"Filled"),0) -> 38.166667 | Q108: =IFERROR(COUNTIFS(M_Dept,$B$108,M_Gender,"Female",M_Status,"Active")/COUNTIFS(M_Dept,$B$108,M_Status,"Active"),0) -> 0.49180328 | R108: =IFERROR(AVERAGEIFS(T_Hours,T_Dept,$B$108),0) -> 27.771429 | S108: =IFERROR(COUNTIFS(P_Dept,$B$108,P_Rating,">=4",P_Status,"Active")/COUNTIFS(M_Dept,$B$108,M_Status,"Active"),0) -> 0.37704918 | T108: =IFERROR(COUNTIFS(T_Dept,$B$108,T_Comp,"Compliant",T_Status,"Active")/COUNTIFS(M_Dept,$B$108,M_Status,"Active"),0) -> 0.85245902 | U108: =IFERROR(AVERAGEIFS(M_Tenure,M_Dept,$B$108,M_Status,"Active"),0) -> 2.3278689
B109: Sales | D109: =COUNTIFS(M_Dept,$B$109,M_Status,"Active") -> 51 | E109: =COUNTIFS(X_Dept,$B$109) -> 9 | F109: =IFERROR(COUNTIFS(X_Dept,$B$109)/((COUNTIFS(M_Dept,$B$109,M_DOJ,"<"&PeriodStart)+COUNTIFS(M_Dept,$B$109,M_Status,"Active"))/2),0) -> 0.18556701 | G109: =IFERROR(AVERAGEIFS(P_Rating,P_Dept,$B$109),0) -> 3.1 | H109: =COUNTIFS(P_Dept,$B$109,P_Elig,"Eligible") -> 9 | I109: =IFERROR(AVERAGEIFS(C_CTC,C_Dept,$B$109,C_Status,"Active")/100000,0) -> 15.844902 | J109: =IFERROR(AVERAGEIFS(C_Compa,C_Dept,$B$109,C_Status,"Active"),0) -> 0.92980392 | K109: =IFERROR(AVERAGEIFS(A_Att,A_Dept,$B$109,A_Status,"Active"),0) -> 0.89352406 | L109: =IFERROR(AVERAGEIFS(E_Overall,E_Dept,$B$109,E_Status,"Active"),0) -> 3.2901961 | M109: =IFERROR((COUNTIFS(E_Dept,$B$109,E_Cat,"Promoter",E_Status,"Active",E_Survey,"Yes")-COUNTIFS(E_Dept,$B$109,E_Cat,"Detractor",E_Status,"Active",E_Survey,"Yes"))/COUNTIFS(E_Dept,$B$109,E_Status,"Active",E_Survey,"Yes")*100,0) -> 18.604651 | N109: =COUNTIFS(E_Dept,$B$109,E_Risk,"High") -> 4 | O109: =COUNTIFS(R_Dept,$B$109,R_Status,"Open") -> 4 | P109: =IFERROR(AVERAGEIFS(R_TTF,R_Dept,$B$109,R_Status,"Filled"),0) -> 42.2 | Q109: =IFERROR(COUNTIFS(M_Dept,$B$109,M_Gender,"Female",M_Status,"Active")/COUNTIFS(M_Dept,$B$109,M_Status,"Active"),0) -> 0.47058824 | R109: =IFERROR(AVERAGEIFS(T_Hours,T_Dept,$B$109),0) -> 25.033333 | S109: =IFERROR(COUNTIFS(P_Dept,$B$109,P_Rating,">=4",P_Status,"Active")/COUNTIFS(M_Dept,$B$109,M_Status,"Active"),0) -> 0.39215686 | T109: =IFERROR(COUNTIFS(T_Dept,$B$109,T_Comp,"Compliant",T_Status,"Active")/COUNTIFS(M_Dept,$B$109,M_Status,"Active"),0) -> 0.88235294 | U109: =IFERROR(AVERAGEIFS(M_Tenure,M_Dept,$B$109,M_Status,"Active"),0) -> 2.6705882
B110: Product | D110: =COUNTIFS(M_Dept,$B$110,M_Status,"Active") -> 33 | E110: =COUNTIFS(X_Dept,$B$110) -> 2 | F110: =IFERROR(COUNTIFS(X_Dept,$B$110)/((COUNTIFS(M_Dept,$B$110,M_DOJ,"<"&PeriodStart)+COUNTIFS(M_Dept,$B$110,M_Status,"Active"))/2),0) -> 0.074074074 | G110: =IFERROR(AVERAGEIFS(P_Rating,P_Dept,$B$110),0) -> 3.3714286 | H110: =COUNTIFS(P_Dept,$B$110,P_Elig,"Eligible") -> 7 | I110: =IFERROR(AVERAGEIFS(C_CTC,C_Dept,$B$110,C_Status,"Active")/100000,0) -> 19.370909 | J110: =IFERROR(AVERAGEIFS(C_Compa,C_Dept,$B$110,C_Status,"Active"),0) -> 1.1133333 | K110: =IFERROR(AVERAGEIFS(A_Att,A_Dept,$B$110,A_Status,"Active"),0) -> 0.87303214 | L110: =IFERROR(AVERAGEIFS(E_Overall,E_Dept,$B$110,E_Status,"Active"),0) -> 3.2675758 | M110: =IFERROR((COUNTIFS(E_Dept,$B$110,E_Cat,"Promoter",E_Status,"Active",E_Survey,"Yes")-COUNTIFS(E_Dept,$B$110,E_Cat,"Detractor",E_Status,"Active",E_Survey,"Yes"))/COUNTIFS(E_Dept,$B$110,E_Status,"Active",E_Survey,"Yes")*100,0) -> 27.586207 | N110: =COUNTIFS(E_Dept,$B$110,E_Risk,"High") -> 0 | O110: =COUNTIFS(R_Dept,$B$110,R_Status,"Open") -> 3 | P110: =IFERROR(AVERAGEIFS(R_TTF,R_Dept,$B$110,R_Status,"Filled"),0) -> 49.166667 | Q110: =IFERROR(COUNTIFS(M_Dept,$B$110,M_Gender,"Female",M_Status,"Active")/COUNTIFS(M_Dept,$B$110,M_Status,"Active"),0) -> 0.48484848 | R110: =IFERROR(AVERAGEIFS(T_Hours,T_Dept,$B$110),0) -> 25.971429 | S110: =IFERROR(COUNTIFS(P_Dept,$B$110,P_Rating,">=4",P_Status,"Active")/COUNTIFS(M_Dept,$B$110,M_Status,"Active"),0) -> 0.42424242 | T110: =IFERROR(COUNTIFS(T_Dept,$B$110,T_Comp,"Compliant",T_Status,"Active")/COUNTIFS(M_Dept,$B$110,M_Status,"Active"),0) -> 0.81818182 | U110: =IFERROR(AVERAGEIFS(M_Tenure,M_Dept,$B$110,M_Status,"Active"),0) -> 2.230303
B111: Marketing | D111: =COUNTIFS(M_Dept,$B$111,M_Status,"Active") -> 27 | E111: =COUNTIFS(X_Dept,$B$111) -> 3 | F111: =IFERROR(COUNTIFS(X_Dept,$B$111)/((COUNTIFS(M_Dept,$B$111,M_DOJ,"<"&PeriodStart)+COUNTIFS(M_Dept,$B$111,M_Status,"Active"))/2),0) -> 0.11764706 | G111: =IFERROR(AVERAGEIFS(P_Rating,P_Dept,$B$111),0) -> 3.0666667 | H111: =COUNTIFS(P_Dept,$B$111,P_Elig,"Eligible") -> 3 | I111: =IFERROR(AVERAGEIFS(C_CTC,C_Dept,$B$111,C_Status,"Active")/100000,0) -> 15.875185 | J111: =IFERROR(AVERAGEIFS(C_Compa,C_Dept,$B$111,C_Status,"Active"),0) -> 0.93037037 | K111: =IFERROR(AVERAGEIFS(A_Att,A_Dept,$B$111,A_Status,"Active"),0) -> 0.90353846 | L111: =IFERROR(AVERAGEIFS(E_Overall,E_Dept,$B$111,E_Status,"Active"),0) -> 3.2148148 | M111: =IFERROR((COUNTIFS(E_Dept,$B$111,E_Cat,"Promoter",E_Status,"Active",E_Survey,"Yes")-COUNTIFS(E_Dept,$B$111,E_Cat,"Detractor",E_Status,"Active",E_Survey,"Yes"))/COUNTIFS(E_Dept,$B$111,E_Status,"Active",E_Survey,"Yes")*100,0) -> 19.230769 | N111: =COUNTIFS(E_Dept,$B$111,E_Risk,"High") -> 1 | O111: =COUNTIFS(R_Dept,$B$111,R_Status,"Open") -> 4 | P111: =IFERROR(AVERAGEIFS(R_TTF,R_Dept,$B$111,R_Status,"Filled"),0) -> 40.428571 | Q111: =IFERROR(COUNTIFS(M_Dept,$B$111,M_Gender,"Female",M_Status,"Active")/COUNTIFS(M_Dept,$B$111,M_Status,"Active"),0) -> 0.51851852 | R111: =IFERROR(AVERAGEIFS(T_Hours,T_Dept,$B$111),0) -> 30.2 | S111: =IFERROR(COUNTIFS(P_Dept,$B$111,P_Rating,">=4",P_Status,"Active")/COUNTIFS(M_Dept,$B$111,M_Status,"Active"),0) -> 0.2962963 | T111: =IFERROR(COUNTIFS(T_Dept,$B$111,T_Comp,"Compliant",T_Status,"Active")/COUNTIFS(M_Dept,$B$111,M_Status,"Active"),0) -> 0.92592593 | U111: =IFERROR(AVERAGEIFS(M_Tenure,M_Dept,$B$111,M_Status,"Active"),0) -> 2.4925926
B112: Data & Analytics | D112: =COUNTIFS(M_Dept,$B$112,M_Status,"Active") -> 23 | E112: =COUNTIFS(X_Dept,$B$112) -> 7 | F112: =IFERROR(COUNTIFS(X_Dept,$B$112)/((COUNTIFS(M_Dept,$B$112,M_DOJ,"<"&PeriodStart)+COUNTIFS(M_Dept,$B$112,M_Status,"Active"))/2),0) -> 0.29787234 | G112: =IFERROR(AVERAGEIFS(P_Rating,P_Dept,$B$112),0) -> 3.2333333 | H112: =COUNTIFS(P_Dept,$B$112,P_Elig,"Eligible") -> 5 | I112: =IFERROR(AVERAGEIFS(C_CTC,C_Dept,$B$112,C_Status,"Active")/100000,0) -> 20.20087 | J112: =IFERROR(AVERAGEIFS(C_Compa,C_Dept,$B$112,C_Status,"Active"),0) -> 1.1282609 | K112: =IFERROR(AVERAGEIFS(A_Att,A_Dept,$B$112,A_Status,"Active"),0) -> 0.91148953 | L112: =IFERROR(AVERAGEIFS(E_Overall,E_Dept,$B$112,E_Status,"Active"),0) -> 3.3030435 | M112: =IFERROR((COUNTIFS(E_Dept,$B$112,E_Cat,"Promoter",E_Status,"Active",E_Survey,"Yes")-COUNTIFS(E_Dept,$B$112,E_Cat,"Detractor",E_Status,"Active",E_Survey,"Yes"))/COUNTIFS(E_Dept,$B$112,E_Status,"Active",E_Survey,"Yes")*100,0) -> 40 | N112: =COUNTIFS(E_Dept,$B$112,E_Risk,"High") -> 1 | O112: =COUNTIFS(R_Dept,$B$112,R_Status,"Open") -> 3 | P112: =IFERROR(AVERAGEIFS(R_TTF,R_Dept,$B$112,R_Status,"Filled"),0) -> 44 | Q112: =IFERROR(COUNTIFS(M_Dept,$B$112,M_Gender,"Female",M_Status,"Active")/COUNTIFS(M_Dept,$B$112,M_Status,"Active"),0) -> 0.47826087 | R112: =IFERROR(AVERAGEIFS(T_Hours,T_Dept,$B$112),0) -> 38.7 | S112: =IFERROR(COUNTIFS(P_Dept,$B$112,P_Rating,">=4",P_Status,"Active")/COUNTIFS(M_Dept,$B$112,M_Status,"Active"),0) -> 0.39130435 | T112: =IFERROR(COUNTIFS(T_Dept,$B$112,T_Comp,"Compliant",T_Status,"Active")/COUNTIFS(M_Dept,$B$112,M_Status,"Active"),0) -> 0.82608696 | U112: =IFERROR(AVERAGEIFS(M_Tenure,M_Dept,$B$112,M_Status,"Active"),0) -> 2.7130435
B113: Finance | D113: =COUNTIFS(M_Dept,$B$113,M_Status,"Active") -> 22 | E113: =COUNTIFS(X_Dept,$B$113) -> 3 | F113: =IFERROR(COUNTIFS(X_Dept,$B$113)/((COUNTIFS(M_Dept,$B$113,M_DOJ,"<"&PeriodStart)+COUNTIFS(M_Dept,$B$113,M_Status,"Active"))/2),0) -> 0.14285714 | G113: =IFERROR(AVERAGEIFS(P_Rating,P_Dept,$B$113),0) -> 3.52 | H113: =COUNTIFS(P_Dept,$B$113,P_Elig,"Eligible") -> 6 | I113: =IFERROR(AVERAGEIFS(C_CTC,C_Dept,$B$113,C_Status,"Active")/100000,0) -> 19.805909 | J113: =IFERROR(AVERAGEIFS(C_Compa,C_Dept,$B$113,C_Status,"Active"),0) -> 0.99636364 | K113: =IFERROR(AVERAGEIFS(A_Att,A_Dept,$B$113,A_Status,"Active"),0) -> 0.89310766 | L113: =IFERROR(AVERAGEIFS(E_Overall,E_Dept,$B$113,E_Status,"Active"),0) -> 3.1359091 | M113: =IFERROR((COUNTIFS(E_Dept,$B$113,E_Cat,"Promoter",E_Status,"Active",E_Survey,"Yes")-COUNTIFS(E_Dept,$B$113,E_Cat,"Detractor",E_Status,"Active",E_Survey,"Yes"))/COUNTIFS(E_Dept,$B$113,E_Status,"Active",E_Survey,"Yes")*100,0) -> 25 | N113: =COUNTIFS(E_Dept,$B$113,E_Risk,"High") -> 2 | O113: =COUNTIFS(R_Dept,$B$113,R_Status,"Open") -> 2 | P113: =IFERROR(AVERAGEIFS(R_TTF,R_Dept,$B$113,R_Status,"Filled"),0) -> 32 | Q113: =IFERROR(COUNTIFS(M_Dept,$B$113,M_Gender,"Female",M_Status,"Active")/COUNTIFS(M_Dept,$B$113,M_Status,"Active"),0) -> 0.63636364 | R113: =IFERROR(AVERAGEIFS(T_Hours,T_Dept,$B$113),0) -> 30.48 | S113: =IFERROR(COUNTIFS(P_Dept,$B$113,P_Rating,">=4",P_Status,"Active")/COUNTIFS(M_Dept,$B$113,M_Status,"Active"),0) -> 0.5 | T113: =IFERROR(COUNTIFS(T_Dept,$B$113,T_Comp,"Compliant",T_Status,"Active")/COUNTIFS(M_Dept,$B$113,M_Status,"Active"),0) -> 0.77272727 | U113: =IFERROR(AVERAGEIFS(M_Tenure,M_Dept,$B$113,M_Status,"Active"),0) -> 2.7727273
B114: Human Resources | D114: =COUNTIFS(M_Dept,$B$114,M_Status,"Active") -> 22 | E114: =COUNTIFS(X_Dept,$B$114) -> 3 | F114: =IFERROR(COUNTIFS(X_Dept,$B$114)/((COUNTIFS(M_Dept,$B$114,M_DOJ,"<"&PeriodStart)+COUNTIFS(M_Dept,$B$114,M_Status,"Active"))/2),0) -> 0.14285714 | G114: =IFERROR(AVERAGEIFS(P_Rating,P_Dept,$B$114),0) -> 3.08 | H114: =COUNTIFS(P_Dept,$B$114,P_Elig,"Eligible") -> 4 | I114: =IFERROR(AVERAGEIFS(C_CTC,C_Dept,$B$114,C_Status,"Active")/100000,0) -> 17.519545 | J114: =IFERROR(AVERAGEIFS(C_Compa,C_Dept,$B$114,C_Status,"Active"),0) -> 0.91772727 | K114: =IFERROR(AVERAGEIFS(A_Att,A_Dept,$B$114,A_Status,"Active"),0) -> 0.89434223 | L114: =IFERROR(AVERAGEIFS(E_Overall,E_Dept,$B$114,E_Status,"Active"),0) -> 3.1522727 | M114: =IFERROR((COUNTIFS(E_Dept,$B$114,E_Cat,"Promoter",E_Status,"Active",E_Survey,"Yes")-COUNTIFS(E_Dept,$B$114,E_Cat,"Detractor",E_Status,"Active",E_Survey,"Yes"))/COUNTIFS(E_Dept,$B$114,E_Status,"Active",E_Survey,"Yes")*100,0) -> 43.75 | N114: =COUNTIFS(E_Dept,$B$114,E_Risk,"High") -> 1 | O114: =COUNTIFS(R_Dept,$B$114,R_Status,"Open") -> 1 | P114: =IFERROR(AVERAGEIFS(R_TTF,R_Dept,$B$114,R_Status,"Filled"),0) -> 17.5 | Q114: =IFERROR(COUNTIFS(M_Dept,$B$114,M_Gender,"Female",M_Status,"Active")/COUNTIFS(M_Dept,$B$114,M_Status,"Active"),0) -> 0.5 | R114: =IFERROR(AVERAGEIFS(T_Hours,T_Dept,$B$114),0) -> 30.08 | S114: =IFERROR(COUNTIFS(P_Dept,$B$114,P_Rating,">=4",P_Status,"Active")/COUNTIFS(M_Dept,$B$114,M_Status,"Active"),0) -> 0.36363636 | T114: =IFERROR(COUNTIFS(T_Dept,$B$114,T_Comp,"Compliant",T_Status,"Active")/COUNTIFS(M_Dept,$B$114,M_Status,"Active"),0) -> 0.86363636 | U114: =IFERROR(AVERAGEIFS(M_Tenure,M_Dept,$B$114,M_Status,"Active"),0) -> 3.5818182
B115: Legal & Compliance | D115: =COUNTIFS(M_Dept,$B$115,M_Status,"Active") -> 23 | E115: =COUNTIFS(X_Dept,$B$115) -> 2 | F115: =IFERROR(COUNTIFS(X_Dept,$B$115)/((COUNTIFS(M_Dept,$B$115,M_DOJ,"<"&PeriodStart)+COUNTIFS(M_Dept,$B$115,M_Status,"Active"))/2),0) -> 0.10526316 | G115: =IFERROR(AVERAGEIFS(P_Rating,P_Dept,$B$115),0) -> 2.84 | H115: =COUNTIFS(P_Dept,$B$115,P_Elig,"Eligible") -> 5 | I115: =IFERROR(AVERAGEIFS(C_CTC,C_Dept,$B$115,C_Status,"Active")/100000,0) -> 20.036957 | J115: =IFERROR(AVERAGEIFS(C_Compa,C_Dept,$B$115,C_Status,"Active"),0) -> 1.0243478 | K115: =IFERROR(AVERAGEIFS(A_Att,A_Dept,$B$115,A_Status,"Active"),0) -> 0.83914227 | L115: =IFERROR(AVERAGEIFS(E_Overall,E_Dept,$B$115,E_Status,"Active"),0) -> 3.1143478 | M115: =IFERROR((COUNTIFS(E_Dept,$B$115,E_Cat,"Promoter",E_Status,"Active",E_Survey,"Yes")-COUNTIFS(E_Dept,$B$115,E_Cat,"Detractor",E_Status,"Active",E_Survey,"Yes"))/COUNTIFS(E_Dept,$B$115,E_Status,"Active",E_Survey,"Yes")*100,0) -> -4.7619048 | N115: =COUNTIFS(E_Dept,$B$115,E_Risk,"High") -> 0 | O115: =COUNTIFS(R_Dept,$B$115,R_Status,"Open") -> 4 | P115: =IFERROR(AVERAGEIFS(R_TTF,R_Dept,$B$115,R_Status,"Filled"),0) -> 52.8 | Q115: =IFERROR(COUNTIFS(M_Dept,$B$115,M_Gender,"Female",M_Status,"Active")/COUNTIFS(M_Dept,$B$115,M_Status,"Active"),0) -> 0.69565217 | R115: =IFERROR(AVERAGEIFS(T_Hours,T_Dept,$B$115),0) -> 25.96 | S115: =IFERROR(COUNTIFS(P_Dept,$B$115,P_Rating,">=4",P_Status,"Active")/COUNTIFS(M_Dept,$B$115,M_Status,"Active"),0) -> 0.30434783 | T115: =IFERROR(COUNTIFS(T_Dept,$B$115,T_Comp,"Compliant",T_Status,"Active")/COUNTIFS(M_Dept,$B$115,M_Status,"Active"),0) -> 0.95652174 | U115: =IFERROR(AVERAGEIFS(M_Tenure,M_Dept,$B$115,M_Status,"Active"),0) -> 1.9043478
B116: Organisation Total | D116: =COUNTIFS(M_Dept,"*",M_Status,"Active") -> 436 | E116: =COUNTIFS(X_Dept,"*") -> 64 | F116: =IFERROR(COUNTIFS(X_Dept,"*")/((COUNTIFS(M_Dept,"*",M_DOJ,"<"&PeriodStart)+COUNTIFS(M_Dept,"*",M_Status,"Active"))/2),0) -> 0.15705521 | G116: =IFERROR(AVERAGEIFS(P_Rating,P_Dept,"*"),0) -> 3.234 | H116: =COUNTIFS(P_Dept,"*",P_Elig,"Eligible") -> 82 | I116: =IFERROR(AVERAGEIFS(C_CTC,C_Dept,"*",C_Status,"Active")/100000,0) -> 16.457752 | J116: =IFERROR(AVERAGEIFS(C_Compa,C_Dept,"*",C_Status,"Active"),0) -> 0.9687156 | K116: =IFERROR(AVERAGEIFS(A_Att,A_Dept,"*",A_Status,"Active"),0) -> 0.89245868 | L116: =IFERROR(AVERAGEIFS(E_Overall,E_Dept,"*",E_Status,"Active"),0) -> 3.2512844 | M116: =IFERROR((COUNTIFS(E_Dept,"*",E_Cat,"Promoter",E_Status,"Active",E_Survey,"Yes")-COUNTIFS(E_Dept,"*",E_Cat,"Detractor",E_Status,"Active",E_Survey,"Yes"))/COUNTIFS(E_Dept,"*",E_Status,"Active",E_Survey,"Yes")*100,0) -> 22.727273 | N116: =COUNTIFS(E_Dept,"*",E_Risk,"High") -> 27 | O116: =COUNTIFS(R_Dept,"*",R_Status,"Open") -> 43 | P116: =IFERROR(AVERAGEIFS(R_TTF,R_Dept,"*",R_Status,"Filled"),0) -> 41.025974 | Q116: =IFERROR(COUNTIFS(M_Dept,"*",M_Gender,"Female",M_Status,"Active")/COUNTIFS(M_Dept,"*",M_Status,"Active"),0) -> 0.46559633 | R116: =IFERROR(AVERAGEIFS(T_Hours,T_Dept,"*"),0) -> 27.746 | S116: =IFERROR(COUNTIFS(P_Dept,"*",P_Rating,">=4",P_Status,"Active")/COUNTIFS(M_Dept,"*",M_Status,"Active"),0) -> 0.39220183 | T116: =IFERROR(COUNTIFS(T_Dept,"*",T_Comp,"Compliant",T_Status,"Active")/COUNTIFS(M_Dept,"*",M_Status,"Active"),0) -> 0.86926606 | U116: =IFERROR(AVERAGEIFS(M_Tenure,M_Dept,"*",M_Status,"Active"),0) -> 2.6311927
B118: Attrition = exits in last 12 months ÷ average of opening and closing headcount. eNPS = % promoters (9-10) minus % detractors (0-6) among active survey participants. All data is fictional.

Sheet Employee_Explorer
A1: EMPLOYEE EXPLORER
A2: =" Every employee in: "&SelLabel&" · "&COUNT(Calc_Engine!$H$2:$H$501)&" people · change the department on the Dashboard to switch the list" -> Every employee in: All Departments · 500 people · change the department on the Dashboard to switch the list
A3: Rows highlighted yellow = the employee selected on the Dashboard. Use the filter arrows to sort or slice this list.
A4: # | B4: Emp ID | C4: Employee Name | D4: Designation | E4: Department | F4: Level | G4: Manager | H4: Status | I4: Tenure (Yrs) | J4: Rating | K4: 9-Box | L4: Promotion | M4: CTC (₹ L) | N4: Compa | O4: Attendance | P4: Engagement | Q4: Flight Risk | R4: row
A5: =IF(B5="","",1) -> 1 | B5: =IF(Calc_Engine!I2="","",Calc_Engine!I2) -> EMP1001 | C5: =IF($R5="","",INDEX(M_Name,$R5)) -> Vidya Kulkarni | D5: =IF($R5="","",INDEX(M_Title,$R5)) -> Head of People | E5: =IF($R5="","",INDEX(M_Dept,$R5)) -> Human Resources | F5: =IF($R5="","",INDEX(M_Level,$R5)) -> L7 | G5: =IF($R5="","",INDEX(M_Mgr,$R5)) -> Arvind Rao (CEO) | H5: =IF($R5="","",INDEX(M_Status,$R5)) -> Active | I5: =IF($R5="","",INDEX(M_Tenure,$R5)) -> 9.8 | J5: =IF($R5="","",INDEX(P_Rating,$R5)) -> 5 | K5: =IF($R5="","",INDEX(P_9Box,$R5)) -> Star | L5: =IF($R5="","",INDEX(P_Elig,$R5)) -> Not Eligible | M5: =IF($R5="","",INDEX(C_CTC,$R5)/100000) -> 76.32 | N5: =IF($R5="","",INDEX(C_Compa,$R5)) -> 0.93 | O5: =IF($R5="","",INDEX(A_Att,$R5)) -> 0.928 | P5: =IF($R5="","",INDEX(E_Overall,$R5)) -> 3.73 | Q5: =IF($R5="","",INDEX(E_Risk,$R5)) -> Low | R5: =IF(B5="","",MATCH(B5,M_ID,0)) -> 1
A6: =IF(B6="","",2) -> 2 | B6: =IF(Calc_Engine!I3="","",Calc_Engine!I3) -> EMP1002 | C6: =IF($R6="","",INDEX(M_Name,$R6)) -> Vikas Singh | D6: =IF($R6="","",INDEX(M_Title,$R6)) -> Engineering Manager | E6: =IF($R6="","",INDEX(M_Dept,$R6)) -> Engineering | F6: =IF($R6="","",INDEX(M_Level,$R6)) -> L5 | G6: =IF($R6="","",INDEX(M_Mgr,$R6)) -> Yamini Nair | H6: =IF($R6="","",INDEX(M_Status,$R6)) -> Active | I6: =IF($R6="","",INDEX(M_Tenure,$R6)) -> 7.9 | J6: =IF($R6="","",INDEX(P_Rating,$R6)) -> 4 | K6: =IF($R6="","",INDEX(P_9Box,$R6)) -> High Performer | L6: =IF($R6="","",INDEX(P_Elig,$R6)) -> Eligible | M6: =IF($R6="","",INDEX(C_CTC,$R6)/100000) -> 44.07 | N6: =IF($R6="","",INDEX(C_Compa,$R6)) -> 1.2 | O6: =IF($R6="","",INDEX(A_Att,$R6)) -> 0.96 | P6: =IF($R6="","",INDEX(E_Overall,$R6)) -> 4.53 | Q6: =IF($R6="","",INDEX(E_Risk,$R6)) -> Low | R6: =IF(B6="","",MATCH(B6,M_ID,0)) -> 2
A7: =IF(B7="","",3) -> 3 | B7: =IF(Calc_Engine!I4="","",Calc_Engine!I4) -> EMP1003 | C7: =IF($R7="","",INDEX(M_Name,$R7)) -> Prakash Das | D7: =IF($R7="","",INDEX(M_Title,$R7)) -> Senior HR Manager | E7: =IF($R7="","",INDEX(M_Dept,$R7)) -> Human Resources | F7: =IF($R7="","",INDEX(M_Level,$R7)) -> L6 | G7: =IF($R7="","",INDEX(M_Mgr,$R7)) -> Vidya Kulkarni | H7: =IF($R7="","",INDEX(M_Status,$R7)) -> Active | I7: =IF($R7="","",INDEX(M_Tenure,$R7)) -> 7.5 | J7: =IF($R7="","",INDEX(P_Rating,$R7)) -> 2 | K7: =IF($R7="","",INDEX(P_9Box,$R7)) -> Inconsistent Player | L7: =IF($R7="","",INDEX(P_Elig,$R7)) -> Not Eligible | M7: =IF($R7="","",INDEX(C_CTC,$R7)/100000) -> 51.06 | N7: =IF($R7="","",INDEX(C_Compa,$R7)) -> 0.95 | O7: =IF($R7="","",INDEX(A_Att,$R7)) -> 0.932 | P7: =IF($R7="","",INDEX(E_Overall,$R7)) -> 3.23 | Q7: =IF($R7="","",INDEX(E_Risk,$R7)) -> Low | R7: =IF(B7="","",MATCH(B7,M_ID,0)) -> 3
A8: =IF(B8="","",4) -> 4 | B8: =IF(Calc_Engine!I5="","",Calc_Engine!I5) -> EMP1004 | C8: =IF($R8="","",INDEX(M_Name,$R8)) -> Fatima Choudhary | D8: =IF($R8="","",INDEX(M_Title,$R8)) -> Engineering Manager | E8: =IF($R8="","",INDEX(M_Dept,$R8)) -> Engineering | F8: =IF($R8="","",INDEX(M_Level,$R8)) -> L5 | G8: =IF($R8="","",INDEX(M_Mgr,$R8)) -> Yamini Nair | H8: =IF($R8="","",INDEX(M_Status,$R8)) -> Active | I8: =IF($R8="","",INDEX(M_Tenure,$R8)) -> 7.5 | J8: =IF($R8="","",INDEX(P_Rating,$R8)) -> 2 | K8: =IF($R8="","",INDEX(P_9Box,$R8)) -> Inconsistent Player | L8: =IF($R8="","",INDEX(P_Elig,$R8)) -> Not Eligible | M8: =IF($R8="","",INDEX(C_CTC,$R8)/100000) -> 44.89 | N8: =IF($R8="","",INDEX(C_Compa,$R8)) -> 1.22 | O8: =IF($R8="","",INDEX(A_Att,$R8)) -> 0.88 | P8: =IF($R8="","",INDEX(E_Overall,$R8)) -> 3.12 | Q8: =IF($R8="","",INDEX(E_Risk,$R8)) -> Low | R8: =IF(B8="","",MATCH(B8,M_ID,0)) -> 4
A9: =IF(B9="","",5) -> 5 | B9: =IF(Calc_Engine!I6="","",Calc_Engine!I6) -> EMP1005 | C9: =IF($R9="","",INDEX(M_Name,$R9)) -> Gaurav Fernandes | D9: =IF($R9="","",INDEX(M_Title,$R9)) -> Engineering Manager | E9: =IF($R9="","",INDEX(M_Dept,$R9)) -> Engineering | F9: =IF($R9="","",INDEX(M_Level,$R9)) -> L5 | G9: =IF($R9="","",INDEX(M_Mgr,$R9)) -> Yamini Nair | H9: =IF($R9="","",INDEX(M_Status,$R9)) -> Active | I9: =IF($R9="","",INDEX(M_Tenure,$R9)) -> 7.2 | J9: =IF($R9="","",INDEX(P_Rating,$R9)) -> 3 | K9: =IF($R9="","",INDEX(P_9Box,$R9)) -> Core Player | L9: =IF($R9="","",INDEX(P_Elig,$R9)) -> Not Eligible | M9: =IF($R9="","",INDEX(C_CTC,$R9)/100000) -> 49.38 | N9: =IF($R9="","",INDEX(C_Compa,$R9)) -> 1.35 | O9: =IF($R9="","",INDEX(A_Att,$R9)) -> 0.94 | P9: =IF($R9="","",INDEX(E_Overall,$R9)) -> 3.82 | Q9: =IF($R9="","",INDEX(E_Risk,$R9)) -> Low | R9: =IF(B9="","",MATCH(B9,M_ID,0)) -> 5
A10: =IF(B10="","",6) -> 6 | B10: =IF(Calc_Engine!I7="","",Calc_Engine!I7) -> EMP1006 | C10: =IF($R10="","",INDEX(M_Name,$R10)) -> Yash Shah | D10: =IF($R10="","",INDEX(M_Title,$R10)) -> Operations Manager | E10: =IF($R10="","",INDEX(M_Dept,$R10)) -> Operations | F10: =IF($R10="","",INDEX(M_Level,$R10)) -> L5 | G10: =IF($R10="","",INDEX(M_Mgr,$R10)) -> Pallavi Shah | H10: =IF($R10="","",INDEX(M_Status,$R10)) -> Exited | I10: =IF($R10="","",INDEX(M_Tenure,$R10)) -> 7 | J10: =IF($R10="","",INDEX(P_Rating,$R10)) -> 4 | K10: =IF($R10="","",INDEX(P_9Box,$R10)) -> High Performer | L10: =IF($R10="","",INDEX(P_Elig,$R10)) -> Not Eligible | M10: =IF($R10="","",INDEX(C_CTC,$R10)/100000) -> 27.14 | N10: =IF($R10="","",INDEX(C_Compa,$R10)) -> 0.74 | O10: =IF($R10="","",INDEX(A_Att,$R10)) -> 0.90047393 | P10: =IF($R10="","",INDEX(E_Overall,$R10)) -> 2.97 | Q10: =IF($R10="","",INDEX(E_Risk,$R10)) -> Exited | R10: =IF(B10="","",MATCH(B10,M_ID,0)) -> 6
A11: =IF(B11="","",7) -> 7 | B11: =IF(Calc_Engine!I8="","",Calc_Engine!I8) -> EMP1007 | C11: =IF($R11="","",INDEX(M_Name,$R11)) -> Imran Tiwari | D11: =IF($R11="","",INDEX(M_Title,$R11)) -> Marketing Lead | E11: =IF($R11="","",INDEX(M_Dept,$R11)) -> Marketing | F11: =IF($R11="","",INDEX(M_Level,$R11)) -> L4 | G11: =IF($R11="","",INDEX(M_Mgr,$R11)) -> Nandini Iyer | H11: =IF($R11="","",INDEX(M_Status,$R11)) -> Exited | I11: =IF($R11="","",INDEX(M_Tenure,$R11)) -> 6.4 | J11: =IF($R11="","",INDEX(P_Rating,$R11)) -> 1 | K11: =IF($R11="","",INDEX(P_9Box,$R11)) -> Underperformer | L11: =IF($R11="","",INDEX(P_Elig,$R11)) -> Not Eligible | M11: =IF($R11="","",INDEX(C_CTC,$R11)/100000) -> 22.29 | N11: =IF($R11="","",INDEX(C_Compa,$R11)) -> 0.95 | O11: =IF($R11="","",INDEX(A_Att,$R11)) -> 0.78448276 | P11: =IF($R11="","",INDEX(E_Overall,$R11)) -> 2.43 | Q11: =IF($R11="","",INDEX(E_Risk,$R11)) -> Exited | R11: =IF(B11="","",MATCH(B11,M_ID,0)) -> 7
A12: =IF(B12="","",8) -> 8 | B12: =IF(Calc_Engine!I9="","",Calc_Engine!I9) -> EMP1008 | C12: =IF($R12="","",INDEX(M_Name,$R12)) -> Aishwarya Khan | D12: =IF($R12="","",INDEX(M_Title,$R12)) -> Head of Engineering | E12: =IF($R12="","",INDEX(M_Dept,$R12)) -> Engineering | F12: =IF($R12="","",INDEX(M_Level,$R12)) -> L7 | G12: =IF($R12="","",INDEX(M_Mgr,$R12)) -> Arvind Rao (CEO) | H12: =IF($R12="","",INDEX(M_Status,$R12)) -> Active | I12: =IF($R12="","",INDEX(M_Tenure,$R12)) -> 6.9 | J12: =IF($R12="","",INDEX(P_Rating,$R12)) -> 3 | K12: =IF($R12="","",INDEX(P_9Box,$R12)) -> Core Player | L12: =IF($R12="","",INDEX(P_Elig,$R12)) -> Not Eligible | M12: =IF($R12="","",INDEX(C_CTC,$R12)/100000) -> 92.08 | N12: =IF($R12="","",INDEX(C_Compa,$R12)) -> 1.12 | O12: =IF($R12="","",INDEX(A_Att,$R12)) -> 0.944 | P12: =IF($R12="","",INDEX(E_Overall,$R12)) -> 2.03 | Q12: =IF($R12="","",INDEX(E_Risk,$R12)) -> Low | R12: =IF(B12="","",MATCH(B12,M_ID,0)) -> 8
A13: =IF(B13="","",9) -> 9 | B13: =IF(Calc_Engine!I10="","",Calc_Engine!I10) -> EMP1009 | C13: =IF($R13="","",INDEX(M_Name,$R13)) -> Ankit Khanna | D13: =IF($R13="","",INDEX(M_Title,$R13)) -> Operations Manager | E13: =IF($R13="","",INDEX(M_Dept,$R13)) -> Operations | F13: =IF($R13="","",INDEX(M_Level,$R13)) -> L5 | G13: =IF($R13="","",INDEX(M_Mgr,$R13)) -> Imran Mishra | H13: =IF($R13="","",INDEX(M_Status,$R13)) -> Active | I13: =IF($R13="","",INDEX(M_Tenure,$R13)) -> 6.9 | J13: =IF($R13="","",INDEX(P_Rating,$R13)) -> 3 | K13: =IF($R13="","",INDEX(P_9Box,$R13)) -> Core Player | L13: =IF($R13="","",INDEX(P_Elig,$R13)) -> Not Eligible | M13: =IF($R13="","",INDEX(C_CTC,$R13)/100000) -> 36.08 | N13: =IF($R13="","",INDEX(C_Compa,$R13)) -> 0.98 | O13: =IF($R13="","",INDEX(A_Att,$R13)) -> 0.944 | P13: =IF($R13="","",INDEX(E_Overall,$R13)) -> 3.2 | Q13: =IF($R13="","",INDEX(E_Risk,$R13)) -> Low | R13: =IF(B13="","",MATCH(B13,M_ID,0)) -> 9
A14: =IF(B14="","",10) -> 10 | B14: =IF(Calc_Engine!I11="","",Calc_Engine!I11) -> EMP1010 | C14: =IF($R14="","",INDEX(M_Name,$R14)) -> Pooja Das | D14: =IF($R14="","",INDEX(M_Title,$R14)) -> Head of Finance | E14: =IF($R14="","",INDEX(M_Dept,$R14)) -> Finance | F14: =IF($R14="","",INDEX(M_Level,$R14)) -> L7 | G14: =IF($R14="","",INDEX(M_Mgr,$R14)) -> Arvind Rao (CEO) | H14: =IF($R14="","",INDEX(M_Status,$R14)) -> Active | I14: =IF($R14="","",INDEX(M_Tenure,$R14)) -> 6.9 | J14: =IF($R14="","",INDEX(P_Rating,$R14)) -> 2 | K14: =IF($R14="","",INDEX(P_9Box,$R14)) -> Inconsistent Player | L14: =IF($R14="","",INDEX(P_Elig,$R14)) -> Not Eligible | M14: =IF($R14="","",INDEX(C_CTC,$R14)/100000) -> 81.36 | N14: =IF($R14="","",INDEX(C_Compa,$R14)) -> 0.99 | O14: =IF($R14="","",INDEX(A_Att,$R14)) -> 0.912 | P14: =IF($R14="","",INDEX(E_Overall,$R14)) -> 3.4 | Q14: =IF($R14="","",INDEX(E_Risk,$R14)) -> Low | R14: =IF(B14="","",MATCH(B14,M_ID,0)) -> 10
A15: =IF(B15="","",11) -> 11 | B15: =IF(Calc_Engine!I12="","",Calc_Engine!I12) -> EMP1011 | C15: =IF($R15="","",INDEX(M_Name,$R15)) -> Trisha Patel | D15: =IF($R15="","",INDEX(M_Title,$R15)) -> Principal Product Manager | E15: =IF($R15="","",INDEX(M_Dept,$R15)) -> Product | F15: =IF($R15="","",INDEX(M_Level,$R15)) -> L6 | G15: =IF($R15="","",INDEX(M_Mgr,$R15)) -> Dev Bose | H15: =IF($R15="","",INDEX(M_Status,$R15)) -> Active | I15: =IF($R15="","",INDEX(M_Tenure,$R15)) -> 6.8 | J15: =IF($R15="","",INDEX(P_Rating,$R15)) -> 3 | K15: =IF($R15="","",INDEX(P_9Box,$R15)) -> Core Player | L15: =IF($R15="","",INDEX(P_Elig,$R15)) -> Not Eligible | M15: =IF($R15="","",INDEX(C_CTC,$R15)/100000) -> 56.57 | N15: =IF($R15="","",INDEX(C_Compa,$R15)) -> 1.05 | O15: =IF($R15="","",INDEX(A_Att,$R15)) -> 0.892 | P15: =IF($R15="","",INDEX(E_Overall,$R15)) -> 2.9 | Q15: =IF($R15="","",INDEX(E_Risk,$R15)) -> Medium | R15: =IF(B15="","",MATCH(B15,M_ID,0)) -> 11
A16: =IF(B16="","",12) -> 12 | B16: =IF(Calc_Engine!I13="","",Calc_Engine!I13) -> EMP1012 | C16: =IF($R16="","",INDEX(M_Name,$R16)) -> Krishna Kumar | D16: =IF($R16="","",INDEX(M_Title,$R16)) -> Operations Lead | E16: =IF($R16="","",INDEX(M_Dept,$R16)) -> Operations | F16: =IF($R16="","",INDEX(M_Level,$R16)) -> L4 | G16: =IF($R16="","",INDEX(M_Mgr,$R16)) -> Amit Kumar | H16: =IF($R16="","",INDEX(M_Status,$R16)) -> Active | I16: =IF($R16="","",INDEX(M_Tenure,$R16)) -> 6.8 | J16: =IF($R16="","",INDEX(P_Rating,$R16)) -> 3 | K16: =IF($R16="","",INDEX(P_9Box,$R16)) -> Core Player | L16: =IF($R16="","",INDEX(P_Elig,$R16)) -> Not Eligible | M16: =IF($R16="","",INDEX(C_CTC,$R16)/100000) -> 17.21 | N16: =IF($R16="","",INDEX(C_Compa,$R16)) -> 0.73 | O16: =IF($R16="","",INDEX(A_Att,$R16)) -> 0.928 | P16: =IF($R16="","",INDEX(E_Overall,$R16)) -> 2.83 | Q16: =IF($R16="","",INDEX(E_Risk,$R16)) -> Medium | R16: =IF(B16="","",MATCH(B16,M_ID,0)) -> 12
A17: =IF(B17="","",13) -> 13 | B17: =IF(Calc_Engine!I14="","",Calc_Engine!I14) -> EMP1013 | C17: =IF($R17="","",INDEX(M_Name,$R17)) -> Ramya Khanna | D17: =IF($R17="","",INDEX(M_Title,$R17)) -> Compliance Manager | E17: =IF($R17="","",INDEX(M_Dept,$R17)) -> Legal & Compliance | F17: =IF($R17="","",INDEX(M_Level,$R17)) -> L5 | G17: =IF($R17="","",INDEX(M_Mgr,$R17)) -> Lakshmi Subramanian | H17: =IF($R17="","",INDEX(M_Status,$R17)) -> Active | I17: =IF($R17="","",INDEX(M_Tenure,$R17)) -> 6.7 | J17: =IF($R17="","",INDEX(P_Rating,$R17)) -> 3 | K17: =IF($R17="","",INDEX(P_9Box,$R17)) -> Core Player | L17: =IF($R17="","",INDEX(P_Elig,$R17)) -> Not Eligible | M17: =IF($R17="","",INDEX(C_CTC,$R17)/100000) -> 34.07 | N17: =IF($R17="","",INDEX(C_Compa,$R17)) -> 0.93 | O17: =IF($R17="","",INDEX(A_Att,$R17)) -> 0.928 | P17: =IF($R17="","",INDEX(E_Overall,$R17)) -> 3.33 | Q17: =IF($R17="","",INDEX(E_Risk,$R17)) -> Low | R17: =IF(B17="","",MATCH(B17,M_ID,0)) -> 13
A18: =IF(B18="","",14) -> 14 | B18: =IF(Calc_Engine!I15="","",Calc_Engine!I15) -> EMP1014 | C18: =IF($R18="","",INDEX(M_Name,$R18)) -> Rashmi Jain | D18: =IF($R18="","",INDEX(M_Title,$R18)) -> Senior HR Business Partner | E18: =IF($R18="","",INDEX(M_Dept,$R18)) -> Human Resources | F18: =IF($R18="","",INDEX(M_Level,$R18)) -> L4 | G18: =IF($R18="","",INDEX(M_Mgr,$R18)) -> Akash Das | H18: =IF($R18="","",INDEX(M_Status,$R18)) -> Active | I18: =IF($R18="","",INDEX(M_Tenure,$R18)) -> 6.5 | J18: =IF($R18="","",INDEX(P_Rating,$R18)) -> 3 | K18: =IF($R18="","",INDEX(P_9Box,$R18)) -> Future Star | L18: =IF($R18="","",INDEX(P_Elig,$R18)) -> Not Eligible | M18: =IF($R18="","",INDEX(C_CTC,$R18)/100000) -> 21.82 | N18: =IF($R18="","",INDEX(C_Compa,$R18)) -> 0.93 | O18: =IF($R18="","",INDEX(A_Att,$R18)) -> 0.956 | P18: =IF($R18="","",INDEX(E_Overall,$R18)) -> 3.28 | Q18: =IF($R18="","",INDEX(E_Risk,$R18)) -> Low | R18: =IF(B18="","",MATCH(B18,M_ID,0)) -> 14
A19: =IF(B19="","",15) -> 15 | B19: =IF(Calc_Engine!I16="","",Calc_Engine!I16) -> EMP1015 | C19: =IF($R19="","",INDEX(M_Name,$R19)) -> Ajay Ansari | D19: =IF($R19="","",INDEX(M_Title,$R19)) -> Operations Lead | E19: =IF($R19="","",INDEX(M_Dept,$R19)) -> Operations | F19: =IF($R19="","",INDEX(M_Level,$R19)) -> L4 | G19: =IF($R19="","",INDEX(M_Mgr,$R19)) -> Ankit Khanna | H19: =IF($R19="","",INDEX(M_Status,$R19)) -> Active | I19: =IF($R19="","",INDEX(M_Tenure,$R19)) -> 6.4 | J19: =IF($R19="","",INDEX(P_Rating,$R19)) -> 4 | K19: =IF($R19="","",INDEX(P_9Box,$R19)) -> Star | L19: =IF($R19="","",INDEX(P_Elig,$R19)) -> Not Eligible | M19: =IF($R19="","",INDEX(C_CTC,$R19)/100000) -> 19.91 | N19: =IF($R19="","",INDEX(C_Compa,$R19)) -> 0.85 | O19: =IF($R19="","",INDEX(A_Att,$R19)) -> 0.908 | P19: =IF($R19="","",INDEX(E_Overall,$R19)) -> 3.48 | Q19: =IF($R19="","",INDEX(E_Risk,$R19)) -> Medium | R19: =IF(B19="","",MATCH(B19,M_ID,0)) -> 15
A20: =IF(B20="","",16) -> 16 | B20: =IF(Calc_Engine!I17="","",Calc_Engine!I17) -> EMP1016 | C20: =IF($R20="","",INDEX(M_Name,$R20)) -> Isha Verma | D20: =IF($R20="","",INDEX(M_Title,$R20)) -> Support Manager | E20: =IF($R20="","",INDEX(M_Dept,$R20)) -> Customer Support | F20: =IF($R20="","",INDEX(M_Level,$R20)) -> L5 | G20: =IF($R20="","",INDEX(M_Mgr,$R20)) -> Akash Dsouza | H20: =IF($R20="","",INDEX(M_Status,$R20)) -> Active | I20: =IF($R20="","",INDEX(M_Tenure,$R20)) -> 6.4 | J20: =IF($R20="","",INDEX(P_Rating,$R20)) -> 3 | K20: =IF($R20="","",INDEX(P_9Box,$R20)) -> Future Star | L20: =IF($R20="","",INDEX(P_Elig,$R20)) -> Not Eligible | M20: =IF($R20="","",INDEX(C_CTC,$R20)/100000) -> 30.24 | N20: =IF($R20="","",INDEX(C_Compa,$R20)) -> 0.82 | O20: =IF($R20="","",INDEX(A_Att,$R20)) -> 0.916 | P20: =IF($R20="","",INDEX(E_Overall,$R20)) -> 3.17 | Q20: =IF($R20="","",INDEX(E_Risk,$R20)) -> Low | R20: =IF(B20="","",MATCH(B20,M_ID,0)) -> 16
A21: =IF(B21="","",17) -> 17 | B21: =IF(Calc_Engine!I18="","",Calc_Engine!I18) -> EMP1017 | C21: =IF($R21="","",INDEX(M_Name,$R21)) -> Pooja Naidu | D21: =IF($R21="","",INDEX(M_Title,$R21)) -> Tech Lead | E21: =IF($R21="","",INDEX(M_Dept,$R21)) -> Engineering | F21: =IF($R21="","",INDEX(M_Level,$R21)) -> L4 | G21: =IF($R21="","",INDEX(M_Mgr,$R21)) -> Harsh Siddiqui | H21: =IF($R21="","",INDEX(M_Status,$R21)) -> Active | I21: =IF($R21="","",INDEX(M_Tenure,$R21)) -> 6.3 | J21: =IF($R21="","",INDEX(P_Rating,$R21)) -> 5 | K21: =IF($R21="","",INDEX(P_9Box,$R21)) -> Star | L21: =IF($R21="","",INDEX(P_Elig,$R21)) -> Eligible | M21: =IF($R21="","",INDEX(C_CTC,$R21)/100000) -> 30.05 | N21: =IF($R21="","",INDEX(C_Compa,$R21)) -> 1.28 | O21: =IF($R21="","",INDEX(A_Att,$R21)) -> 0.904 | P21: =IF($R21="","",INDEX(E_Overall,$R21)) -> 3.9 | Q21: =IF($R21="","",INDEX(E_Risk,$R21)) -> Low | R21: =IF(B21="","",MATCH(B21,M_ID,0)) -> 17
A22: =IF(B22="","",18) -> 18 | B22: =IF(Calc_Engine!I19="","",Calc_Engine!I19) -> EMP1018 | C22: =IF($R22="","",INDEX(M_Name,$R22)) -> Isha Chatterjee | D22: =IF($R22="","",INDEX(M_Title,$R22)) -> Marketing Manager | E22: =IF($R22="","",INDEX(M_Dept,$R22)) -> Marketing | F22: =IF($R22="","",INDEX(M_Level,$R22)) -> L5 | G22: =IF($R22="","",INDEX(M_Mgr,$R22)) -> Aishwarya Mukherjee | H22: =IF($R22="","",INDEX(M_Status,$R22)) -> Exited | I22: =IF($R22="","",INDEX(M_Tenure,$R22)) -> 5.8 | J22: =IF($R22="","",INDEX(P_Rating,$R22)) -> 5 | K22: =IF($R22="","",INDEX(P_9Box,$R22)) -> High Performer | L22: =IF($R22="","",INDEX(P_Elig,$R22)) -> Not Eligible | M22: =IF($R22="","",INDEX(C_CTC,$R22)/100000) -> 34.3 | N22: =IF($R22="","",INDEX(C_Compa,$R22)) -> 0.94 | O22: =IF($R22="","",INDEX(A_Att,$R22)) -> 0.83211679 | P22: =IF($R22="","",INDEX(E_Overall,$R22)) -> 3.45 | Q22: =IF($R22="","",INDEX(E_Risk,$R22)) -> Exited | R22: =IF(B22="","",MATCH(B22,M_ID,0)) -> 18
A23: =IF(B23="","",19) -> 19 | B23: =IF(Calc_Engine!I20="","",Calc_Engine!I20) -> EMP1019 | C23: =IF($R23="","",INDEX(M_Name,$R23)) -> Fatima Reddy | D23: =IF($R23="","",INDEX(M_Title,$R23)) -> Key Account Manager | E23: =IF($R23="","",INDEX(M_Dept,$R23)) -> Sales | F23: =IF($R23="","",INDEX(M_Level,$R23)) -> L4 | G23: =IF($R23="","",INDEX(M_Mgr,$R23)) -> Srinivas Shah | H23: =IF($R23="","",INDEX(M_Status,$R23)) -> Active | I23: =IF($R23="","",INDEX(M_Tenure,$R23)) -> 6.2 | J23: =IF($R23="","",INDEX(P_Rating,$R23)) -> 3 | K23: =IF($R23="","",INDEX(P_9Box,$R23)) -> Core Player | L23: =IF($R23="","",INDEX(P_Elig,$R23)) -> Not Eligible | M23: =IF($R23="","",INDEX(C_CTC,$R23)/100000) -> 24.22 | N23: =IF($R23="","",INDEX(C_Compa,$R23)) -> 1.03 | O23: =IF($R23="","",INDEX(A_Att,$R23)) -> 0.92 | P23: =IF($R23="","",INDEX(E_Overall,$R23)) -> 2.33 | Q23: =IF($R23="","",INDEX(E_Risk,$R23)) -> Medium | R23: =IF(B23="","",MATCH(B23,M_ID,0)) -> 19
A24: =IF(B24="","",20) -> 20 | B24: =IF(Calc_Engine!I21="","",Calc_Engine!I21) -> EMP1020 | C24: =IF($R24="","",INDEX(M_Name,$R24)) -> Naveen Subramanian | D24: =IF($R24="","",INDEX(M_Title,$R24)) -> Support Team Lead | E24: =IF($R24="","",INDEX(M_Dept,$R24)) -> Customer Support | F24: =IF($R24="","",INDEX(M_Level,$R24)) -> L4 | G24: =IF($R24="","",INDEX(M_Mgr,$R24)) -> Ashish Varghese | H24: =IF($R24="","",INDEX(M_Status,$R24)) -> Active | I24: =IF($R24="","",INDEX(M_Tenure,$R24)) -> 6.2 | J24: =IF($R24="","",INDEX(P_Rating,$R24)) -> 3 | K24: =IF($R24="","",INDEX(P_9Box,$R24)) -> Core Player | L24: =IF($R24="","",INDEX(P_Elig,$R24)) -> Not Eligible | M24: =IF($R24="","",INDEX(C_CTC,$R24)/100000) -> 17.31 | N24: =IF($R24="","",INDEX(C_Compa,$R24)) -> 0.74 | O24: =IF($R24="","",INDEX(A_Att,$R24)) -> 0.956 | P24: =IF($R24="","",INDEX(E_Overall,$R24)) -> 3.4 | Q24: =IF($R24="","",INDEX(E_Risk,$R24)) -> Low | R24: =IF(B24="","",MATCH(B24,M_ID,0)) -> 20
A25: =IF(B25="","",21) -> 21 | B25: =IF(Calc_Engine!I22="","",Calc_Engine!I22) -> EMP1021 | C25: =IF($R25="","",INDEX(M_Name,$R25)) -> Arun Mukherjee | D25: =IF($R25="","",INDEX(M_Title,$R25)) -> Analytics Manager | E25: =IF($R25="","",INDEX(M_Dept,$R25)) -> Data & Analytics | F25: =IF($R25="","",INDEX(M_Level,$R25)) -> L5 | G25: =IF($R25="","",INDEX(M_Mgr,$R25)) -> Trisha Jain | H25: =IF($R25="","",INDEX(M_Status,$R25)) -> Active | I25: =IF($R25="","",INDEX(M_Tenure,$R25)) -> 6 | J25: =IF($R25="","",INDEX(P_Rating,$R25)) -> 3 | K25: =IF($R25="","",INDEX(P_9Box,$R25)) -> Future Star | L25: =IF($R25="","",INDEX(P_Elig,$R25)) -> Not Eligible | M25: =IF($R25="","",INDEX(C_CTC,$R25)/100000) -> 43.9 | N25: =IF($R25="","",INDEX(C_Compa,$R25)) -> 1.2 | O25: =IF($R25="","",INDEX(A_Att,$R25)) -> 0.952 | P25: =IF($R25="","",INDEX(E_Overall,$R25)) -> 3.53 | Q25: =IF($R25="","",INDEX(E_Risk,$R25)) -> Low | R25: =IF(B25="","",MATCH(B25,M_ID,0)) -> 21
A26: =IF(B26="","",22) -> 22 | B26: =IF(Calc_Engine!I23="","",Calc_Engine!I23) -> EMP1022 | C26: =IF($R26="","",INDEX(M_Name,$R26)) -> Arun Joshi | D26: =IF($R26="","",INDEX(M_Title,$R26)) -> Senior Data Analyst | E26: =IF($R26="","",INDEX(M_Dept,$R26)) -> Data & Analytics | F26: =IF($R26="","",INDEX(M_Level,$R26)) -> L3 | G26: =IF($R26="","",INDEX(M_Mgr,$R26)) -> Arun Mukherjee | H26: =IF($R26="","",INDEX(M_Status,$R26)) -> Active | I26: =IF($R26="","",INDEX(M_Tenure,$R26)) -> 6 | J26: =IF($R26="","",INDEX(P_Rating,$R26)) -> 3 | K26: =IF($R26="","",INDEX(P_9Box,$R26)) -> Effective Contributor | L26: =IF($R26="","",INDEX(P_Elig,$R26)) -> Not Eligible | M26: =IF($R26="","",INDEX(C_CTC,$R26)/100000) -> 15.59 | N26: =IF($R26="","",INDEX(C_Compa,$R26)) -> 1.08 | O26: =IF($R26="","",INDEX(A_Att,$R26)) -> 0.928 | P26: =IF($R26="","",INDEX(E_Overall,$R26)) -> 3.07 | Q26: =IF($R26="","",INDEX(E_Risk,$R26)) -> Low | R26: =IF(B26="","",MATCH(B26,M_ID,0)) -> 22
A27: =IF(B27="","",23) -> 23 | B27: =IF(Calc_Engine!I24="","",Calc_Engine!I24) -> EMP1023 | C27: =IF($R27="","",INDEX(M_Name,$R27)) -> Ashish Prabhu | D27: =IF($R27="","",INDEX(M_Title,$R27)) -> Senior Operations Executive | E27: =IF($R27="","",INDEX(M_Dept,$R27)) -> Operations | F27: =IF($R27="","",INDEX(M_Level,$R27)) -> L3 | G27: =IF($R27="","",INDEX(M_Mgr,$R27)) -> Ajay Kumar | H27: =IF($R27="","",INDEX(M_Status,$R27)) -> Active | I27: =IF($R27="","",INDEX(M_Tenure,$R27)) -> 6 | J27: =IF($R27="","",INDEX(P_Rating,$R27)) -> 3 | K27: =IF($R27="","",INDEX(P_9Box,$R27)) -> Core Player | L27: =IF($R27="","",INDEX(P_Elig,$R27)) -> Not Eligible | M27: =IF($R27="","",INDEX(C_CTC,$R27)/100000) -> 11.77 | N27: =IF($R27="","",INDEX(C_Compa,$R27)) -> 0.81 | O27: =IF($R27="","",INDEX(A_Att,$R27)) -> 0.944 | P27: =IF($R27="","",INDEX(E_Overall,$R27)) -> 3.48 | Q27: =IF($R27="","",INDEX(E_Risk,$R27)) -> Low | R27: =IF(B27="","",MATCH(B27,M_ID,0)) -> 23
A28: =IF(B28="","",24) -> 24 | B28: =IF(Calc_Engine!I25="","",Calc_Engine!I25) -> EMP1024 | C28: =IF($R28="","",INDEX(M_Name,$R28)) -> Priyanka Naidu | D28: =IF($R28="","",INDEX(M_Title,$R28)) -> HR Business Partner | E28: =IF($R28="","",INDEX(M_Dept,$R28)) -> Human Resources | F28: =IF($R28="","",INDEX(M_Level,$R28)) -> L3 | G28: =IF($R28="","",INDEX(M_Mgr,$R28)) -> Ajay Patel | H28: =IF($R28="","",INDEX(M_Status,$R28)) -> Active | I28: =IF($R28="","",INDEX(M_Tenure,$R28)) -> 6 | J28: =IF($R28="","",INDEX(P_Rating,$R28)) -> 4 | K28: =IF($R28="","",INDEX(P_9Box,$R28)) -> Star | L28: =IF($R28="","",INDEX(P_Elig,$R28)) -> Eligible | M28: =IF($R28="","",INDEX(C_CTC,$R28)/100000) -> 14.71 | N28: =IF($R28="","",INDEX(C_Compa,$R28)) -> 1.02 | O28: =IF($R28="","",INDEX(A_Att,$R28)) -> 0.952 | P28: =IF($R28="","",INDEX(E_Overall,$R28)) -> 3.53 | Q28: =IF($R28="","",INDEX(E_Risk,$R28)) -> Low | R28: =IF(B28="","",MATCH(B28,M_ID,0)) -> 24
A29: =IF(B29="","",25) -> 25 | B29: =IF(Calc_Engine!I26="","",Calc_Engine!I26) -> EMP1025 | C29: =IF($R29="","",INDEX(M_Name,$R29)) -> Nikhil Agarwal | D29: =IF($R29="","",INDEX(M_Title,$R29)) -> Sales Manager | E29: =IF($R29="","",INDEX(M_Dept,$R29)) -> Sales | F29: =IF($R29="","",INDEX(M_Level,$R29)) -> L5 | G29: =IF($R29="","",INDEX(M_Mgr,$R29)) -> Joseph Varghese | H29: =IF($R29="","",INDEX(M_Status,$R29)) -> Active | I29: =IF($R29="","",INDEX(M_Tenure,$R29)) -> 5.9 | J29: =IF($R29="","",INDEX(P_Rating,$R29)) -> 2 | K29: =IF($R29="","",INDEX(P_9Box,$R29)) -> Inconsistent Player | L29: =IF($R29="","",INDEX(P_Elig,$R29)) -> Not Eligible | M29: =IF($R29="","",INDEX(C_CTC,$R29)/100000) -> 35.26 | N29: =IF($R29="","",INDEX(C_Compa,$R29)) -> 0.96 | O29: =IF($R29="","",INDEX(A_Att,$R29)) -> 0.888 | P29: =IF($R29="","",INDEX(E_Overall,$R29)) -> 3.1 | Q29: =IF($R29="","",INDEX(E_Risk,$R29)) -> Low | R29: =IF(B29="","",MATCH(B29,M_ID,0)) -> 25
A30: =IF(B30="","",26) -> 26 | B30: =IF(Calc_Engine!I27="","",Calc_Engine!I27) -> EMP1026 | C30: =IF($R30="","",INDEX(M_Name,$R30)) -> Revathi Rao | D30: =IF($R30="","",INDEX(M_Title,$R30)) -> Senior Sales Executive | E30: =IF($R30="","",INDEX(M_Dept,$R30)) -> Sales | F30: =IF($R30="","",INDEX(M_Level,$R30)) -> L3 | G30: =IF($R30="","",INDEX(M_Mgr,$R30)) -> Yash Raghavan | H30: =IF($R30="","",INDEX(M_Status,$R30)) -> Exited | I30: =IF($R30="","",INDEX(M_Tenure,$R30)) -> 5.3 | J30: =IF($R30="","",INDEX(P_Rating,$R30)) -> 3 | K30: =IF($R30="","",INDEX(P_9Box,$R30)) -> Core Player | L30: =IF($R30="","",INDEX(P_Elig,$R30)) -> Not Eligible | M30: =IF($R30="","",INDEX(C_CTC,$R30)/100000) -> 16.07 | N30: =IF($R30="","",INDEX(C_Compa,$R30)) -> 1.11 | O30: =IF($R30="","",INDEX(A_Att,$R30)) -> 0.79775281 | P30: =IF($R30="","",INDEX(E_Overall,$R30)) -> 2.7 | Q30: =IF($R30="","",INDEX(E_Risk,$R30)) -> Exited | R30: =IF(B30="","",MATCH(B30,M_ID,0)) -> 26
A31: =IF(B31="","",27) -> 27 | B31: =IF(Calc_Engine!I28="","",Calc_Engine!I28) -> EMP1027 | C31: =IF($R31="","",INDEX(M_Name,$R31)) -> Yash Yadav | D31: =IF($R31="","",INDEX(M_Title,$R31)) -> Senior Software Engineer | E31: =IF($R31="","",INDEX(M_Dept,$R31)) -> Engineering | F31: =IF($R31="","",INDEX(M_Level,$R31)) -> L3 | G31: =IF($R31="","",INDEX(M_Mgr,$R31)) -> Bhavana Hegde | H31: =IF($R31="","",INDEX(M_Status,$R31)) -> Active | I31: =IF($R31="","",INDEX(M_Tenure,$R31)) -> 5.9 | J31: =IF($R31="","",INDEX(P_Rating,$R31)) -> 3 | K31: =IF($R31="","",INDEX(P_9Box,$R31)) -> Core Player | L31: =IF($R31="","",INDEX(P_Elig,$R31)) -> Not Eligible | M31: =IF($R31="","",INDEX(C_CTC,$R31)/100000) -> 14.29 | N31: =IF($R31="","",INDEX(C_Compa,$R31)) -> 0.99 | O31: =IF($R31="","",INDEX(A_Att,$R31)) -> 0.924 | P31: =IF($R31="","",INDEX(E_Overall,$R31)) -> 3.62 | Q31: =IF($R31="","",INDEX(E_Risk,$R31)) -> Low | R31: =IF(B31="","",MATCH(B31,M_ID,0)) -> 27
A32: =IF(B32="","",28) -> 28 | B32: =IF(Calc_Engine!I29="","",Calc_Engine!I29) -> EMP1028 | C32: =IF($R32="","",INDEX(M_Name,$R32)) -> Gayatri Krishnan | D32: =IF($R32="","",INDEX(M_Title,$R32)) -> Operations Lead | E32: =IF($R32="","",INDEX(M_Dept,$R32)) -> Operations | F32: =IF($R32="","",INDEX(M_Level,$R32)) -> L4 | G32: =IF($R32="","",INDEX(M_Mgr,$R32)) -> Ajay Kumar | H32: =IF($R32="","",INDEX(M_Status,$R32)) -> Exited | I32: =IF($R32="","",INDEX(M_Tenure,$R32)) -> 5.1 | J32: =IF($R32="","",INDEX(P_Rating,$R32)) -> 3 | K32: =IF($R32="","",INDEX(P_9Box,$R32)) -> Future Star | L32: =IF($R32="","",INDEX(P_Elig,$R32)) -> Not Eligible | M32: =IF($R32="","",INDEX(C_CTC,$R32)/100000) -> 18.79 | N32: =IF($R32="","",INDEX(C_Compa,$R32)) -> 0.8 | O32: =IF($R32="","",INDEX(A_Att,$R32)) -> 0.69387755 | P32: =IF($R32="","",INDEX(E_Overall,$R32)) -> 2.73 | Q32: =IF($R32="","",INDEX(E_Risk,$R32)) -> Exited | R32: =IF(B32="","",MATCH(B32,M_ID,0)) -> 28
A33: =IF(B33="","",29) -> 29 | B33: =IF(Calc_Engine!I30="","",Calc_Engine!I30) -> EMP1029 | C33: =IF($R33="","",INDEX(M_Name,$R33)) -> Nisha Jain | D33: =IF($R33="","",INDEX(M_Title,$R33)) -> Senior Support Executive | E33: =IF($R33="","",INDEX(M_Dept,$R33)) -> Customer Support | F33: =IF($R33="","",INDEX(M_Level,$R33)) -> L3 | G33: =IF($R33="","",INDEX(M_Mgr,$R33)) -> Vidya Chatterjee | H33: =IF($R33="","",INDEX(M_Status,$R33)) -> Active | I33: =IF($R33="","",INDEX(M_Tenure,$R33)) -> 5.9 | J33: =IF($R33="","",INDEX(P_Rating,$R33)) -> 4 | K33: =IF($R33="","",INDEX(P_9Box,$R33)) -> High Performer | L33: =IF($R33="","",INDEX(P_Elig,$R33)) -> Eligible | M33: =IF($R33="","",INDEX(C_CTC,$R33)/100000) -> 8.91 | N33: =IF($R33="","",INDEX(C_Compa,$R33)) -> 0.62 | O33: =IF($R33="","",INDEX(A_Att,$R33)) -> 0.94 | P33: =IF($R33="","",INDEX(E_Overall,$R33)) -> 3.75 | Q33: =IF($R33="","",INDEX(E_Risk,$R33)) -> Medium | R33: =IF(B33="","",MATCH(B33,M_ID,0)) -> 29
A34: =IF(B34="","",30) -> 30 | B34: =IF(Calc_Engine!I31="","",Calc_Engine!I31) -> EMP1030 | C34: =IF($R34="","",INDEX(M_Name,$R34)) -> Rashmi Ansari | D34: =IF($R34="","",INDEX(M_Title,$R34)) -> Senior Finance Executive | E34: =IF($R34="","",INDEX(M_Dept,$R34)) -> Finance | F34: =IF($R34="","",INDEX(M_Level,$R34)) -> L3 | G34: =IF($R34="","",INDEX(M_Mgr,$R34)) -> Ravi Prabhu | H34: =IF($R34="","",INDEX(M_Status,$R34)) -> Active | I34: =IF($R34="","",INDEX(M_Tenure,$R34)) -> 5.9 | J34: =IF($R34="","",INDEX(P_Rating,$R34)) -> 3 | K34: =IF($R34="","",INDEX(P_9Box,$R34)) -> Effective Contributor | L34: =IF($R34="","",INDEX(P_Elig,$R34)) -> Not Eligible | M34: =IF($R34="","",INDEX(C_CTC,$R34)/100000) -> 12.25 | N34: =IF($R34="","",INDEX(C_Compa,$R34)) -> 0.85 | O34: =IF($R34="","",INDEX(A_Att,$R34)) -> 0.944 | P34: =IF($R34="","",INDEX(E_Overall,$R34)) -> 3.8 | Q34: =IF($R34="","",INDEX(E_Risk,$R34)) -> Low | R34: =IF(B34="","",MATCH(B34,M_ID,0)) -> 30
A35: =IF(B35="","",31) -> 31 | B35: =IF(Calc_Engine!I32="","",Calc_Engine!I32) -> EMP1031 | C35: =IF($R35="","",INDEX(M_Name,$R35)) -> Prakash Krishnan | D35: =IF($R35="","",INDEX(M_Title,$R35)) -> Senior Marketing Executive | E35: =IF($R35="","",INDEX(M_Dept,$R35)) -> Marketing | F35: =IF($R35="","",INDEX(M_Level,$R35)) -> L3 | G35: =IF($R35="","",INDEX(M_Mgr,$R35)) -> Nandini Iyer | H35: =IF($R35="","",INDEX(M_Status,$R35)) -> Active | I35: =IF($R35="","",INDEX(M_Tenure,$R35)) -> 5.9 | J35: =IF($R35="","",INDEX(P_Rating,$R35)) -> 4 | K35: =IF($R35="","",INDEX(P_9Box,$R35)) -> High Performer | L35: =IF($R35="","",INDEX(P_Elig,$R35)) -> Eligible | M35: =IF($R35="","",INDEX(C_CTC,$R35)/100000) -> 15.51 | N35: =IF($R35="","",INDEX(C_Compa,$R35)) -> 1.07 | O35: =IF($R35="","",INDEX(A_Att,$R35)) -> 0.912 | P35: =IF($R35="","",INDEX(E_Overall,$R35)) -> 3.62 | Q35: =IF($R35="","",INDEX(E_Risk,$R35)) -> Low | R35: =IF(B35="","",MATCH(B35,M_ID,0)) -> 31
A36: =IF(B36="","",32) -> 32 | B36: =IF(Calc_Engine!I33="","",Calc_Engine!I33) -> EMP1032 | C36: =IF($R36="","",INDEX(M_Name,$R36)) -> Vishal Prabhu | D36: =IF($R36="","",INDEX(M_Title,$R36)) -> Senior Operations Executive | E36: =IF($R36="","",INDEX(M_Dept,$R36)) -> Operations | F36: =IF($R36="","",INDEX(M_Level,$R36)) -> L3 | G36: =IF($R36="","",INDEX(M_Mgr,$R36)) -> Amit Kumar | H36: =IF($R36="","",INDEX(M_Status,$R36)) -> Active | I36: =IF($R36="","",INDEX(M_Tenure,$R36)) -> 5.8 | J36: =IF($R36="","",INDEX(P_Rating,$R36)) -> 3 | K36: =IF($R36="","",INDEX(P_9Box,$R36)) -> Core Player | L36: =IF($R36="","",INDEX(P_Elig,$R36)) -> Not Eligible | M36: =IF($R36="","",INDEX(C_CTC,$R36)/100000) -> 12.05 | N36: =IF($R36="","",INDEX(C_Compa,$R36)) -> 0.83 | O36: =IF($R36="","",INDEX(A_Att,$R36)) -> 0.908 | P36: =IF($R36="","",INDEX(E_Overall,$R36)) -> 3.23 | Q36: =IF($R36="","",INDEX(E_Risk,$R36)) -> Medium | R36: =IF(B36="","",MATCH(B36,M_ID,0)) -> 32
A37: =IF(B37="","",33) -> 33 | B37: =IF(Calc_Engine!I34="","",Calc_Engine!I34) -> EMP1033 | C37: =IF($R37="","",INDEX(M_Name,$R37)) -> Gayatri Tiwari | D37: =IF($R37="","",INDEX(M_Title,$R37)) -> Regional Sales Manager | E37: =IF($R37="","",INDEX(M_Dept,$R37)) -> Sales | F37: =IF($R37="","",INDEX(M_Level,$R37)) -> L6 | G37: =IF($R37="","",INDEX(M_Mgr,$R37)) -> Akash Bansal | H37: =IF($R37="","",INDEX(M_Status,$R37)) -> Active | I37: =IF($R37="","",INDEX(M_Tenure,$R37)) -> 5.8 | J37: =IF($R37="","",INDEX(P_Rating,$R37)) -> 4 | K37: =IF($R37="","",INDEX(P_9Box,$R37)) -> Star | L37: =IF($R37="","",INDEX(P_Elig,$R37)) -> Eligible | M37: =IF($R37="","",INDEX(C_CTC,$R37)/100000) -> 43.45 | N37: =IF($R37="","",INDEX(C_Compa,$R37)) -> 0.81 | O37: =IF($R37="","",INDEX(A_Att,$R37)) -> 0.956 | P37: =IF($R37="","",INDEX(E_Overall,$R37)) -> 2.1 | Q37: =IF($R37="","",INDEX(E_Risk,$R37)) -> High | R37: =IF(B37="","",MATCH(B37,M_ID,0)) -> 33
A38: =IF(B38="","",34) -> 34 | B38: =IF(Calc_Engine!I35="","",Calc_Engine!I35) -> EMP1034 | C38: =IF($R38="","",INDEX(M_Name,$R38)) -> Aditi Varghese | D38: =IF($R38="","",INDEX(M_Title,$R38)) -> Tech Lead | E38: =IF($R38="","",INDEX(M_Dept,$R38)) -> Engineering | F38: =IF($R38="","",INDEX(M_Level,$R38)) -> L4 | G38: =IF($R38="","",INDEX(M_Mgr,$R38)) -> Vikas Singh | H38: =IF($R38="","",INDEX(M_Status,$R38)) -> Active | I38: =IF($R38="","",INDEX(M_Tenure,$R38)) -> 5.7 | J38: =IF($R38="","",INDEX(P_Rating,$R38)) -> 2 | K38: =IF($R38="","",INDEX(P_9Box,$R38)) -> Underperformer | L38: =IF($R38="","",INDEX(P_Elig,$R38)) -> Not Eligible | M38: =IF($R38="","",INDEX(C_CTC,$R38)/100000) -> 24.27 | N38: =IF($R38="","",INDEX(C_Compa,$R38)) -> 1.04 | O38: =IF($R38="","",INDEX(A_Att,$R38)) -> 0.916 | P38: =IF($R38="","",INDEX(E_Overall,$R38)) -> 2.7 | Q38: =IF($R38="","",INDEX(E_Risk,$R38)) -> Low | R38: =IF(B38="","",MATCH(B38,M_ID,0)) -> 34
A39: =IF(B39="","",35) -> 35 | B39: =IF(Calc_Engine!I36="","",Calc_Engine!I36) -> EMP1035 | C39: =IF($R39="","",INDEX(M_Name,$R39)) -> Dev Gupta | D39: =IF($R39="","",INDEX(M_Title,$R39)) -> Senior Operations Executive | E39: =IF($R39="","",INDEX(M_Dept,$R39)) -> Operations | F39: =IF($R39="","",INDEX(M_Level,$R39)) -> L3 | G39: =IF($R39="","",INDEX(M_Mgr,$R39)) -> Ankit Khanna | H39: =IF($R39="","",INDEX(M_Status,$R39)) -> Active | I39: =IF($R39="","",INDEX(M_Tenure,$R39)) -> 5.7 | J39: =IF($R39="","",INDEX(P_Rating,$R39)) -> 4 | K39: =IF($R39="","",INDEX(P_9Box,$R39)) -> Star | L39: =IF($R39="","",INDEX(P_Elig,$R39)) -> Not Eligible | M39: =IF($R39="","",INDEX(C_CTC,$R39)/100000) -> 11.85 | N39: =IF($R39="","",INDEX(C_Compa,$R39)) -> 0.82 | O39: =IF($R39="","",INDEX(A_Att,$R39)) -> 0.928 | P39: =IF($R39="","",INDEX(E_Overall,$R39)) -> 3.68 | Q39: =IF($R39="","",INDEX(E_Risk,$R39)) -> Medium | R39: =IF(B39="","",MATCH(B39,M_ID,0)) -> 35
A40: =IF(B40="","",36) -> 36 | B40: =IF(Calc_Engine!I37="","",Calc_Engine!I37) -> EMP1036 | C40: =IF($R40="","",INDEX(M_Name,$R40)) -> Anjali Thomas | D40: =IF($R40="","",INDEX(M_Title,$R40)) -> Senior HR Business Partner | E40: =IF($R40="","",INDEX(M_Dept,$R40)) -> Human Resources | F40: =IF($R40="","",INDEX(M_Level,$R40)) -> L4 | G40: =IF($R40="","",INDEX(M_Mgr,$R40)) -> Akash Das | H40: =IF($R40="","",INDEX(M_Status,$R40)) -> Active | I40: =IF($R40="","",INDEX(M_Tenure,$R40)) -> 5.7 | J40: =IF($R40="","",INDEX(P_Rating,$R40)) -> 2 | K40: =IF($R40="","",INDEX(P_9Box,$R40)) -> Underperformer | L40: =IF($R40="","",INDEX(P_Elig,$R40)) -> Not Eligible | M40: =IF($R40="","",INDEX(C_CTC,$R40)/100000) -> 21.09 | N40: =IF($R40="","",INDEX(C_Compa,$R40)) -> 0.9 | O40: =IF($R40="","",INDEX(A_Att,$R40)) -> 0.912 | P40: =IF($R40="","",INDEX(E_Overall,$R40)) -> 2.9 | Q40: =IF($R40="","",INDEX(E_Risk,$R40)) -> Low | R40: =IF(B40="","",MATCH(B40,M_ID,0)) -> 36
A41: =IF(B41="","",37) -> 37 | B41: =IF(Calc_Engine!I38="","",Calc_Engine!I38) -> EMP1037 | C41: =IF($R41="","",INDEX(M_Name,$R41)) -> Aniket Khanna | D41: =IF($R41="","",INDEX(M_Title,$R41)) -> Senior Product Manager | E41: =IF($R41="","",INDEX(M_Dept,$R41)) -> Product | F41: =IF($R41="","",INDEX(M_Level,$R41)) -> L4 | G41: =IF($R41="","",INDEX(M_Mgr,$R41)) -> Mansi Pillai | H41: =IF($R41="","",INDEX(M_Status,$R41)) -> Active | I41: =IF($R41="","",INDEX(M_Tenure,$R41)) -> 5.7 | J41: =IF($R41="","",INDEX(P_Rating,$R41)) -> 4 | K41: =IF($R41="","",INDEX(P_9Box,$R41)) -> High Performer | L41: =IF($R41="","",INDEX(P_Elig,$R41)) -> Eligible | M41: =IF($R41="","",INDEX(C_CTC,$R41)/100000) -> 21.22 | N41: =IF($R41="","",INDEX(C_Compa,$R41)) -> 0.91 | O41: =IF($R41="","",INDEX(A_Att,$R41)) -> 0.892 | P41: =IF($R41="","",INDEX(E_Overall,$R41)) -> 3.75 | Q41: =IF($R41="","",INDEX(E_Risk,$R41)) -> Low | R41: =IF(B41="","",MATCH(B41,M_ID,0)) -> 37
A42: =IF(B42="","",38) -> 38 | B42: =IF(Calc_Engine!I39="","",Calc_Engine!I39) -> EMP1038 | C42: =IF($R42="","",INDEX(M_Name,$R42)) -> Varun Reddy | D42: =IF($R42="","",INDEX(M_Title,$R42)) -> Senior Support Executive | E42: =IF($R42="","",INDEX(M_Dept,$R42)) -> Customer Support | F42: =IF($R42="","",INDEX(M_Level,$R42)) -> L3 | G42: =IF($R42="","",INDEX(M_Mgr,$R42)) -> Anjali Iyer | H42: =IF($R42="","",INDEX(M_Status,$R42)) -> Active | I42: =IF($R42="","",INDEX(M_Tenure,$R42)) -> 5.7 | J42: =IF($R42="","",INDEX(P_Rating,$R42)) -> 5 | K42: =IF($R42="","",INDEX(P_9Box,$R42)) -> Star | L42: =IF($R42="","",INDEX(P_Elig,$R42)) -> Eligible | M42: =IF($R42="","",INDEX(C_CTC,$R42)/100000) -> 9.78 | N42: =IF($R42="","",INDEX(C_Compa,$R42)) -> 0.68 | O42: =IF($R42="","",INDEX(A_Att,$R42)) -> 0.94 | P42: =IF($R42="","",INDEX(E_Overall,$R42)) -> 4.3 | Q42: =IF($R42="","",INDEX(E_Risk,$R42)) -> Medium | R42: =IF(B42="","",MATCH(B42,M_ID,0)) -> 38
A43: =IF(B43="","",39) -> 39 | B43: =IF(Calc_Engine!I40="","",Calc_Engine!I40) -> EMP1039 | C43: =IF($R43="","",INDEX(M_Name,$R43)) -> Karan Patel | D43: =IF($R43="","",INDEX(M_Title,$R43)) -> Senior Finance Manager | E43: =IF($R43="","",INDEX(M_Dept,$R43)) -> Finance | F43: =IF($R43="","",INDEX(M_Level,$R43)) -> L6 | G43: =IF($R43="","",INDEX(M_Mgr,$R43)) -> Pooja Das | H43: =IF($R43="","",INDEX(M_Status,$R43)) -> Active | I43: =IF($R43="","",INDEX(M_Tenure,$R43)) -> 5.6 | J43: =IF($R43="","",INDEX(P_Rating,$R43)) -> 4 | K43: =IF($R43="","",INDEX(P_9Box,$R43)) -> Star | L43: =IF($R43="","",INDEX(P_Elig,$R43)) -> Eligible | M43: =IF($R43="","",INDEX(C_CTC,$R43)/100000) -> 62.3 | N43: =IF($R43="","",INDEX(C_Compa,$R43)) -> 1.16 | O43: =IF($R43="","",INDEX(A_Att,$R43)) -> 0.928 | P43: =IF($R43="","",INDEX(E_Overall,$R43)) -> 2.73 | Q43: =IF($R43="","",INDEX(E_Risk,$R43)) -> Medium | R43: =IF(B43="","",MATCH(B43,M_ID,0)) -> 39
A44: =IF(B44="","",40) -> 40 | B44: =IF(Calc_Engine!I41="","",Calc_Engine!I41) -> EMP1040 | C44: =IF($R44="","",INDEX(M_Name,$R44)) -> Sanjay Mehta | D44: =IF($R44="","",INDEX(M_Title,$R44)) -> Senior HR Business Partner | E44: =IF($R44="","",INDEX(M_Dept,$R44)) -> Human Resources | F44: =IF($R44="","",INDEX(M_Level,$R44)) -> L4 | G44: =IF($R44="","",INDEX(M_Mgr,$R44)) -> Prakash Das | H44: =IF($R44="","",INDEX(M_Status,$R44)) -> Active | I44: =IF($R44="","",INDEX(M_Tenure,$R44)) -> 5.6 | J44: =IF($R44="","",INDEX(P_Rating,$R44)) -> 2 | K44: =IF($R44="","",INDEX(P_9Box,$R44)) -> Inconsistent Player | L44: =IF($R44="","",INDEX(P_Elig,$R44)) -> Not Eligible | M44: =IF($R44="","",INDEX(C_CTC,$R44)/100000) -> 21.13 | N44: =IF($R44="","",INDEX(C_Compa,$R44)) -> 0.9 | O44: =IF($R44="","",INDEX(A_Att,$R44)) -> 0.892 | P44: =IF($R44="","",INDEX(E_Overall,$R44)) -> 2.5 | Q44: =IF($R44="","",INDEX(E_Risk,$R44)) -> Low | R44: =IF(B44="","",MATCH(B44,M_ID,0)) -> 40
A45: =IF(B45="","",41) -> 41 | B45: =IF(Calc_Engine!I42="","",Calc_Engine!I42) -> EMP1041 | C45: =IF($R45="","",INDEX(M_Name,$R45)) -> Nisha Mehta | D45: =IF($R45="","",INDEX(M_Title,$R45)) -> HR Business Partner | E45: =IF($R45="","",INDEX(M_Dept,$R45)) -> Human Resources | F45: =IF($R45="","",INDEX(M_Level,$R45)) -> L3 | G45: =IF($R45="","",INDEX(M_Mgr,$R45)) -> Akash Das | H45: =IF($R45="","",INDEX(M_Status,$R45)) -> Exited | I45: =IF($R45="","",INDEX(M_Tenure,$R45)) -> 5.4 | J45: =IF($R45="","",INDEX(P_Rating,$R45)) -> 2 | K45: =IF($R45="","",INDEX(P_9Box,$R45)) -> Underperformer | L45: =IF($R45="","",INDEX(P_Elig,$R45)) -> Not Eligible | M45: =IF($R45="","",INDEX(C_CTC,$R45)/100000) -> 10.12 | N45: =IF($R45="","",INDEX(C_Compa,$R45)) -> 0.7 | O45: =IF($R45="","",INDEX(A_Att,$R45)) -> 0.81067961 | P45: =IF($R45="","",INDEX(E_Overall,$R45)) -> 3.2 | Q45: =IF($R45="","",INDEX(E_Risk,$R45)) -> Exited | R45: =IF(B45="","",MATCH(B45,M_ID,0)) -> 41
A46: =IF(B46="","",42) -> 42 | B46: =IF(Calc_Engine!I43="","",Calc_Engine!I43) -> EMP1042 | C46: =IF($R46="","",INDEX(M_Name,$R46)) -> Tejaswini Hegde | D46: =IF($R46="","",INDEX(M_Title,$R46)) -> Engineering Manager | E46: =IF($R46="","",INDEX(M_Dept,$R46)) -> Engineering | F46: =IF($R46="","",INDEX(M_Level,$R46)) -> L5 | G46: =IF($R46="","",INDEX(M_Mgr,$R46)) -> Yamini Nair | H46: =IF($R46="","",INDEX(M_Status,$R46)) -> Active | I46: =IF($R46="","",INDEX(M_Tenure,$R46)) -> 5.5 | J46: =IF($R46="","",INDEX(P_Rating,$R46)) -> 2 | K46: =IF($R46="","",INDEX(P_9Box,$R46)) -> Inconsistent Player | L46: =IF($R46="","",INDEX(P_Elig,$R46)) -> Not Eligible | M46: =IF($R46="","",INDEX(C_CTC,$R46)/100000) -> 36.25 | N46: =IF($R46="","",INDEX(C_Compa,$R46)) -> 0.99 | O46: =IF($R46="","",INDEX(A_Att,$R46)) -> 0.944 | P46: =IF($R46="","",INDEX(E_Overall,$R46)) -> 3.13 | Q46: =IF($R46="","",INDEX(E_Risk,$R46)) -> Low | R46: =IF(B46="","",MATCH(B46,M_ID,0)) -> 42
A47: =IF(B47="","",43) -> 43 | B47: =IF(Calc_Engine!I44="","",Calc_Engine!I44) -> EMP1043 | C47: =IF($R47="","",INDEX(M_Name,$R47)) -> Trisha Jain | D47: =IF($R47="","",INDEX(M_Title,$R47)) -> Senior Analytics Manager | E47: =IF($R47="","",INDEX(M_Dept,$R47)) -> Data & Analytics | F47: =IF($R47="","",INDEX(M_Level,$R47)) -> L6 | G47: =IF($R47="","",INDEX(M_Mgr,$R47)) -> Aishwarya Fernandes | H47: =IF($R47="","",INDEX(M_Status,$R47)) -> Active | I47: =IF($R47="","",INDEX(M_Tenure,$R47)) -> 5.5 | J47: =IF($R47="","",INDEX(P_Rating,$R47)) -> 3 | K47: =IF($R47="","",INDEX(P_9Box,$R47)) -> Core Player | L47: =IF($R47="","",INDEX(P_Elig,$R47)) -> Not Eligible | M47: =IF($R47="","",INDEX(C_CTC,$R47)/100000) -> 56.47 | N47: =IF($R47="","",INDEX(C_Compa,$R47)) -> 1.05 | O47: =IF($R47="","",INDEX(A_Att,$R47)) -> 0.848 | P47: =IF($R47="","",INDEX(E_Overall,$R47)) -> 2.42 | Q47: =IF($R47="","",INDEX(E_Risk,$R47)) -> Low | R47: =IF(B47="","",MATCH(B47,M_ID,0)) -> 43
A48: =IF(B48="","",44) -> 44 | B48: =IF(Calc_Engine!I45="","",Calc_Engine!I45) -> EMP1044 | C48: =IF($R48="","",INDEX(M_Name,$R48)) -> Rohan Patel | D48: =IF($R48="","",INDEX(M_Title,$R48)) -> Senior Software Engineer | E48: =IF($R48="","",INDEX(M_Dept,$R48)) -> Engineering | F48: =IF($R48="","",INDEX(M_Level,$R48)) -> L3 | G48: =IF($R48="","",INDEX(M_Mgr,$R48)) -> Isha Jain | H48: =IF($R48="","",INDEX(M_Status,$R48)) -> Active | I48: =IF($R48="","",INDEX(M_Tenure,$R48)) -> 5.5 | J48: =IF($R48="","",INDEX(P_Rating,$R48)) -> 3 | K48: =IF($R48="","",INDEX(P_9Box,$R48)) -> Future Star | L48: =IF($R48="","",INDEX(P_Elig,$R48)) -> Not Eligible | M48: =IF($R48="","",INDEX(C_CTC,$R48)/100000) -> 15.14 | N48: =IF($R48="","",INDEX(C_Compa,$R48)) -> 1.05 | O48: =IF($R48="","",INDEX(A_Att,$R48)) -> 0.896 | P48: =IF($R48="","",INDEX(E_Overall,$R48)) -> 3.52 | Q48: =IF($R48="","",INDEX(E_Risk,$R48)) -> Low | R48: =IF(B48="","",MATCH(B48,M_ID,0)) -> 44
A49: =IF(B49="","",45) -> 45 | B49: =IF(Calc_Engine!I46="","",Calc_Engine!I46) -> EMP1045 | C49: =IF($R49="","",INDEX(M_Name,$R49)) -> Vikas Chatterjee | D49: =IF($R49="","",INDEX(M_Title,$R49)) -> Operations Lead | E49: =IF($R49="","",INDEX(M_Dept,$R49)) -> Operations | F49: =IF($R49="","",INDEX(M_Level,$R49)) -> L4 | G49: =IF($R49="","",INDEX(M_Mgr,$R49)) -> Yash Shah | H49: =IF($R49="","",INDEX(M_Status,$R49)) -> Exited | I49: =IF($R49="","",INDEX(M_Tenure,$R49)) -> 5.2 | J49: =IF($R49="","",INDEX(P_Rating,$R49)) -> 3 | K49: =IF($R49="","",INDEX(P_9Box,$R49)) -> Core Player | L49: =IF($R49="","",INDEX(P_Elig,$R49)) -> Not Eligible | M49: =IF($R49="","",INDEX(C_CTC,$R49)/100000) -> 17.24 | N49: =IF($R49="","",INDEX(C_Compa,$R49)) -> 0.74 | O49: =IF($R49="","",INDEX(A_Att,$R49)) -> 0.85795455 | P49: =IF($R49="","",INDEX(E_Overall,$R49)) -> 2.68 | Q49: =IF($R49="","",INDEX(E_Risk,$R49)) -> Exited | R49: =IF(B49="","",MATCH(B49,M_ID,0)) -> 45
A50: =IF(B50="","",46) -> 46 | B50: =IF(Calc_Engine!I47="","",Calc_Engine!I47) -> EMP1046 | C50: =IF($R50="","",INDEX(M_Name,$R50)) -> Karan Gowda | D50: =IF($R50="","",INDEX(M_Title,$R50)) -> Senior Operations Executive | E50: =IF($R50="","",INDEX(M_Dept,$R50)) -> Operations | F50: =IF($R50="","",INDEX(M_Level,$R50)) -> L3 | G50: =IF($R50="","",INDEX(M_Mgr,$R50)) -> Pallavi Shah | H50: =IF($R50="","",INDEX(M_Status,$R50)) -> Active | I50: =IF($R50="","",INDEX(M_Tenure,$R50)) -> 5.5 | J50: =IF($R50="","",INDEX(P_Rating,$R50)) -> 3 | K50: =IF($R50="","",INDEX(P_9Box,$R50)) -> Core Player | L50: =IF($R50="","",INDEX(P_Elig,$R50)) -> Not Eligible | M50: =IF($R50="","",INDEX(C_CTC,$R50)/100000) -> 13.6 | N50: =IF($R50="","",INDEX(C_Compa,$R50)) -> 0.94 | O50: =IF($R50="","",INDEX(A_Att,$R50)) -> 0.92 | P50: =IF($R50="","",INDEX(E_Overall,$R50)) -> 3.57 | Q50: =IF($R50="","",INDEX(E_Risk,$R50)) -> Low | R50: =IF(B50="","",MATCH(B50,M_ID,0)) -> 46
A51: =IF(B51="","",47) -> 47 | B51: =IF(Calc_Engine!I48="","",Calc_Engine!I48) -> EMP1047 | C51: =IF($R51="","",INDEX(M_Name,$R51)) -> Keerthi Gupta | D51: =IF($R51="","",INDEX(M_Title,$R51)) -> Support Team Lead | E51: =IF($R51="","",INDEX(M_Dept,$R51)) -> Customer Support | F51: =IF($R51="","",INDEX(M_Level,$R51)) -> L4 | G51: =IF($R51="","",INDEX(M_Mgr,$R51)) -> Vidya Chatterjee | H51: =IF($R51="","",INDEX(M_Status,$R51)) -> Active | I51: =IF($R51="","",INDEX(M_Tenure,$R51)) -> 5.5 | J51: =IF($R51="","",INDEX(P_Rating,$R51)) -> 3 | K51: =IF($R51="","",INDEX(P_9Box,$R51)) -> Future Star | L51: =IF($R51="","",INDEX(P_Elig,$R51)) -> Not Eligible | M51: =IF($R51="","",INDEX(C_CTC,$R51)/100000) -> 14.75 | N51: =IF($R51="","",INDEX(C_Compa,$R51)) -> 0.63 | O51: =IF($R51="","",INDEX(A_Att,$R51)) -> 0.908 | P51: =IF($R51="","",INDEX(E_Overall,$R51)) -> 2.97 | Q51: =IF($R51="","",INDEX(E_Risk,$R51)) -> High | R51: =IF(B51="","",MATCH(B51,M_ID,0)) -> 47
A52: =IF(B52="","",48) -> 48 | B52: =IF(Calc_Engine!I49="","",Calc_Engine!I49) -> EMP1048 | C52: =IF($R52="","",INDEX(M_Name,$R52)) -> Sindhu Sharma | D52: =IF($R52="","",INDEX(M_Title,$R52)) -> Senior Data Analyst | E52: =IF($R52="","",INDEX(M_Dept,$R52)) -> Data & Analytics | F52: =IF($R52="","",INDEX(M_Level,$R52)) -> L3 | G52: =IF($R52="","",INDEX(M_Mgr,$R52)) -> Arun Mukherjee | H52: =IF($R52="","",INDEX(M_Status,$R52)) -> Active | I52: =IF($R52="","",INDEX(M_Tenure,$R52)) -> 5.5 | J52: =IF($R52="","",INDEX(P_Rating,$R52)) -> 4 | K52: =IF($R52="","",INDEX(P_9Box,$R52)) -> Star | L52: =IF($R52="","",INDEX(P_Elig,$R52)) -> Not Eligible | M52: =IF($R52="","",INDEX(C_CTC,$R52)/100000) -> 13.14 | N52: =IF($R52="","",INDEX(C_Compa,$R52)) -> 0.91 | O52: =IF($R52="","",INDEX(A_Att,$R52)) -> 0.864 | P52: =IF($R52="","",INDEX(E_Overall,$R52)) -> 3.6 | Q52: =IF($R52="","",INDEX(E_Risk,$R52)) -> Low | R52: =IF(B52="","",MATCH(B52,M_ID,0)) -> 48
A53: =IF(B53="","",49) -> 49 | B53: =IF(Calc_Engine!I50="","",Calc_Engine!I50) -> EMP1049 | C53: =IF($R53="","",INDEX(M_Name,$R53)) -> Ajay Kumar | D53: =IF($R53="","",INDEX(M_Title,$R53)) -> Operations Manager | E53: =IF($R53="","",INDEX(M_Dept,$R53)) -> Operations | F53: =IF($R53="","",INDEX(M_Level,$R53)) -> L5 | G53: =IF($R53="","",INDEX(M_Mgr,$R53)) -> Imran Mishra | H53: =IF($R53="","",INDEX(M_Status,$R53)) -> Active | I53: =IF($R53="","",INDEX(M_Tenure,$R53)) -> 5.4 | J53: =IF($R53="","",INDEX(P_Rating,$R53)) -> 4 | K53: =IF($R53="","",INDEX(P_9Box,$R53)) -> Star | L53: =IF($R53="","",INDEX(P_Elig,$R53)) -> Eligible | M53: =IF($R53="","",INDEX(C_CTC,$R53)/100000) -> 34.33 | N53: =IF($R53="","",INDEX(C_Compa,$R53)) -> 0.94 | O53: =IF($R53="","",INDEX(A_Att,$R53)) -> 0.908 | P53: =IF($R53="","",INDEX(E_Overall,$R53)) -> 2.83 | Q53: =IF($R53="","",INDEX(E_Risk,$R53)) -> High | R53: =IF(B53="","",MATCH(B53,M_ID,0)) -> 49
A54: =IF(B54="","",50) -> 50 | B54: =IF(Calc_Engine!I51="","",Calc_Engine!I51) -> EMP1050 | C54: =IF($R54="","",INDEX(M_Name,$R54)) -> Harini Choudhary | D54: =IF($R54="","",INDEX(M_Title,$R54)) -> Tech Lead | E54: =IF($R54="","",INDEX(M_Dept,$R54)) -> Engineering | F54: =IF($R54="","",INDEX(M_Level,$R54)) -> L4 | G54: =IF($R54="","",INDEX(M_Mgr,$R54)) -> Vikas Singh | H54: =IF($R54="","",INDEX(M_Status,$R54)) -> Active | I54: =IF($R54="","",INDEX(M_Tenure,$R54)) -> 5.4 | J54: =IF($R54="","",INDEX(P_Rating,$R54)) -> 3 | K54: =IF($R54="","",INDEX(P_9Box,$R54)) -> Core Player | L54: =IF($R54="","",INDEX(P_Elig,$R54)) -> Not Eligible | M54: =IF($R54="","",INDEX(C_CTC,$R54)/100000) -> 24.07 | N54: =IF($R54="","",INDEX(C_Compa,$R54)) -> 1.03 | O54: =IF($R54="","",INDEX(A_Att,$R54)) -> 0.956 | P54: =IF($R54="","",INDEX(E_Overall,$R54)) -> 3.6 | Q54: =IF($R54="","",INDEX(E_Risk,$R54)) -> Low | R54: =IF(B54="","",MATCH(B54,M_ID,0)) -> 50
A55: =IF(B55="","",51) -> 51 | B55: =IF(Calc_Engine!I52="","",Calc_Engine!I52) -> EMP1051 | C55: =IF($R55="","",INDEX(M_Name,$R55)) -> Joseph Varghese | D55: =IF($R55="","",INDEX(M_Title,$R55)) -> Regional Sales Manager | E55: =IF($R55="","",INDEX(M_Dept,$R55)) -> Sales | F55: =IF($R55="","",INDEX(M_Level,$R55)) -> L6 | G55: =IF($R55="","",INDEX(M_Mgr,$R55)) -> Akash Bansal | H55: =IF($R55="","",INDEX(M_Status,$R55)) -> Active | I55: =IF($R55="","",INDEX(M_Tenure,$R55)) -> 5.4 | J55: =IF($R55="","",INDEX(P_Rating,$R55)) -> 1 | K55: =IF($R55="","",INDEX(P_9Box,$R55)) -> Underperformer | L55: =IF($R55="","",INDEX(P_Elig,$R55)) -> Not Eligible | M55: =IF($R55="","",INDEX(C_CTC,$R55)/100000) -> 43.83 | N55: =IF($R55="","",INDEX(C_Compa,$R55)) -> 0.81 | O55: =IF($R55="","",INDEX(A_Att,$R55)) -> 0.888 | P55: =IF($R55="","",INDEX(E_Overall,$R55)) -> 3.48 | Q55: =IF($R55="","",INDEX(E_Risk,$R55)) -> Low | R55: =IF(B55="","",MATCH(B55,M_ID,0)) -> 51
A56: =IF(B56="","",52) -> 52 | B56: =IF(Calc_Engine!I53="","",Calc_Engine!I53) -> EMP1052 | C56: =IF($R56="","",INDEX(M_Name,$R56)) -> Siddharth Mehta | D56: =IF($R56="","",INDEX(M_Title,$R56)) -> Senior Software Engineer | E56: =IF($R56="","",INDEX(M_Dept,$R56)) -> Engineering | F56: =IF($R56="","",INDEX(M_Level,$R56)) -> L3 | G56: =IF($R56="","",INDEX(M_Mgr,$R56)) -> Vikas Singh | H56: =IF($R56="","",INDEX(M_Status,$R56)) -> Exited | I56: =IF($R56="","",INDEX(M_Tenure,$R56)) -> 4.6 | J56: =IF($R56="","",INDEX(P_Rating,$R56)) -> 3 | K56: =IF($R56="","",INDEX(P_9Box,$R56)) -> Core Player | L56: =IF($R56="","",INDEX(P_Elig,$R56)) -> Not Eligible | M56: =IF($R56="","",INDEX(C_CTC,$R56)/100000) -> 20.84 | N56: =IF($R56="","",INDEX(C_Compa,$R56)) -> 1.44 | O56: =IF($R56="","",INDEX(A_Att,$R56)) -> 0.76190476 | P56: =IF($R56="","",INDEX(E_Overall,$R56)) -> 2.2 | Q56: =IF($R56="","",INDEX(E_Risk,$R56)) -> Exited | R56: =IF(B56="","",MATCH(B56,M_ID,0)) -> 52
A57: =IF(B57="","",53) -> 53 | B57: =IF(Calc_Engine!I54="","",Calc_Engine!I54) -> EMP1053 | C57: =IF($R57="","",INDEX(M_Name,$R57)) -> Dev Jain | D57: =IF($R57="","",INDEX(M_Title,$R57)) -> Senior Sales Executive | E57: =IF($R57="","",INDEX(M_Dept,$R57)) -> Sales | F57: =IF($R57="","",INDEX(M_Level,$R57)) -> L3 | G57: =IF($R57="","",INDEX(M_Mgr,$R57)) -> Kavya Krishnan | H57: =IF($R57="","",INDEX(M_Status,$R57)) -> Active | I57: =IF($R57="","",INDEX(M_Tenure,$R57)) -> 5.3 | J57: =IF($R57="","",INDEX(P_Rating,$R57)) -> 5 | K57: =IF($R57="","",INDEX(P_9Box,$R57)) -> High Performer | L57: =IF($R57="","",INDEX(P_Elig,$R57)) -> Eligible | M57: =IF($R57="","",INDEX(C_CTC,$R57)/100000) -> 16.46 | N57: =IF($R57="","",INDEX(C_Compa,$R57)) -> 1.14 | O57: =IF($R57="","",INDEX(A_Att,$R57)) -> 0.94 | P57: =IF($R57="","",INDEX(E_Overall,$R57)) -> 3.52 | Q57: =IF($R57="","",INDEX(E_Risk,$R57)) -> Low | R57: =IF(B57="","",MATCH(B57,M_ID,0)) -> 53
A58: =IF(B58="","",54) -> 54 | B58: =IF(Calc_Engine!I55="","",Calc_Engine!I55) -> EMP1054 | C58: =IF($R58="","",INDEX(M_Name,$R58)) -> Ritu Patel | D58: =IF($R58="","",INDEX(M_Title,$R58)) -> Senior Operations Executive | E58: =IF($R58="","",INDEX(M_Dept,$R58)) -> Operations | F58: =IF($R58="","",INDEX(M_Level,$R58)) -> L3 | G58: =IF($R58="","",INDEX(M_Mgr,$R58)) -> Ajay Kumar | H58: =IF($R58="","",INDEX(M_Status,$R58)) -> Active | I58: =IF($R58="","",INDEX(M_Tenure,$R58)) -> 5.3 | J58: =IF($R58="","",INDEX(P_Rating,$R58)) -> 4 | K58: =IF($R58="","",INDEX(P_9Box,$R58)) -> Trusted Professional | L58: =IF($R58="","",INDEX(P_Elig,$R58)) -> Eligible | M58: =IF($R58="","",INDEX(C_CTC,$R58)/100000) -> 9.17 | N58: =IF($R58="","",INDEX(C_Compa,$R58)) -> 0.63 | O58: =IF($R58="","",INDEX(A_Att,$R58)) -> 0.952 | P58: =IF($R58="","",INDEX(E_Overall,$R58)) -> 3.28 | Q58: =IF($R58="","",INDEX(E_Risk,$R58)) -> Medium | R58: =IF(B58="","",MATCH(B58,M_ID,0)) -> 54
A59: =IF(B59="","",55) -> 55 | B59: =IF(Calc_Engine!I56="","",Calc_Engine!I56) -> EMP1055 | C59: =IF($R59="","",INDEX(M_Name,$R59)) -> Sachin Iyer | D59: =IF($R59="","",INDEX(M_Title,$R59)) -> Senior Support Executive | E59: =IF($R59="","",INDEX(M_Dept,$R59)) -> Customer Support | F59: =IF($R59="","",INDEX(M_Level,$R59)) -> L3 | G59: =IF($R59="","",INDEX(M_Mgr,$R59)) -> Ashish Varghese | H59: =IF($R59="","",INDEX(M_Status,$R59)) -> Active | I59: =IF($R59="","",INDEX(M_Tenure,$R59)) -> 5.3 | J59: =IF($R59="","",INDEX(P_Rating,$R59)) -> 3 | K59: =IF($R59="","",INDEX(P_9Box,$R59)) -> Core Player | L59: =IF($R59="","",INDEX(P_Elig,$R59)) -> Not Eligible | M59: =IF($R59="","",INDEX(C_CTC,$R59)/100000) -> 13.2 | N59: =IF($R59="","",INDEX(C_Compa,$R59)) -> 0.91 | O59: =IF($R59="","",INDEX(A_Att,$R59)) -> 0.952 | P59: =IF($R59="","",INDEX(E_Overall,$R59)) -> 3.38 | Q59: =IF($R59="","",INDEX(E_Risk,$R59)) -> Low | R59: =IF(B59="","",MATCH(B59,M_ID,0)) -> 55
A60: =IF(B60="","",56) -> 56 | B60: =IF(Calc_Engine!I57="","",Calc_Engine!I57) -> EMP1056 | C60: =IF($R60="","",INDEX(M_Name,$R60)) -> Pallavi Menon | D60: =IF($R60="","",INDEX(M_Title,$R60)) -> Senior Software Engineer | E60: =IF($R60="","",INDEX(M_Dept,$R60)) -> Engineering | F60: =IF($R60="","",INDEX(M_Level,$R60)) -> L3 | G60: =IF($R60="","",INDEX(M_Mgr,$R60)) -> Prakash Desai | H60: =IF($R60="","",INDEX(M_Status,$R60)) -> Active | I60: =IF($R60="","",INDEX(M_Tenure,$R60)) -> 5.3 | J60: =IF($R60="","",INDEX(P_Rating,$R60)) -> 3 | K60: =IF($R60="","",INDEX(P_9Box,$R60)) -> Core Player | L60: =IF($R60="","",INDEX(P_Elig,$R60)) -> Not Eligible | M60: =IF($R60="","",INDEX(C_CTC,$R60)/100000) -> 19.71 | N60: =IF($R60="","",INDEX(C_Compa,$R60)) -> 1.36 | O60: =IF($R60="","",INDEX(A_Att,$R60)) -> 0.94 | P60: =IF($R60="","",INDEX(E_Overall,$R60)) -> 2.95 | Q60: =IF($R60="","",INDEX(E_Risk,$R60)) -> Low | R60: =IF(B60="","",MATCH(B60,M_ID,0)) -> 56
A61: =IF(B61="","",57) -> 57 | B61: =IF(Calc_Engine!I58="","",Calc_Engine!I58) -> EMP1057 | C61: =IF($R61="","",INDEX(M_Name,$R61)) -> Imran Jain | D61: =IF($R61="","",INDEX(M_Title,$R61)) -> Senior Software Engineer | E61: =IF($R61="","",INDEX(M_Dept,$R61)) -> Engineering | F61: =IF($R61="","",INDEX(M_Level,$R61)) -> L3 | G61: =IF($R61="","",INDEX(M_Mgr,$R61)) -> Tejaswini Hegde | H61: =IF($R61="","",INDEX(M_Status,$R61)) -> Active | I61: =IF($R61="","",INDEX(M_Tenure,$R61)) -> 5.3 | J61: =IF($R61="","",INDEX(P_Rating,$R61)) -> 4 | K61: =IF($R61="","",INDEX(P_9Box,$R61)) -> High Performer | L61: =IF($R61="","",INDEX(P_Elig,$R61)) -> Eligible | M61: =IF($R61="","",INDEX(C_CTC,$R61)/100000) -> 19.02 | N61: =IF($R61="","",INDEX(C_Compa,$R61)) -> 1.32 | O61: =IF($R61="","",INDEX(A_Att,$R61)) -> 0.936 | P61: =IF($R61="","",INDEX(E_Overall,$R61)) -> 3.93 | Q61: =IF($R61="","",INDEX(E_Risk,$R61)) -> Low | R61: =IF(B61="","",MATCH(B61,M_ID,0)) -> 57
A62: =IF(B62="","",58) -> 58 | B62: =IF(Calc_Engine!I59="","",Calc_Engine!I59) -> EMP1058 | C62: =IF($R62="","",INDEX(M_Name,$R62)) -> Amit Gupta | D62: =IF($R62="","",INDEX(M_Title,$R62)) -> Tech Lead | E62: =IF($R62="","",INDEX(M_Dept,$R62)) -> Engineering | F62: =IF($R62="","",INDEX(M_Level,$R62)) -> L4 | G62: =IF($R62="","",INDEX(M_Mgr,$R62)) -> Fatima Choudhary | H62: =IF($R62="","",INDEX(M_Status,$R62)) -> Active | I62: =IF($R62="","",INDEX(M_Tenure,$R62)) -> 5.3 | J62: =IF($R62="","",INDEX(P_Rating,$R62)) -> 3 | K62: =IF($R62="","",INDEX(P_9Box,$R62)) -> Core Player | L62: =IF($R62="","",INDEX(P_Elig,$R62)) -> Not Eligible | M62: =IF($R62="","",INDEX(C_CTC,$R62)/100000) -> 23.73 | N62: =IF($R62="","",INDEX(C_Compa,$R62)) -> 1.01 | O62: =IF($R62="","",INDEX(A_Att,$R62)) -> 0.924 | P62: =IF($R62="","",INDEX(E_Overall,$R62)) -> 3.22 | Q62: =IF($R62="","",INDEX(E_Risk,$R62)) -> Low | R62: =IF(B62="","",MATCH(B62,M_ID,0)) -> 58
A63: =IF(B63="","",59) -> 59 | B63: =IF(Calc_Engine!I60="","",Calc_Engine!I60) -> EMP1059 | C63: =IF($R63="","",INDEX(M_Name,$R63)) -> Fatima Kulkarni | D63: =IF($R63="","",INDEX(M_Title,$R63)) -> Tech Lead | E63: =IF($R63="","",INDEX(M_Dept,$R63)) -> Engineering | F63: =IF($R63="","",INDEX(M_Level,$R63)) -> L4 | G63: =IF($R63="","",INDEX(M_Mgr,$R63)) -> Vikas Singh | H63: =IF($R63="","",INDEX(M_Status,$R63)) -> Exited | I63: =IF($R63="","",INDEX(M_Tenure,$R63)) -> 4.7 | J63: =IF($R63="","",INDEX(P_Rating,$R63)) -> 3 | K63: =IF($R63="","",INDEX(P_9Box,$R63)) -> Core Player | L63: =IF($R63="","",INDEX(P_Elig,$R63)) -> Not Eligible | M63: =IF($R63="","",INDEX(C_CTC,$R63)/100000) -> 27.64 | N63: =IF($R63="","",INDEX(C_Compa,$R63)) -> 1.18 | O63: =IF($R63="","",INDEX(A_Att,$R63)) -> 0.85 | P63: =IF($R63="","",INDEX(E_Overall,$R63)) -> 2.13 | Q63: =IF($R63="","",INDEX(E_Risk,$R63)) -> Exited | R63: =IF(B63="","",MATCH(B63,M_ID,0)) -> 59
A64: =IF(B64="","",60) -> 60 | B64: =IF(Calc_Engine!I61="","",Calc_Engine!I61) -> EMP1060 | C64: =IF($R64="","",INDEX(M_Name,$R64)) -> Isha Jain | D64: =IF($R64="","",INDEX(M_Title,$R64)) -> Engineering Manager | E64: =IF($R64="","",INDEX(M_Dept,$R64)) -> Engineering | F64: =IF($R64="","",INDEX(M_Level,$R64)) -> L5 | G64: =IF($R64="","",INDEX(M_Mgr,$R64)) -> Vikram Verma | H64: =IF($R64="","",INDEX(M_Status,$R64)) -> Active | I64: =IF($R64="","",INDEX(M_Tenure,$R64)) -> 5.3 | J64: =IF($R64="","",INDEX(P_Rating,$R64)) -> 5 | K64: =IF($R64="","",INDEX(P_9Box,$R64)) -> Star | L64: =IF($R64="","",INDEX(P_Elig,$R64)) -> Eligible | M64: =IF($R64="","",INDEX(C_CTC,$R64)/100000) -> 50.9 | N64: =IF($R64="","",INDEX(C_Compa,$R64)) -> 1.39 | O64: =IF($R64="","",INDEX(A_Att,$R64)) -> 0.904 | P64: =IF($R64="","",INDEX(E_Overall,$R64)) -> 3.82 | Q64: =IF($R64="","",INDEX(E_Risk,$R64)) -> Low | R64: =IF(B64="","",MATCH(B64,M_ID,0)) -> 60
A65: =IF(B65="","",61) -> 61 | B65: =IF(Calc_Engine!I62="","",Calc_Engine!I62) -> EMP1061 | C65: =IF($R65="","",INDEX(M_Name,$R65)) -> Sowmya Mishra | D65: =IF($R65="","",INDEX(M_Title,$R65)) -> Senior Operations Executive | E65: =IF($R65="","",INDEX(M_Dept,$R65)) -> Operations | F65: =IF($R65="","",INDEX(M_Level,$R65)) -> L3 | G65: =IF($R65="","",INDEX(M_Mgr,$R65)) -> Ankit Khanna | H65: =IF($R65="","",INDEX(M_Status,$R65)) -> Active | I65: =IF($R65="","",INDEX(M_Tenure,$R65)) -> 5.2 | J65: =IF($R65="","",INDEX(P_Rating,$R65)) -> 3 | K65: =IF($R65="","",INDEX(P_9Box,$R65)) -> Effective Contributor | L65: =IF($R65="","",INDEX(P_Elig,$R65)) -> Not Eligible | M65: =IF($R65="","",INDEX(C_CTC,$R65)/100000) -> 9.37 | N65: =IF($R65="","",INDEX(C_Compa,$R65)) -> 0.65 | O65: =IF($R65="","",INDEX(A_Att,$R65)) -> 0.912 | P65: =IF($R65="","",INDEX(E_Overall,$R65)) -> 3.18 | Q65: =IF($R65="","",INDEX(E_Risk,$R65)) -> Medium | R65: =IF(B65="","",MATCH(B65,M_ID,0)) -> 61
A66: =IF(B66="","",62) -> 62 | B66: =IF(Calc_Engine!I63="","",Calc_Engine!I63) -> EMP1062 | C66: =IF($R66="","",INDEX(M_Name,$R66)) -> Mohit Kapoor | D66: =IF($R66="","",INDEX(M_Title,$R66)) -> Tech Lead | E66: =IF($R66="","",INDEX(M_Dept,$R66)) -> Engineering | F66: =IF($R66="","",INDEX(M_Level,$R66)) -> L4 | G66: =IF($R66="","",INDEX(M_Mgr,$R66)) -> Isha Jain | H66: =IF($R66="","",INDEX(M_Status,$R66)) -> Active | I66: =IF($R66="","",INDEX(M_Tenure,$R66)) -> 5.2 | J66: =IF($R66="","",INDEX(P_Rating,$R66)) -> 3 | K66: =IF($R66="","",INDEX(P_9Box,$R66)) -> Core Player | L66: =IF($R66="","",INDEX(P_Elig,$R66)) -> Not Eligible | M66: =IF($R66="","",INDEX(C_CTC,$R66)/100000) -> 26.12 | N66: =IF($R66="","",INDEX(C_Compa,$R66)) -> 1.12 | O66: =IF($R66="","",INDEX(A_Att,$R66)) -> 0.924 | P66: =IF($R66="","",INDEX(E_Overall,$R66)) -> 2.83 | Q66: =IF($R66="","",INDEX(E_Risk,$R66)) -> Low | R66: =IF(B66="","",MATCH(B66,M_ID,0)) -> 62
A67: =IF(B67="","",63) -> 63 | B67: =IF(Calc_Engine!I64="","",Calc_Engine!I64) -> EMP1063 | C67: =IF($R67="","",INDEX(M_Name,$R67)) -> Akash Mukherjee | D67: =IF($R67="","",INDEX(M_Title,$R67)) -> Senior Software Engineer | E67: =IF($R67="","",INDEX(M_Dept,$R67)) -> Engineering | F67: =IF($R67="","",INDEX(M_Level,$R67)) -> L3 | G67: =IF($R67="","",INDEX(M_Mgr,$R67)) -> Bhavana Hegde | H67: =IF($R67="","",INDEX(M_Status,$R67)) -> Exited | I67: =IF($R67="","",INDEX(M_Tenure,$R67)) -> 4.9 | J67: =IF($R67="","",INDEX(P_Rating,$R67)) -> 3 | K67: =IF($R67="","",INDEX(P_9Box,$R67)) -> Core Player | L67: =IF($R67="","",INDEX(P_Elig,$R67)) -> Not Eligible | M67: =IF($R67="","",INDEX(C_CTC,$R67)/100000) -> 15.86 | N67: =IF($R67="","",INDEX(C_Compa,$R67)) -> 1.1 | O67: =IF($R67="","",INDEX(A_Att,$R67)) -> 0.90909091 | P67: =IF($R67="","",INDEX(E_Overall,$R67)) -> 2.95 | Q67: =IF($R67="","",INDEX(E_Risk,$R67)) -> Exited | R67: =IF(B67="","",MATCH(B67,M_ID,0)) -> 63
A68: =IF(B68="","",64) -> 64 | B68: =IF(Calc_Engine!I65="","",Calc_Engine!I65) -> EMP1064 | C68: =IF($R68="","",INDEX(M_Name,$R68)) -> Swathi Bose | D68: =IF($R68="","",INDEX(M_Title,$R68)) -> Senior Software Engineer | E68: =IF($R68="","",INDEX(M_Dept,$R68)) -> Engineering | F68: =IF($R68="","",INDEX(M_Level,$R68)) -> L3 | G68: =IF($R68="","",INDEX(M_Mgr,$R68)) -> Isha Jain | H68: =IF($R68="","",INDEX(M_Status,$R68)) -> Active | I68: =IF($R68="","",INDEX(M_Tenure,$R68)) -> 5.2 | J68: =IF($R68="","",INDEX(P_Rating,$R68)) -> 3 | K68: =IF($R68="","",INDEX(P_9Box,$R68)) -> Core Player | L68: =IF($R68="","",INDEX(P_Elig,$R68)) -> Not Eligible | M68: =IF($R68="","",INDEX(C_CTC,$R68)/100000) -> 19.6 | N68: =IF($R68="","",INDEX(C_Compa,$R68)) -> 1.36 | O68: =IF($R68="","",INDEX(A_Att,$R68)) -> 0.936 | P68: =IF($R68="","",INDEX(E_Overall,$R68)) -> 2.68 | Q68: =IF($R68="","",INDEX(E_Risk,$R68)) -> Low | R68: =IF(B68="","",MATCH(B68,M_ID,0)) -> 64
A69: =IF(B69="","",65) -> 65 | B69: =IF(Calc_Engine!I66="","",Calc_Engine!I66) -> EMP1065 | C69: =IF($R69="","",INDEX(M_Name,$R69)) -> Rohit Iyer | D69: =IF($R69="","",INDEX(M_Title,$R69)) -> Senior Operations Executive | E69: =IF($R69="","",INDEX(M_Dept,$R69)) -> Operations | F69: =IF($R69="","",INDEX(M_Level,$R69)) -> L3 | G69: =IF($R69="","",INDEX(M_Mgr,$R69)) -> Pallavi Nair | H69: =IF($R69="","",INDEX(M_Status,$R69)) -> Active | I69: =IF($R69="","",INDEX(M_Tenure,$R69)) -> 5.1 | J69: =IF($R69="","",INDEX(P_Rating,$R69)) -> 4 | K69: =IF($R69="","",INDEX(P_9Box,$R69)) -> Star | L69: =IF($R69="","",INDEX(P_Elig,$R69)) -> Eligible | M69: =IF($R69="","",INDEX(C_CTC,$R69)/100000) -> 9.98 | N69: =IF($R69="","",INDEX(C_Compa,$R69)) -> 0.69 | O69: =IF($R69="","",INDEX(A_Att,$R69)) -> 0.94 | P69: =IF($R69="","",INDEX(E_Overall,$R69)) -> 3.97 | Q69: =IF($R69="","",INDEX(E_Risk,$R69)) -> Medium | R69: =IF(B69="","",MATCH(B69,M_ID,0)) -> 65
A70: =IF(B70="","",66) -> 66 | B70: =IF(Calc_Engine!I67="","",Calc_Engine!I67) -> EMP1066 | C70: =IF($R70="","",INDEX(M_Name,$R70)) -> Ajay Joshi | D70: =IF($R70="","",INDEX(M_Title,$R70)) -> Operations Lead | E70: =IF($R70="","",INDEX(M_Dept,$R70)) -> Operations | F70: =IF($R70="","",INDEX(M_Level,$R70)) -> L4 | G70: =IF($R70="","",INDEX(M_Mgr,$R70)) -> Nandini Fernandes | H70: =IF($R70="","",INDEX(M_Status,$R70)) -> Active | I70: =IF($R70="","",INDEX(M_Tenure,$R70)) -> 5.1 | J70: =IF($R70="","",INDEX(P_Rating,$R70)) -> 2 | K70: =IF($R70="","",INDEX(P_9Box,$R70)) -> Underperformer | L70: =IF($R70="","",INDEX(P_Elig,$R70)) -> Not Eligible | M70: =IF($R70="","",INDEX(C_CTC,$R70)/100000) -> 17.22 | N70: =IF($R70="","",INDEX(C_Compa,$R70)) -> 0.74 | O70: =IF($R70="","",INDEX(A_Att,$R70)) -> 0.924 | P70: =IF($R70="","",INDEX(E_Overall,$R70)) -> 3.02 | Q70: =IF($R70="","",INDEX(E_Risk,$R70)) -> Low | R70: =IF(B70="","",MATCH(B70,M_ID,0)) -> 66
A71: =IF(B71="","",67) -> 67 | B71: =IF(Calc_Engine!I68="","",Calc_Engine!I68) -> EMP1067 | C71: =IF($R71="","",INDEX(M_Name,$R71)) -> Akash Bansal | D71: =IF($R71="","",INDEX(M_Title,$R71)) -> Head of Sales | E71: =IF($R71="","",INDEX(M_Dept,$R71)) -> Sales | F71: =IF($R71="","",INDEX(M_Level,$R71)) -> L7 | G71: =IF($R71="","",INDEX(M_Mgr,$R71)) -> Arvind Rao (CEO) | H71: =IF($R71="","",INDEX(M_Status,$R71)) -> Active | I71: =IF($R71="","",INDEX(M_Tenure,$R71)) -> 5.1 | J71: =IF($R71="","",INDEX(P_Rating,$R71)) -> 3 | K71: =IF($R71="","",INDEX(P_9Box,$R71)) -> Core Player | L71: =IF($R71="","",INDEX(P_Elig,$R71)) -> Not Eligible | M71: =IF($R71="","",INDEX(C_CTC,$R71)/100000) -> 76.56 | N71: =IF($R71="","",INDEX(C_Compa,$R71)) -> 0.93 | O71: =IF($R71="","",INDEX(A_Att,$R71)) -> 0.932 | P71: =IF($R71="","",INDEX(E_Overall,$R71)) -> 3.15 | Q71: =IF($R71="","",INDEX(E_Risk,$R71)) -> Low | R71: =IF(B71="","",MATCH(B71,M_ID,0)) -> 67
A72: =IF(B72="","",68) -> 68 | B72: =IF(Calc_Engine!I69="","",Calc_Engine!I69) -> EMP1068 | C72: =IF($R72="","",INDEX(M_Name,$R72)) -> Pooja Mehta | D72: =IF($R72="","",INDEX(M_Title,$R72)) -> Support Team Lead | E72: =IF($R72="","",INDEX(M_Dept,$R72)) -> Customer Support | F72: =IF($R72="","",INDEX(M_Level,$R72)) -> L4 | G72: =IF($R72="","",INDEX(M_Mgr,$R72)) -> Isha Verma | H72: =IF($R72="","",INDEX(M_Status,$R72)) -> Active | I72: =IF($R72="","",INDEX(M_Tenure,$R72)) -> 5 | J72: =IF($R72="","",INDEX(P_Rating,$R72)) -> 3 | K72: =IF($R72="","",INDEX(P_9Box,$R72)) -> Effective Contributor | L72: =IF($R72="","",INDEX(P_Elig,$R72)) -> Not Eligible | M72: =IF($R72="","",INDEX(C_CTC,$R72)/100000) -> 16.03 | N72: =IF($R72="","",INDEX(C_Compa,$R72)) -> 0.68 | O72: =IF($R72="","",INDEX(A_Att,$R72)) -> 0.944 | P72: =IF($R72="","",INDEX(E_Overall,$R72)) -> 3.37 | Q72: =IF($R72="","",INDEX(E_Risk,$R72)) -> Low | R72: =IF(B72="","",MATCH(B72,M_ID,0)) -> 68
A73: =IF(B73="","",69) -> 69 | B73: =IF(Calc_Engine!I70="","",Calc_Engine!I70) -> EMP1069 | C73: =IF($R73="","",INDEX(M_Name,$R73)) -> Akash Dsouza | D73: =IF($R73="","",INDEX(M_Title,$R73)) -> Senior Support Manager | E73: =IF($R73="","",INDEX(M_Dept,$R73)) -> Customer Support | F73: =IF($R73="","",INDEX(M_Level,$R73)) -> L6 | G73: =IF($R73="","",INDEX(M_Mgr,$R73)) -> Vikram Joshi | H73: =IF($R73="","",INDEX(M_Status,$R73)) -> Active | I73: =IF($R73="","",INDEX(M_Tenure,$R73)) -> 5 | J73: =IF($R73="","",INDEX(P_Rating,$R73)) -> 5 | K73: =IF($R73="","",INDEX(P_9Box,$R73)) -> Star | L73: =IF($R73="","",INDEX(P_Elig,$R73)) -> Eligible | M73: =IF($R73="","",INDEX(C_CTC,$R73)/100000) -> 40.97 | N73: =IF($R73="","",INDEX(C_Compa,$R73)) -> 0.76 | O73: =IF($R73="","",INDEX(A_Att,$R73)) -> 0.9 | P73: =IF($R73="","",INDEX(E_Overall,$R73)) -> 4.1 | Q73: =IF($R73="","",INDEX(E_Risk,$R73)) -> Medium | R73: =IF(B73="","",MATCH(B73,M_ID,0)) -> 69
A74: =IF(B74="","",70) -> 70 | B74: =IF(Calc_Engine!I71="","",Calc_Engine!I71) -> EMP1070 | C74: =IF($R74="","",INDEX(M_Name,$R74)) -> Naveen Mehta | D74: =IF($R74="","",INDEX(M_Title,$R74)) -> Senior Data Analyst | E74: =IF($R74="","",INDEX(M_Dept,$R74)) -> Data & Analytics | F74: =IF($R74="","",INDEX(M_Level,$R74)) -> L3 | G74: =IF($R74="","",INDEX(M_Mgr,$R74)) -> Arun Mukherjee | H74: =IF($R74="","",INDEX(M_Status,$R74)) -> Exited | I74: =IF($R74="","",INDEX(M_Tenure,$R74)) -> 4.4 | J74: =IF($R74="","",INDEX(P_Rating,$R74)) -> 3 | K74: =IF($R74="","",INDEX(P_9Box,$R74)) -> Core Player | L74: =IF($R74="","",INDEX(P_Elig,$R74)) -> Not Eligible | M74: =IF($R74="","",INDEX(C_CTC,$R74)/100000) -> 17.87 | N74: =IF($R74="","",INDEX(C_Compa,$R74)) -> 1.24 | O74: =IF($R74="","",INDEX(A_Att,$R74)) -> 0.88636364 | P74: =IF($R74="","",INDEX(E_Overall,$R74)) -> 3.25 | Q74: =IF($R74="","",INDEX(E_Risk,$R74)) -> Exited | R74: =IF(B74="","",MATCH(B74,M_ID,0)) -> 70
A75: =IF(B75="","",71) -> 71 | B75: =IF(Calc_Engine!I72="","",Calc_Engine!I72) -> EMP1071 | C75: =IF($R75="","",INDEX(M_Name,$R75)) -> Varsha Siddiqui | D75: =IF($R75="","",INDEX(M_Title,$R75)) -> Tech Lead | E75: =IF($R75="","",INDEX(M_Dept,$R75)) -> Engineering | F75: =IF($R75="","",INDEX(M_Level,$R75)) -> L4 | G75: =IF($R75="","",INDEX(M_Mgr,$R75)) -> Madhuri Menon | H75: =IF($R75="","",INDEX(M_Status,$R75)) -> Active | I75: =IF($R75="","",INDEX(M_Tenure,$R75)) -> 5 | J75: =IF($R75="","",INDEX(P_Rating,$R75)) -> 4 | K75: =IF($R75="","",INDEX(P_9Box,$R75)) -> High Performer | L75: =IF($R75="","",INDEX(P_Elig,$R75)) -> Eligible | M75: =IF($R75="","",INDEX(C_CTC,$R75)/100000) -> 25.25 | N75: =IF($R75="","",INDEX(C_Compa,$R75)) -> 1.08 | O75: =IF($R75="","",INDEX(A_Att,$R75)) -> 0.928 | P75: =IF($R75="","",INDEX(E_Overall,$R75)) -> 2.68 | Q75: =IF($R75="","",INDEX(E_Risk,$R75)) -> Medium | R75: =IF(B75="","",MATCH(B75,M_ID,0)) -> 71
A76: =IF(B76="","",72) -> 72 | B76: =IF(Calc_Engine!I73="","",Calc_Engine!I73) -> EMP1072 | C76: =IF($R76="","",INDEX(M_Name,$R76)) -> Rajesh Shah | D76: =IF($R76="","",INDEX(M_Title,$R76)) -> Marketing Lead | E76: =IF($R76="","",INDEX(M_Dept,$R76)) -> Marketing | F76: =IF($R76="","",INDEX(M_Level,$R76)) -> L4 | G76: =IF($R76="","",INDEX(M_Mgr,$R76)) -> Isha Chatterjee | H76: =IF($R76="","",INDEX(M_Status,$R76)) -> Active | I76: =IF($R76="","",INDEX(M_Tenure,$R76)) -> 5 | J76: =IF($R76="","",INDEX(P_Rating,$R76)) -> 5 | K76: =IF($R76="","",INDEX(P_9Box,$R76)) -> Star | L76: =IF($R76="","",INDEX(P_Elig,$R76)) -> Not Eligible | M76: =IF($R76="","",INDEX(C_CTC,$R76)/100000) -> 23.7 | N76: =IF($R76="","",INDEX(C_Compa,$R76)) -> 1.01 | O76: =IF($R76="","",INDEX(A_Att,$R76)) -> 0.924 | P76: =IF($R76="","",INDEX(E_Overall,$R76)) -> 3.17 | Q76: =IF($R76="","",INDEX(E_Risk,$R76)) -> Low | R76: =IF(B76="","",MATCH(B76,M_ID,0)) -> 72
A77: =IF(B77="","",73) -> 73 | B77: =IF(Calc_Engine!I74="","",Calc_Engine!I74) -> EMP1073 | C77: =IF($R77="","",INDEX(M_Name,$R77)) -> Vishal Ansari | D77: =IF($R77="","",INDEX(M_Title,$R77)) -> Product Manager | E77: =IF($R77="","",INDEX(M_Dept,$R77)) -> Product | F77: =IF($R77="","",INDEX(M_Level,$R77)) -> L3 | G77: =IF($R77="","",INDEX(M_Mgr,$R77)) -> Mansi Pillai | H77: =IF($R77="","",INDEX(M_Status,$R77)) -> Active | I77: =IF($R77="","",INDEX(M_Tenure,$R77)) -> 5 | J77: =IF($R77="","",INDEX(P_Rating,$R77)) -> 4 | K77: =IF($R77="","",INDEX(P_9Box,$R77)) -> High Performer | L77: =IF($R77="","",INDEX(P_Elig,$R77)) -> Eligible | M77: =IF($R77="","",INDEX(C_CTC,$R77)/100000) -> 13.5 | N77: =IF($R77="","",INDEX(C_Compa,$R77)) -> 0.93 | O77: =IF($R77="","",INDEX(A_Att,$R77)) -> 0.904 | P77: =IF($R77="","",INDEX(E_Overall,$R77)) -> 4.13 | Q77: =IF($R77="","",INDEX(E_Risk,$R77)) -> Low | R77: =IF(B77="","",MATCH(B77,M_ID,0)) -> 73
A78: =IF(B78="","",74) -> 74 | B78: =IF(Calc_Engine!I75="","",Calc_Engine!I75) -> EMP1074 | C78: =IF($R78="","",INDEX(M_Name,$R78)) -> Mansi Reddy | D78: =IF($R78="","",INDEX(M_Title,$R78)) -> Senior Sales Executive | E78: =IF($R78="","",INDEX(M_Dept,$R78)) -> Sales | F78: =IF($R78="","",INDEX(M_Level,$R78)) -> L3 | G78: =IF($R78="","",INDEX(M_Mgr,$R78)) -> Gayatri Tiwari | H78: =IF($R78="","",INDEX(M_Status,$R78)) -> Active | I78: =IF($R78="","",INDEX(M_Tenure,$R78)) -> 5 | J78: =IF($R78="","",INDEX(P_Rating,$R78)) -> 2 | K78: =IF($R78="","",INDEX(P_9Box,$R78)) -> Underperformer | L78: =IF($R78="","",INDEX(P_Elig,$R78)) -> Not Eligible | M78: =IF($R78="","",INDEX(C_CTC,$R78)/100000) -> 16.27 | N78: =IF($R78="","",INDEX(C_Compa,$R78)) -> 1.13 | O78: =IF($R78="","",INDEX(A_Att,$R78)) -> 0.884 | P78: =IF($R78="","",INDEX(E_Overall,$R78)) -> 3.42 | Q78: =IF($R78="","",INDEX(E_Risk,$R78)) -> Low | R78: =IF(B78="","",MATCH(B78,M_ID,0)) -> 74
A79: =IF(B79="","",75) -> 75 | B79: =IF(Calc_Engine!I76="","",Calc_Engine!I76) -> EMP1075 | C79: =IF($R79="","",INDEX(M_Name,$R79)) -> Sandeep Gupta | D79: =IF($R79="","",INDEX(M_Title,$R79)) -> Senior Operations Executive | E79: =IF($R79="","",INDEX(M_Dept,$R79)) -> Operations | F79: =IF($R79="","",INDEX(M_Level,$R79)) -> L3 | G79: =IF($R79="","",INDEX(M_Mgr,$R79)) -> Ramya Menon | H79: =IF($R79="","",INDEX(M_Status,$R79)) -> Active | I79: =IF($R79="","",INDEX(M_Tenure,$R79)) -> 4.9 | J79: =IF($R79="","",INDEX(P_Rating,$R79)) -> 3 | K79: =IF($R79="","",INDEX(P_9Box,$R79)) -> Effective Contributor | L79: =IF($R79="","",INDEX(P_Elig,$R79)) -> Not Eligible | M79: =IF($R79="","",INDEX(C_CTC,$R79)/100000) -> 13.79 | N79: =IF($R79="","",INDEX(C_Compa,$R79)) -> 0.95 | O79: =IF($R79="","",INDEX(A_Att,$R79)) -> 0.956 | P79: =IF($R79="","",INDEX(E_Overall,$R79)) -> 3.27 | Q79: =IF($R79="","",INDEX(E_Risk,$R79)) -> Low | R79: =IF(B79="","",MATCH(B79,M_ID,0)) -> 75
A80: =IF(B80="","",76) -> 76 | B80: =IF(Calc_Engine!I77="","",Calc_Engine!I77) -> EMP1076 | C80: =IF($R80="","",INDEX(M_Name,$R80)) -> Sneha Hegde | D80: =IF($R80="","",INDEX(M_Title,$R80)) -> Senior Software Engineer | E80: =IF($R80="","",INDEX(M_Dept,$R80)) -> Engineering | F80: =IF($R80="","",INDEX(M_Level,$R80)) -> L3 | G80: =IF($R80="","",INDEX(M_Mgr,$R80)) -> Harsh Siddiqui | H80: =IF($R80="","",INDEX(M_Status,$R80)) -> Active | I80: =IF($R80="","",INDEX(M_Tenure,$R80)) -> 4.9 | J80: =IF($R80="","",INDEX(P_Rating,$R80)) -> 4 | K80: =IF($R80="","",INDEX(P_9Box,$R80)) -> Trusted Professional | L80: =IF($R80="","",INDEX(P_Elig,$R80)) -> Eligible | M80: =IF($R80="","",INDEX(C_CTC,$R80)/100000) -> 17.7 | N80: =IF($R80="","",INDEX(C_Compa,$R80)) -> 1.22 | O80: =IF($R80="","",INDEX(A_Att,$R80)) -> 0.952 | P80: =IF($R80="","",INDEX(E_Overall,$R80)) -> 2.4 | Q80: =IF($R80="","",INDEX(E_Risk,$R80)) -> Medium | R80: =IF(B80="","",MATCH(B80,M_ID,0)) -> 76
A81: =IF(B81="","",77) -> 77 | B81: =IF(Calc_Engine!I78="","",Calc_Engine!I78) -> EMP1077 | C81: =IF($R81="","",INDEX(M_Name,$R81)) -> Kiran Chatterjee | D81: =IF($R81="","",INDEX(M_Title,$R81)) -> Senior Operations Executive | E81: =IF($R81="","",INDEX(M_Dept,$R81)) -> Operations | F81: =IF($R81="","",INDEX(M_Level,$R81)) -> L3 | G81: =IF($R81="","",INDEX(M_Mgr,$R81)) -> Yash Shah | H81: =IF($R81="","",INDEX(M_Status,$R81)) -> Active | I81: =IF($R81="","",INDEX(M_Tenure,$R81)) -> 4.9 | J81: =IF($R81="","",INDEX(P_Rating,$R81)) -> 3 | K81: =IF($R81="","",INDEX(P_9Box,$R81)) -> Core Player | L81: =IF($R81="","",INDEX(P_Elig,$R81)) -> Not Eligible | M81: =IF($R81="","",INDEX(C_CTC,$R81)/100000) -> 11.2 | N81: =IF($R81="","",INDEX(C_Compa,$R81)) -> 0.78 | O81: =IF($R81="","",INDEX(A_Att,$R81)) -> 0.92 | P81: =IF($R81="","",INDEX(E_Overall,$R81)) -> 3.95 | Q81: =IF($R81="","",INDEX(E_Risk,$R81)) -> Low | R81: =IF(B81="","",MATCH(B81,M_ID,0)) -> 77
A82: =IF(B82="","",78) -> 78 | B82: =IF(Calc_Engine!I79="","",Calc_Engine!I79) -> EMP1078 | C82: =IF($R82="","",INDEX(M_Name,$R82)) -> Aishwarya Joshi | D82: =IF($R82="","",INDEX(M_Title,$R82)) -> Finance Lead | E82: =IF($R82="","",INDEX(M_Dept,$R82)) -> Finance | F82: =IF($R82="","",INDEX(M_Level,$R82)) -> L4 | G82: =IF($R82="","",INDEX(M_Mgr,$R82)) -> Karan Patel | H82: =IF($R82="","",INDEX(M_Status,$R82)) -> Active | I82: =IF($R82="","",INDEX(M_Tenure,$R82)) -> 4.8 | J82: =IF($R82="","",INDEX(P_Rating,$R82)) -> 4 | K82: =IF($R82="","",INDEX(P_9Box,$R82)) -> High Performer | L82: =IF($R82="","",INDEX(P_Elig,$R82)) -> Eligible | M82: =IF($R82="","",INDEX(C_CTC,$R82)/100000) -> 18.87 | N82: =IF($R82="","",INDEX(C_Compa,$R82)) -> 0.81 | O82: =IF($R82="","",INDEX(A_Att,$R82)) -> 0.908 | P82: =IF($R82="","",INDEX(E_Overall,$R82)) -> 3.73 | Q82: =IF($R82="","",INDEX(E_Risk,$R82)) -> Medium | R82: =IF(B82="","",MATCH(B82,M_ID,0)) -> 78
A83: =IF(B83="","",79) -> 79 | B83: =IF(Calc_Engine!I80="","",Calc_Engine!I80) -> EMP1079 | C83: =IF($R83="","",INDEX(M_Name,$R83)) -> Sindhu Das | D83: =IF($R83="","",INDEX(M_Title,$R83)) -> Senior Marketing Executive | E83: =IF($R83="","",INDEX(M_Dept,$R83)) -> Marketing | F83: =IF($R83="","",INDEX(M_Level,$R83)) -> L3 | G83: =IF($R83="","",INDEX(M_Mgr,$R83)) -> Nandini Iyer | H83: =IF($R83="","",INDEX(M_Status,$R83)) -> Active | I83: =IF($R83="","",INDEX(M_Tenure,$R83)) -> 4.8 | J83: =IF($R83="","",INDEX(P_Rating,$R83)) -> 3 | K83: =IF($R83="","",INDEX(P_9Box,$R83)) -> Core Player | L83: =IF($R83="","",INDEX(P_Elig,$R83)) -> Not Eligible | M83: =IF($R83="","",INDEX(C_CTC,$R83)/100000) -> 13.16 | N83: =IF($R83="","",INDEX(C_Compa,$R83)) -> 0.91 | O83: =IF($R83="","",INDEX(A_Att,$R83)) -> 0.936 | P83: =IF($R83="","",INDEX(E_Overall,$R83)) -> 1.88 | Q83: =IF($R83="","",INDEX(E_Risk,$R83)) -> Medium | R83: =IF(B83="","",MATCH(B83,M_ID,0)) -> 79
A84: =IF(B84="","",80) -> 80 | B84: =IF(Calc_Engine!I81="","",Calc_Engine!I81) -> EMP1080 | C84: =IF($R84="","",INDEX(M_Name,$R84)) -> Nandini Shetty | D84: =IF($R84="","",INDEX(M_Title,$R84)) -> Senior Data Analyst | E84: =IF($R84="","",INDEX(M_Dept,$R84)) -> Data & Analytics | F84: =IF($R84="","",INDEX(M_Level,$R84)) -> L3 | G84: =IF($R84="","",INDEX(M_Mgr,$R84)) -> Karan Verma | H84: =IF($R84="","",INDEX(M_Status,$R84)) -> Active | I84: =IF($R84="","",INDEX(M_Tenure,$R84)) -> 4.8 | J84: =IF($R84="","",INDEX(P_Rating,$R84)) -> 4 | K84: =IF($R84="","",INDEX(P_9Box,$R84)) -> Star | L84: =IF($R84="","",INDEX(P_Elig,$R84)) -> Eligible | M84: =IF($R84="","",INDEX(C_CTC,$R84)/100000) -> 20.05 | N84: =IF($R84="","",INDEX(C_Compa,$R84)) -> 1.39 | O84: =IF($R84="","",INDEX(A_Att,$R84)) -> 0.892 | P84: =IF($R84="","",INDEX(E_Overall,$R84)) -> 3.27 | Q84: =IF($R84="","",INDEX(E_Risk,$R84)) -> Low | R84: =IF(B84="","",MATCH(B84,M_ID,0)) -> 80
A85: =IF(B85="","",81) -> 81 | B85: =IF(Calc_Engine!I82="","",Calc_Engine!I82) -> EMP1081 | C85: =IF($R85="","",INDEX(M_Name,$R85)) -> Deepak Thomas | D85: =IF($R85="","",INDEX(M_Title,$R85)) -> Senior Software Engineer | E85: =IF($R85="","",INDEX(M_Dept,$R85)) -> Engineering | F85: =IF($R85="","",INDEX(M_Level,$R85)) -> L3 | G85: =IF($R85="","",INDEX(M_Mgr,$R85)) -> Vikas Singh | H85: =IF($R85="","",INDEX(M_Status,$R85)) -> Active | I85: =IF($R85="","",INDEX(M_Tenure,$R85)) -> 4.8 | J85: =IF($R85="","",INDEX(P_Rating,$R85)) -> 3 | K85: =IF($R85="","",INDEX(P_9Box,$R85)) -> Core Player | L85: =IF($R85="","",INDEX(P_Elig,$R85)) -> Not Eligible | M85: =IF($R85="","",INDEX(C_CTC,$R85)/100000) -> 14.89 | N85: =IF($R85="","",INDEX(C_Compa,$R85)) -> 1.03 | O85: =IF($R85="","",INDEX(A_Att,$R85)) -> 0.944 | P85: =IF($R85="","",INDEX(E_Overall,$R85)) -> 3.43 | Q85: =IF($R85="","",INDEX(E_Risk,$R85)) -> Low | R85: =IF(B85="","",MATCH(B85,M_ID,0)) -> 81
A86: =IF(B86="","",82) -> 82 | B86: =IF(Calc_Engine!I83="","",Calc_Engine!I83) -> EMP1082 | C86: =IF($R86="","",INDEX(M_Name,$R86)) -> Mansi Dsouza | D86: =IF($R86="","",INDEX(M_Title,$R86)) -> Tech Lead | E86: =IF($R86="","",INDEX(M_Dept,$R86)) -> Engineering | F86: =IF($R86="","",INDEX(M_Level,$R86)) -> L4 | G86: =IF($R86="","",INDEX(M_Mgr,$R86)) -> Gaurav Fernandes | H86: =IF($R86="","",INDEX(M_Status,$R86)) -> Active | I86: =IF($R86="","",INDEX(M_Tenure,$R86)) -> 4.7 | J86: =IF($R86="","",INDEX(P_Rating,$R86)) -> 3 | K86: =IF($R86="","",INDEX(P_9Box,$R86)) -> Core Player | L86: =IF($R86="","",INDEX(P_Elig,$R86)) -> Not Eligible | M86: =IF($R86="","",INDEX(C_CTC,$R86)/100000) -> 29.14 | N86: =IF($R86="","",INDEX(C_Compa,$R86)) -> 1.24 | O86: =IF($R86="","",INDEX(A_Att,$R86)) -> 0.896 | P86: =IF($R86="","",INDEX(E_Overall,$R86)) -> 3.68 | Q86: =IF($R86="","",INDEX(E_Risk,$R86)) -> Low | R86: =IF(B86="","",MATCH(B86,M_ID,0)) -> 82
A87: =IF(B87="","",83) -> 83 | B87: =IF(Calc_Engine!I84="","",Calc_Engine!I84) -> EMP1083 | C87: =IF($R87="","",INDEX(M_Name,$R87)) -> Akash Das | D87: =IF($R87="","",INDEX(M_Title,$R87)) -> HR Manager | E87: =IF($R87="","",INDEX(M_Dept,$R87)) -> Human Resources | F87: =IF($R87="","",INDEX(M_Level,$R87)) -> L5 | G87: =IF($R87="","",INDEX(M_Mgr,$R87)) -> Prakash Das | H87: =IF($R87="","",INDEX(M_Status,$R87)) -> Active | I87: =IF($R87="","",INDEX(M_Tenure,$R87)) -> 4.7 | J87: =IF($R87="","",INDEX(P_Rating,$R87)) -> 4 | K87: =IF($R87="","",INDEX(P_9Box,$R87)) -> Star | L87: =IF($R87="","",INDEX(P_Elig,$R87)) -> Eligible | M87: =IF($R87="","",INDEX(C_CTC,$R87)/100000) -> 40.05 | N87: =IF($R87="","",INDEX(C_Compa,$R87)) -> 1.09 | O87: =IF($R87="","",INDEX(A_Att,$R87)) -> 0.916 | P87: =IF($R87="","",INDEX(E_Overall,$R87)) -> 3.37 | Q87: =IF($R87="","",INDEX(E_Risk,$R87)) -> Low | R87: =IF(B87="","",MATCH(B87,M_ID,0)) -> 83
A88: =IF(B88="","",84) -> 84 | B88: =IF(Calc_Engine!I85="","",Calc_Engine!I85) -> EMP1084 | C88: =IF($R88="","",INDEX(M_Name,$R88)) -> Mansi Pillai | D88: =IF($R88="","",INDEX(M_Title,$R88)) -> Group Product Manager | E88: =IF($R88="","",INDEX(M_Dept,$R88)) -> Product | F88: =IF($R88="","",INDEX(M_Level,$R88)) -> L5 | G88: =IF($R88="","",INDEX(M_Mgr,$R88)) -> Trisha Patel | H88: =IF($R88="","",INDEX(M_Status,$R88)) -> Active | I88: =IF($R88="","",INDEX(M_Tenure,$R88)) -> 4.7 | J88: =IF($R88="","",INDEX(P_Rating,$R88)) -> 4 | K88: =IF($R88="","",INDEX(P_9Box,$R88)) -> High Performer | L88: =IF($R88="","",INDEX(P_Elig,$R88)) -> Eligible | M88: =IF($R88="","",INDEX(C_CTC,$R88)/100000) -> 33.72 | N88: =IF($R88="","",INDEX(C_Compa,$R88)) -> 0.92 | O88: =IF($R88="","",INDEX(A_Att,$R88)) -> 0.944 | P88: =IF($R88="","",INDEX(E_Overall,$R88)) -> 3.72 | Q88: =IF($R88="","",INDEX(E_Risk,$R88)) -> Low | R88: =IF(B88="","",MATCH(B88,M_ID,0)) -> 84
A89: =IF(B89="","",85) -> 85 | B89: =IF(Calc_Engine!I86="","",Calc_Engine!I86) -> EMP1085 | C89: =IF($R89="","",INDEX(M_Name,$R89)) -> Rohan Menon | D89: =IF($R89="","",INDEX(M_Title,$R89)) -> Senior Operations Executive | E89: =IF($R89="","",INDEX(M_Dept,$R89)) -> Operations | F89: =IF($R89="","",INDEX(M_Level,$R89)) -> L3 | G89: =IF($R89="","",INDEX(M_Mgr,$R89)) -> Amit Kumar | H89: =IF($R89="","",INDEX(M_Status,$R89)) -> Active | I89: =IF($R89="","",INDEX(M_Tenure,$R89)) -> 4.7 | J89: =IF($R89="","",INDEX(P_Rating,$R89)) -> 2 | K89: =IF($R89="","",INDEX(P_9Box,$R89)) -> Inconsistent Player | L89: =IF($R89="","",INDEX(P_Elig,$R89)) -> Not Eligible | M89: =IF($R89="","",INDEX(C_CTC,$R89)/100000) -> 14.06 | N89: =IF($R89="","",INDEX(C_Compa,$R89)) -> 0.97 | O89: =IF($R89="","",INDEX(A_Att,$R89)) -> 0.904 | P89: =IF($R89="","",INDEX(E_Overall,$R89)) -> 2.62 | Q89: =IF($R89="","",INDEX(E_Risk,$R89)) -> Low | R89: =IF(B89="","",MATCH(B89,M_ID,0)) -> 85
A90: =IF(B90="","",86) -> 86 | B90: =IF(Calc_Engine!I87="","",Calc_Engine!I87) -> EMP1086 | C90: =IF($R90="","",INDEX(M_Name,$R90)) -> Bhavana Hegde | D90: =IF($R90="","",INDEX(M_Title,$R90)) -> Engineering Manager | E90: =IF($R90="","",INDEX(M_Dept,$R90)) -> Engineering | F90: =IF($R90="","",INDEX(M_Level,$R90)) -> L5 | G90: =IF($R90="","",INDEX(M_Mgr,$R90)) -> Vikram Verma | H90: =IF($R90="","",INDEX(M_Status,$R90)) -> Active | I90: =IF($R90="","",INDEX(M_Tenure,$R90)) -> 4.7 | J90: =IF($R90="","",INDEX(P_Rating,$R90)) -> 3 | K90: =IF($R90="","",INDEX(P_9Box,$R90)) -> Core Player | L90: =IF($R90="","",INDEX(P_Elig,$R90)) -> Not Eligible | M90: =IF($R90="","",INDEX(C_CTC,$R90)/100000) -> 36.92 | N90: =IF($R90="","",INDEX(C_Compa,$R90)) -> 1.01 | O90: =IF($R90="","",INDEX(A_Att,$R90)) -> 0.912 | P90: =IF($R90="","",INDEX(E_Overall,$R90)) -> 3.18 | Q90: =IF($R90="","",INDEX(E_Risk,$R90)) -> Low | R90: =IF(B90="","",MATCH(B90,M_ID,0)) -> 86
A91: =IF(B91="","",87) -> 87 | B91: =IF(Calc_Engine!I88="","",Calc_Engine!I88) -> EMP1087 | C91: =IF($R91="","",INDEX(M_Name,$R91)) -> Arun Choudhary | D91: =IF($R91="","",INDEX(M_Title,$R91)) -> Senior Software Engineer | E91: =IF($R91="","",INDEX(M_Dept,$R91)) -> Engineering | F91: =IF($R91="","",INDEX(M_Level,$R91)) -> L3 | G91: =IF($R91="","",INDEX(M_Mgr,$R91)) -> Tejaswini Hegde | H91: =IF($R91="","",INDEX(M_Status,$R91)) -> Active | I91: =IF($R91="","",INDEX(M_Tenure,$R91)) -> 4.7 | J91: =IF($R91="","",INDEX(P_Rating,$R91)) -> 3 | K91: =IF($R91="","",INDEX(P_9Box,$R91)) -> Core Player | L91: =IF($R91="","",INDEX(P_Elig,$R91)) -> Not Eligible | M91: =IF($R91="","",INDEX(C_CTC,$R91)/100000) -> 16.78 | N91: =IF($R91="","",INDEX(C_Compa,$R91)) -> 1.16 | O91: =IF($R91="","",INDEX(A_Att,$R91)) -> 0.948 | P91: =IF($R91="","",INDEX(E_Overall,$R91)) -> 2.45 | Q91: =IF($R91="","",INDEX(E_Risk,$R91)) -> Medium | R91: =IF(B91="","",MATCH(B91,M_ID,0)) -> 87
A92: =IF(B92="","",88) -> 88 | B92: =IF(Calc_Engine!I89="","",Calc_Engine!I89) -> EMP1088 | C92: =IF($R92="","",INDEX(M_Name,$R92)) -> Ankit Tiwari | D92: =IF($R92="","",INDEX(M_Title,$R92)) -> HR Business Partner | E92: =IF($R92="","",INDEX(M_Dept,$R92)) -> Human Resources | F92: =IF($R92="","",INDEX(M_Level,$R92)) -> L3 | G92: =IF($R92="","",INDEX(M_Mgr,$R92)) -> Akash Das | H92: =IF($R92="","",INDEX(M_Status,$R92)) -> Active | I92: =IF($R92="","",INDEX(M_Tenure,$R92)) -> 4.7 | J92: =IF($R92="","",INDEX(P_Rating,$R92)) -> 5 | K92: =IF($R92="","",INDEX(P_9Box,$R92)) -> High Performer | L92: =IF($R92="","",INDEX(P_Elig,$R92)) -> Not Eligible | M92: =IF($R92="","",INDEX(C_CTC,$R92)/100000) -> 13.15 | N92: =IF($R92="","",INDEX(C_Compa,$R92)) -> 0.91 | O92: =IF($R92="","",INDEX(A_Att,$R92)) -> 0.88 | P92: =IF($R92="","",INDEX(E_Overall,$R92)) -> 3.27 | Q92: =IF($R92="","",INDEX(E_Risk,$R92)) -> Low | R92: =IF(B92="","",MATCH(B92,M_ID,0)) -> 88
A93: =IF(B93="","",89) -> 89 | B93: =IF(Calc_Engine!I90="","",Calc_Engine!I90) -> EMP1089 | C93: =IF($R93="","",INDEX(M_Name,$R93)) -> Mary Varghese | D93: =IF($R93="","",INDEX(M_Title,$R93)) -> Senior Support Executive | E93: =IF($R93="","",INDEX(M_Dept,$R93)) -> Customer Support | F93: =IF($R93="","",INDEX(M_Level,$R93)) -> L3 | G93: =IF($R93="","",INDEX(M_Mgr,$R93)) -> Ashish Varghese | H93: =IF($R93="","",INDEX(M_Status,$R93)) -> Active | I93: =IF($R93="","",INDEX(M_Tenure,$R93)) -> 4.7 | J93: =IF($R93="","",INDEX(P_Rating,$R93)) -> 2 | K93: =IF($R93="","",INDEX(P_9Box,$R93)) -> Underperformer | L93: =IF($R93="","",INDEX(P_Elig,$R93)) -> Not Eligible | M93: =IF($R93="","",INDEX(C_CTC,$R93)/100000) -> 9.31 | N93: =IF($R93="","",INDEX(C_Compa,$R93)) -> 0.64 | O93: =IF($R93="","",INDEX(A_Att,$R93)) -> 0.9 | P93: =IF($R93="","",INDEX(E_Overall,$R93)) -> 3.12 | Q93: =IF($R93="","",INDEX(E_Risk,$R93)) -> Low | R93: =IF(B93="","",MATCH(B93,M_ID,0)) -> 89
A94: =IF(B94="","",90) -> 90 | B94: =IF(Calc_Engine!I91="","",Calc_Engine!I91) -> EMP1090 | C94: =IF($R94="","",INDEX(M_Name,$R94)) -> Madhuri Malhotra | D94: =IF($R94="","",INDEX(M_Title,$R94)) -> Sales Manager | E94: =IF($R94="","",INDEX(M_Dept,$R94)) -> Sales | F94: =IF($R94="","",INDEX(M_Level,$R94)) -> L5 | G94: =IF($R94="","",INDEX(M_Mgr,$R94)) -> Gayatri Tiwari | H94: =IF($R94="","",INDEX(M_Status,$R94)) -> Exited | I94: =IF($R94="","",INDEX(M_Tenure,$R94)) -> 4.5 | J94: =IF($R94="","",INDEX(P_Rating,$R94)) -> 3 | K94: =IF($R94="","",INDEX(P_9Box,$R94)) -> Effective Contributor | L94: =IF($R94="","",INDEX(P_Elig,$R94)) -> Not Eligible | M94: =IF($R94="","",INDEX(C_CTC,$R94)/100000) -> 32.47 | N94: =IF($R94="","",INDEX(C_Compa,$R94)) -> 0.89 | O94: =IF($R94="","",INDEX(A_Att,$R94)) -> 0.91891892 | P94: =IF($R94="","",INDEX(E_Overall,$R94)) -> 2.3 | Q94: =IF($R94="","",INDEX(E_Risk,$R94)) -> Exited | R94: =IF(B94="","",MATCH(B94,M_ID,0)) -> 90
A95: =IF(B95="","",91) -> 91 | B95: =IF(Calc_Engine!I92="","",Calc_Engine!I92) -> EMP1091 | C95: =IF($R95="","",INDEX(M_Name,$R95)) -> Srinivas Bose | D95: =IF($R95="","",INDEX(M_Title,$R95)) -> Tech Lead | E95: =IF($R95="","",INDEX(M_Dept,$R95)) -> Engineering | F95: =IF($R95="","",INDEX(M_Level,$R95)) -> L4 | G95: =IF($R95="","",INDEX(M_Mgr,$R95)) -> Tejaswini Hegde | H95: =IF($R95="","",INDEX(M_Status,$R95)) -> Active | I95: =IF($R95="","",INDEX(M_Tenure,$R95)) -> 4.6 | J95: =IF($R95="","",INDEX(P_Rating,$R95)) -> 3 | K95: =IF($R95="","",INDEX(P_9Box,$R95)) -> Core Player | L95: =IF($R95="","",INDEX(P_Elig,$R95)) -> Not Eligible | M95: =IF($R95="","",INDEX(C_CTC,$R95)/100000) -> 22.45 | N95: =IF($R95="","",INDEX(C_Compa,$R95)) -> 0.96 | O95: =IF($R95="","",INDEX(A_Att,$R95)) -> 0.92 | P95: =IF($R95="","",INDEX(E_Overall,$R95)) -> 3.28 | Q95: =IF($R95="","",INDEX(E_Risk,$R95)) -> Low | R95: =IF(B95="","",MATCH(B95,M_ID,0)) -> 91
A96: =IF(B96="","",92) -> 92 | B96: =IF(Calc_Engine!I93="","",Calc_Engine!I93) -> EMP1092 | C96: =IF($R96="","",INDEX(M_Name,$R96)) -> Kunal Jain | D96: =IF($R96="","",INDEX(M_Title,$R96)) -> Senior Operations Executive | E96: =IF($R96="","",INDEX(M_Dept,$R96)) -> Operations | F96: =IF($R96="","",INDEX(M_Level,$R96)) -> L3 | G96: =IF($R96="","",INDEX(M_Mgr,$R96)) -> Pallavi Nair | H96: =IF($R96="","",INDEX(M_Status,$R96)) -> Active | I96: =IF($R96="","",INDEX(M_Tenure,$R96)) -> 4.6 | J96: =IF($R96="","",INDEX(P_Rating,$R96)) -> 3 | K96: =IF($R96="","",INDEX(P_9Box,$R96)) -> Effective Contributor | L96: =IF($R96="","",INDEX(P_Elig,$R96)) -> Not Eligible | M96: =IF($R96="","",INDEX(C_CTC,$R96)/100000) -> 13.44 | N96: =IF($R96="","",INDEX(C_Compa,$R96)) -> 0.93 | O96: =IF($R96="","",INDEX(A_Att,$R96)) -> 0.908 | P96: =IF($R96="","",INDEX(E_Overall,$R96)) -> 3.72 | Q96: =IF($R96="","",INDEX(E_Risk,$R96)) -> Low | R96: =IF(B96="","",MATCH(B96,M_ID,0)) -> 92
A97: =IF(B97="","",93) -> 93 | B97: =IF(Calc_Engine!I94="","",Calc_Engine!I94) -> EMP1093 | C97: =IF($R97="","",INDEX(M_Name,$R97)) -> Priyanka Hegde | D97: =IF($R97="","",INDEX(M_Title,$R97)) -> Product Manager | E97: =IF($R97="","",INDEX(M_Dept,$R97)) -> Product | F97: =IF($R97="","",INDEX(M_Level,$R97)) -> L3 | G97: =IF($R97="","",INDEX(M_Mgr,$R97)) -> Mansi Pillai | H97: =IF($R97="","",INDEX(M_Status,$R97)) -> Active | I97: =IF($R97="","",INDEX(M_Tenure,$R97)) -> 4.5 | J97: =IF($R97="","",INDEX(P_Rating,$R97)) -> 3 | K97: =IF($R97="","",INDEX(P_9Box,$R97)) -> Future Star | L97: =IF($R97="","",INDEX(P_Elig,$R97)) -> Not Eligible | M97: =IF($R97="","",INDEX(C_CTC,$R97)/100000) -> 19.52 | N97: =IF($R97="","",INDEX(C_Compa,$R97)) -> 1.35 | O97: =IF($R97="","",INDEX(A_Att,$R97)) -> 0.908 | P97: =IF($R97="","",INDEX(E_Overall,$R97)) -> 2.77 | Q97: =IF($R97="","",INDEX(E_Risk,$R97)) -> Low | R97: =IF(B97="","",MATCH(B97,M_ID,0)) -> 93
A98: =IF(B98="","",94) -> 94 | B98: =IF(Calc_Engine!I95="","",Calc_Engine!I95) -> EMP1094 | C98: =IF($R98="","",INDEX(M_Name,$R98)) -> Gayatri Thomas | D98: =IF($R98="","",INDEX(M_Title,$R98)) -> Product Manager | E98: =IF($R98="","",INDEX(M_Dept,$R98)) -> Product | F98: =IF($R98="","",INDEX(M_Level,$R98)) -> L3 | G98: =IF($R98="","",INDEX(M_Mgr,$R98)) -> Trisha Patel | H98: =IF($R98="","",INDEX(M_Status,$R98)) -> Active | I98: =IF($R98="","",INDEX(M_Tenure,$R98)) -> 4.5 | J98: =IF($R98="","",INDEX(P_Rating,$R98)) -> 4 | K98: =IF($R98="","",INDEX(P_9Box,$R98)) -> Star | L98: =IF($R98="","",INDEX(P_Elig,$R98)) -> Eligible | M98: =IF($R98="","",INDEX(C_CTC,$R98)/100000) -> 19.8 | N98: =IF($R98="","",INDEX(C_Compa,$R98)) -> 1.37 | O98: =IF($R98="","",INDEX(A_Att,$R98)) -> 0.92 | P98: =IF($R98="","",INDEX(E_Overall,$R98)) -> 4.05 | Q98: =IF($R98="","",INDEX(E_Risk,$R98)) -> Low | R98: =IF(B98="","",MATCH(B98,M_ID,0)) -> 94
A99: =IF(B99="","",95) -> 95 | B99: =IF(Calc_Engine!I96="","",Calc_Engine!I96) -> EMP1095 | C99: =IF($R99="","",INDEX(M_Name,$R99)) -> Mary Banerjee | D99: =IF($R99="","",INDEX(M_Title,$R99)) -> Lead Data Scientist | E99: =IF($R99="","",INDEX(M_Dept,$R99)) -> Data & Analytics | F99: =IF($R99="","",INDEX(M_Level,$R99)) -> L4 | G99: =IF($R99="","",INDEX(M_Mgr,$R99)) -> Karan Verma | H99: =IF($R99="","",INDEX(M_Status,$R99)) -> Active | I99: =IF($R99="","",INDEX(M_Tenure,$R99)) -> 4.5 | J99: =IF($R99="","",INDEX(P_Rating,$R99)) -> 3 | K99: =IF($R99="","",INDEX(P_9Box,$R99)) -> Core Player | L99: =IF($R99="","",INDEX(P_Elig,$R99)) -> Not Eligible | M99: =IF($R99="","",INDEX(C_CTC,$R99)/100000) -> 29.33 | N99: =IF($R99="","",INDEX(C_Compa,$R99)) -> 1.25 | O99: =IF($R99="","",INDEX(A_Att,$R99)) -> 0.96 | P99: =IF($R99="","",INDEX(E_Overall,$R99)) -> 3.88 | Q99: =IF($R99="","",INDEX(E_Risk,$R99)) -> Low | R99: =IF(B99="","",MATCH(B99,M_ID,0)) -> 95
A100: =IF(B100="","",96) -> 96 | B100: =IF(Calc_Engine!I97="","",Calc_Engine!I97) -> EMP1096 | C100: =IF($R100="","",INDEX(M_Name,$R100)) -> Pallavi Malhotra | D100: =IF($R100="","",INDEX(M_Title,$R100)) -> Marketing Lead | E100: =IF($R100="","",INDEX(M_Dept,$R100)) -> Marketing | F100: =IF($R100="","",INDEX(M_Level,$R100)) -> L4 | G100: =IF($R100="","",INDEX(M_Mgr,$R100)) -> Nandini Iyer | H100: =IF($R100="","",INDEX(M_Status,$R100)) -> Active | I100: =IF($R100="","",INDEX(M_Tenure,$R100)) -> 4.5 | J100: =IF($R100="","",INDEX(P_Rating,$R100)) -> 4 | K100: =IF($R100="","",INDEX(P_9Box,$R100)) -> High Performer | L100: =IF($R100="","",INDEX(P_Elig,$R100)) -> Eligible | M100: =IF($R100="","",INDEX(C_CTC,$R100)/100000) -> 18.89 | N100: =IF($R100="","",INDEX(C_Compa,$R100)) -> 0.81 | O100: =IF($R100="","",INDEX(A_Att,$R100)) -> 0.952 | P100: =IF($R100="","",INDEX(E_Overall,$R100)) -> 3.05 | Q100: =IF($R100="","",INDEX(E_Risk,$R100)) -> Medium | R100: =IF(B100="","",MATCH(B100,M_ID,0)) -> 96
...

Sheet Employee_Master
A1: Emp ID | B1: Employee Name | C1: Email | D1: Manager | E1: Manager ID | F1: Designation | G1: Level | H1: Level No | I1: Department | J1: Gender | K1: Location | L1: Employment Type | M1: Date of Joining | N1: Age | O1: Status | P1: Exit Date | Q1: Tenure (Yrs) | R1: Tenure Band | S1: Direct Reports
A2: EMP1001 | B2: Vidya Kulkarni | C2: vidya.kulkarni@samplecorp.in | D2: Arvind Rao (CEO) | E2: EMP1000 | F2: Head of People | G2: L7 | H2: =VALUE(MID(G2,2,1)) -> 7 | I2: Human Resources | J2: Female | K2: Bengaluru | L2: Full-time | M2: 42718 | N2: 44 | O2: =IF(COUNTIF(Exits_Attrition!$A$2:$A$65,A2)>0,"Exited","Active") -> Active | P2: =IFERROR(INDEX(Exits_Attrition!$H$2:$H$65,MATCH(A2,Exits_Attrition!$A$2:$A$65,0)),"") | Q2: =ROUND((IF(P2="",AsOf,P2)-M2)/365.25,1) -> 9.8 | R2: =IF(Q2<1,"Under 1 Yr",IF(Q2<3,"1-3 Yrs",IF(Q2<5,"3-5 Yrs","5+ Yrs"))) -> 5+ Yrs | S2: =COUNTIF($E$2:$E$501,A2) -> 1
A3: EMP1002 | B3: Vikas Singh | C3: vikas.singh@samplecorp.in | D3: Yamini Nair | E3: EMP1247 | F3: Engineering Manager | G3: L5 | H3: =VALUE(MID(G3,2,1)) -> 5 | I3: Engineering | J3: Male | K3: Chennai | L3: Full-time | M3: 43401 | N3: 40 | O3: =IF(COUNTIF(Exits_Attrition!$A$2:$A$65,A3)>0,"Exited","Active") -> Active | P3: =IFERROR(INDEX(Exits_Attrition!$H$2:$H$65,MATCH(A3,Exits_Attrition!$A$2:$A$65,0)),"") | Q3: =ROUND((IF(P3="",AsOf,P3)-M3)/365.25,1) -> 7.9 | R3: =IF(Q3<1,"Under 1 Yr",IF(Q3<3,"1-3 Yrs",IF(Q3<5,"3-5 Yrs","5+ Yrs"))) -> 5+ Yrs | S3: =COUNTIF($E$2:$E$501,A3) -> 14
A4: EMP1003 | B4: Prakash Das | C4: prakash.das@samplecorp.in | D4: Vidya Kulkarni | E4: EMP1001 | F4: Senior HR Manager | G4: L6 | H4: =VALUE(MID(G4,2,1)) -> 6 | I4: Human Resources | J4: Male | K4: Bengaluru | L4: Full-time | M4: 43538 | N4: 36 | O4: =IF(COUNTIF(Exits_Attrition!$A$2:$A$65,A4)>0,"Exited","Active") -> Active | P4: =IFERROR(INDEX(Exits_Attrition!$H$2:$H$65,MATCH(A4,Exits_Attrition!$A$2:$A$65,0)),"") | Q4: =ROUND((IF(P4="",AsOf,P4)-M4)/365.25,1) -> 7.5 | R4: =IF(Q4<1,"Under 1 Yr",IF(Q4<3,"1-3 Yrs",IF(Q4<5,"3-5 Yrs","5+ Yrs"))) -> 5+ Yrs | S4: =COUNTIF($E$2:$E$501,A4) -> 5
A5: EMP1004 | B5: Fatima Choudhary | C5: fatima.choudhary@samplecorp.in | D5: Yamini Nair | E5: EMP1247 | F5: Engineering Manager | G5: L5 | H5: =VALUE(MID(G5,2,1)) -> 5 | I5: Engineering | J5: Female | K5: Bengaluru | L5: Full-time | M5: 43552 | N5: 39 | O5: =IF(COUNTIF(Exits_Attrition!$A$2:$A$65,A5)>0,"Exited","Active") -> Active | P5: =IFERROR(INDEX(Exits_Attrition!$H$2:$H$65,MATCH(A5,Exits_Attrition!$A$2:$A$65,0)),"") | Q5: =ROUND((IF(P5="",AsOf,P5)-M5)/365.25,1) -> 7.5 | R5: =IF(Q5<1,"Under 1 Yr",IF(Q5<3,"1-3 Yrs",IF(Q5<5,"3-5 Yrs","5+ Yrs"))) -> 5+ Yrs | S5: =COUNTIF($E$2:$E$501,A5) -> 10
A6: EMP1005 | B6: Gaurav Fernandes | C6: gaurav.fernandes@samplecorp.in | D6: Yamini Nair | E6: EMP1247 | F6: Engineering Manager | G6: L5 | H6: =VALUE(MID(G6,2,1)) -> 5 | I6: Engineering | J6: Male | K6: Bengaluru | L6: Full-time | M6: 43659 | N6: 34 | O6: =IF(COUNTIF(Exits_Attrition!$A$2:$A$65,A6)>0,"Exited","Active") -> Active | P6: =IFERROR(INDEX(Exits_Attrition!$H$2:$H$65,MATCH(A6,Exits_Attrition!$A$2:$A$65,0)),"") | Q6: =ROUND((IF(P6="",AsOf,P6)-M6)/365.25,1) -> 7.2 | R6: =IF(Q6<1,"Under 1 Yr",IF(Q6<3,"1-3 Yrs",IF(Q6<5,"3-5 Yrs","5+ Yrs"))) -> 5+ Yrs | S6: =COUNTIF($E$2:$E$501,A6) -> 11
A7: EMP1006 | B7: Yash Shah | C7: yash.shah@samplecorp.in | D7: Pallavi Shah | E7: EMP1158 | F7: Operations Manager | G7: L5 | H7: =VALUE(MID(G7,2,1)) -> 5 | I7: Operations | J7: Male | K7: Mumbai | L7: Full-time | M7: 43681 | N7: 37 | O7: =IF(COUNTIF(Exits_Attrition!$A$2:$A$65,A7)>0,"Exited","Active") -> Exited | P7: =IFERROR(INDEX(Exits_Attrition!$H$2:$H$65,MATCH(A7,Exits_Attrition!$A$2:$A$65,0)),"") -> 46239 | Q7: =ROUND((IF(P7="",AsOf,P7)-M7)/365.25,1) -> 7 | R7: =IF(Q7<1,"Under 1 Yr",IF(Q7<3,"1-3 Yrs",IF(Q7<5,"3-5 Yrs","5+ Yrs"))) -> 5+ Yrs | S7: =COUNTIF($E$2:$E$501,A7) -> 14
A8: EMP1007 | B8: Imran Tiwari | C8: imran.tiwari@samplecorp.in | D8: Nandini Iyer | E8: EMP1238 | F8: Marketing Lead | G8: L4 | H8: =VALUE(MID(G8,2,1)) -> 4 | I8: Marketing | J8: Male | K8: Bengaluru | L8: Full-time | M8: 43750 | N8: 32 | O8: =IF(COUNTIF(Exits_Attrition!$A$2:$A$65,A8)>0,"Exited","Active") -> Exited | P8: =IFERROR(INDEX(Exits_Attrition!$H$2:$H$65,MATCH(A8,Exits_Attrition!$A$2:$A$65,0)),"") -> 46100 | Q8: =ROUND((IF(P8="",AsOf,P8)-M8)/365.25,1) -> 6.4 | R8: =IF(Q8<1,"Under 1 Yr",IF(Q8<3,"1-3 Yrs",IF(Q8<5,"3-5 Yrs","5+ Yrs"))) -> 5+ Yrs | S8: =COUNTIF($E$2:$E$501,A8) -> 0
A9: EMP1008 | B9: Aishwarya Khan | C9: aishwarya.khan@samplecorp.in | D9: Arvind Rao (CEO) | E9: EMP1000 | F9: Head of Engineering | G9: L7 | H9: =VALUE(MID(G9,2,1)) -> 7 | I9: Engineering | J9: Female | K9: Bengaluru | L9: Full-time | M9: 43771 | N9: 39 | O9: =IF(COUNTIF(Exits_Attrition!$A$2:$A$65,A9)>0,"Exited","Active") -> Active | P9: =IFERROR(INDEX(Exits_Attrition!$H$2:$H$65,MATCH(A9,Exits_Attrition!$A$2:$A$65,0)),"") | Q9: =ROUND((IF(P9="",AsOf,P9)-M9)/365.25,1) -> 6.9 | R9: =IF(Q9<1,"Under 1 Yr",IF(Q9<3,"1-3 Yrs",IF(Q9<5,"3-5 Yrs","5+ Yrs"))) -> 5+ Yrs | S9: =COUNTIF($E$2:$E$501,A9) -> 2
A10: EMP1009 | B10: Ankit Khanna | C10: ankit.khanna@samplecorp.in | D10: Imran Mishra | E10: EMP1373 | F10: Operations Manager | G10: L5 | H10: =VALUE(MID(G10,2,1)) -> 5 | I10: Operations | J10: Male | K10: Bengaluru | L10: Full-time | M10: 43783 | N10: 38 | O10: =IF(COUNTIF(Exits_Attrition!$A$2:$A$65,A10)>0,"Exited","Active") -> Active | P10: =IFERROR(INDEX(Exits_Attrition!$H$2:$H$65,MATCH(A10,Exits_Attrition!$A$2:$A$65,0)),"") | Q10: =ROUND((IF(P10="",AsOf,P10)-M10)/365.25,1) -> 6.9 | R10: =IF(Q10<1,"Under 1 Yr",IF(Q10<3,"1-3 Yrs",IF(Q10<5,"3-5 Yrs","5+ Yrs"))) -> 5+ Yrs | S10: =COUNTIF($E$2:$E$501,A10) -> 12
A11: EMP1010 | B11: Pooja Das | C11: pooja.das@samplecorp.in | D11: Arvind Rao (CEO) | E11: EMP1000 | F11: Head of Finance | G11: L7 | H11: =VALUE(MID(G11,2,1)) -> 7 | I11: Finance | J11: Female | K11: Bengaluru | L11: Full-time | M11: 43793 | N11: 44 | O11: =IF(COUNTIF(Exits_Attrition!$A$2:$A$65,A11)>0,"Exited","Active") -> Active | P11: =IFERROR(INDEX(Exits_Attrition!$H$2:$H$65,MATCH(A11,Exits_Attrition!$A$2:$A$65,0)),"") | Q11: =ROUND((IF(P11="",AsOf,P11)-M11)/365.25,1) -> 6.9 | R11: =IF(Q11<1,"Under 1 Yr",IF(Q11<3,"1-3 Yrs",IF(Q11<5,"3-5 Yrs","5+ Yrs"))) -> 5+ Yrs | S11: =COUNTIF($E$2:$E$501,A11) -> 1
A12: EMP1011 | B12: Trisha Patel | C12: trisha.patel@samplecorp.in | D12: Dev Bose | E12: EMP1429 | F12: Principal Product Manager | G12: L6 | H12: =VALUE(MID(G12,2,1)) -> 6 | I12: Product | J12: Female | K12: Bengaluru | L12: Full-time | M12: 43809 | N12: 42 | O12: =IF(COUNTIF(Exits_Attrition!$A$2:$A$65,A12)>0,"Exited","Active") -> Active | P12: =IFERROR(INDEX(Exits_Attrition!$H$2:$H$65,MATCH(A12,Exits_Attrition!$A$2:$A$65,0)),"") | Q12: =ROUND((IF(P12="",AsOf,P12)-M12)/365.25,1) -> 6.8 | R12: =IF(Q12<1,"Under 1 Yr",IF(Q12<3,"1-3 Yrs",IF(Q12<5,"3-5 Yrs","5+ Yrs"))) -> 5+ Yrs | S12: =COUNTIF($E$2:$E$501,A12) -> 4
A13: EMP1012 | B13: Krishna Kumar | C13: krishna.kumar@samplecorp.in | D13: Amit Kumar | E13: EMP1118 | F13: Operations Lead | G13: L4 | H13: =VALUE(MID(G13,2,1)) -> 4 | I13: Operations | J13: Male | K13: Hyderabad | L13: Full-time | M13: 43829 | N13: 38 | O13: =IF(COUNTIF(Exits_Attrition!$A$2:$A$65,A13)>0,"Exited","Active") -> Active | P13: =IFERROR(INDEX(Exits_Attrition!$H$2:$H$65,MATCH(A13,Exits_Attrition!$A$2:$A$65,0)),"") | Q13: =ROUND((IF(P13="",AsOf,P13)-M13)/365.25,1) -> 6.8 | R13: =IF(Q13<1,"Under 1 Yr",IF(Q13<3,"1-3 Yrs",IF(Q13<5,"3-5 Yrs","5+ Yrs"))) -> 5+ Yrs | S13: =COUNTIF($E$2:$E$501,A13) -> 0
... A501: EMP1500 | B501: Sowmya Patel | C501: sowmya.patel@samplecorp.in | D501: Ramya Khanna | E501: EMP1013 | F501: Compliance Executive | G501: L2 | H501: =VALUE(MID(G501,2,1)) -> 2 | I501: Legal & Compliance | J501: Female | K501: Hyderabad | L501: Full-time | M501: 46289 | N501: 30 | O501: =IF(COUNTIF(Exits_Attrition!$A$2:$A$65,A501)>0,"Exited","Active") -> Active | P501: =IFERROR(INDEX(Exits_Attrition!$H$2:$H$65,MATCH(A501,Exits_Attrition!$A$2:$A$65,0)),"") | Q501: =ROUND((IF(P501="",AsOf,P501)-M501)/365.25,1) -> 0 | R501: =IF(Q501<1,"Under 1 Yr",IF(Q501<3,"1-3 Yrs",IF(Q501<5,"3-5 Yrs","5+ Yrs"))) -> Under 1 Yr | S501: =COUNTIF($E$2:$E$501,A501) -> 0

Sheet Performance
A1: Emp ID | B1: Employee Name | C1: Manager | D1: Department | E1: Level | F1: Status | G1: Rating (1-5) | H1: Rating Label | I1: Previous Rating | J1: Rating Trend | K1: Goals Achieved % | L1: Competency Score | M1: Potential | N1: Performance Band | O1: 9-Box Category | P1: Last Promotion / Joining Date | Q1: Yrs in Current Level | R1: Promotion Eligibility | S1: Eligibility Reason | T1: Review Status
A2: EMP1001 | B2: =INDEX(M_Name,MATCH($A2,M_ID,0)) -> Vidya Kulkarni | C2: =INDEX(M_Mgr,MATCH($A2,M_ID,0)) -> Arvind Rao (CEO) | D2: =INDEX(M_Dept,MATCH($A2,M_ID,0)) -> Human Resources | E2: =INDEX(M_Level,MATCH($A2,M_ID,0)) -> L7 | F2: =INDEX(M_Status,MATCH($A2,M_ID,0)) -> Active | G2: 5 | H2: =INDEX(RatingLbl,MATCH(G2,RatingNo,0)) -> Outstanding | I2: 5 | J2: =IF(G2>I2,"Improved",IF(G2<I2,"Declined","Stable")) -> Stable | K2: 1.1 | L2: 5 | M2: High | N2: =IF(G2>=4,"High",IF(G2=3,"Mid","Low")) -> High | O2: =INDEX(NineBox,MATCH(N2,{"Low","Mid","High"},0),MATCH(M2,{"Low","Medium","High"},0)) -> Star | P2: 46102 | Q2: =(AsOf-P2)/365.25 -> 0.5284052 | R2: =IF(F2="Exited","Not Eligible",IF(AND(G2>=MinRating,Q2>=MinYrs,VALUE(MID(E2,2,1))<=MaxLvl),"Eligible","Not Eligible")) -> Not Eligible | S2: =IF(F2="Exited","Employee has exited",IF(R2="Eligible","Meets rating and time-in-level criteria",IF(VALUE(MID(E2,2,1))>MaxLvl,"Already at top level",IF(G2<MinRating,"Rating below "&MinRating,"Under "&MinYrs&" yrs in current level")))) -> Already at top level | T2: Completed
A3: EMP1002 | B3: =INDEX(M_Name,MATCH($A3,M_ID,0)) -> Vikas Singh | C3: =INDEX(M_Mgr,MATCH($A3,M_ID,0)) -> Yamini Nair | D3: =INDEX(M_Dept,MATCH($A3,M_ID,0)) -> Engineering | E3: =INDEX(M_Level,MATCH($A3,M_ID,0)) -> L5 | F3: =INDEX(M_Status,MATCH($A3,M_ID,0)) -> Active | G3: 4 | H3: =INDEX(RatingLbl,MATCH(G3,RatingNo,0)) -> Exceeds Expectations | I3: 4 | J3: =IF(G3>I3,"Improved",IF(G3<I3,"Declined","Stable")) -> Stable | K3: 0.94 | L3: 4.3 | M3: Medium | N3: =IF(G3>=4,"High",IF(G3=3,"Mid","Low")) -> High | O3: =INDEX(NineBox,MATCH(N3,{"Low","Mid","High"},0),MATCH(M3,{"Low","Medium","High"},0)) -> High Performer | P3: 43401 | Q3: =(AsOf-P3)/365.25 -> 7.9233402 | R3: =IF(F3="Exited","Not Eligible",IF(AND(G3>=MinRating,Q3>=MinYrs,VALUE(MID(E3,2,1))<=MaxLvl),"Eligible","Not Eligible")) -> Eligible | S3: =IF(F3="Exited","Employee has exited",IF(R3="Eligible","Meets rating and time-in-level criteria",IF(VALUE(MID(E3,2,1))>MaxLvl,"Already at top level",IF(G3<MinRating,"Rating below "&MinRating,"Under "&MinYrs&" yrs in current level")))) -> Meets rating and time-in-level criteria | T3: Completed
A4: EMP1003 | B4: =INDEX(M_Name,MATCH($A4,M_ID,0)) -> Prakash Das | C4: =INDEX(M_Mgr,MATCH($A4,M_ID,0)) -> Vidya Kulkarni | D4: =INDEX(M_Dept,MATCH($A4,M_ID,0)) -> Human Resources | E4: =INDEX(M_Level,MATCH($A4,M_ID,0)) -> L6 | F4: =INDEX(M_Status,MATCH($A4,M_ID,0)) -> Active | G4: 2 | H4: =INDEX(RatingLbl,MATCH(G4,RatingNo,0)) -> Needs Improvement | I4: 1 | J4: =IF(G4>I4,"Improved",IF(G4<I4,"Declined","Stable")) -> Improved | K4: 0.64 | L4: 1.3 | M4: Medium | N4: =IF(G4>=4,"High",IF(G4=3,"Mid","Low")) -> Low | O4: =INDEX(NineBox,MATCH(N4,{"Low","Mid","High"},0),MATCH(M4,{"Low","Medium","High"},0)) -> Inconsistent Player | P4: 43538 | Q4: =(AsOf-P4)/365.25 -> 7.5482546 | R4: =IF(F4="Exited","Not Eligible",IF(AND(G4>=MinRating,Q4>=MinYrs,VALUE(MID(E4,2,1))<=MaxLvl),"Eligible","Not Eligible")) -> Not Eligible | S4: =IF(F4="Exited","Employee has exited",IF(R4="Eligible","Meets rating and time-in-level criteria",IF(VALUE(MID(E4,2,1))>MaxLvl,"Already at top level",IF(G4<MinRating,"Rating below "&MinRating,"Under "&MinYrs&" yrs in current level")))) -> Rating below 4 | T4: Completed
A5: EMP1004 | B5: =INDEX(M_Name,MATCH($A5,M_ID,0)) -> Fatima Choudhary | C5: =INDEX(M_Mgr,MATCH($A5,M_ID,0)) -> Yamini Nair | D5: =INDEX(M_Dept,MATCH($A5,M_ID,0)) -> Engineering | E5: =INDEX(M_Level,MATCH($A5,M_ID,0)) -> L5 | F5: =INDEX(M_Status,MATCH($A5,M_ID,0)) -> Active | G5: 2 | H5: =INDEX(RatingLbl,MATCH(G5,RatingNo,0)) -> Needs Improvement | I5: 2 | J5: =IF(G5>I5,"Improved",IF(G5<I5,"Declined","Stable")) -> Stable | K5: 0.64 | L5: 2.3 | M5: Medium | N5: =IF(G5>=4,"High",IF(G5=3,"Mid","Low")) -> Low | O5: =INDEX(NineBox,MATCH(N5,{"Low","Mid","High"},0),MATCH(M5,{"Low","Medium","High"},0)) -> Inconsistent Player | P5: 43552 | Q5: =(AsOf-P5)/365.25 -> 7.5099247 | R5: =IF(F5="Exited","Not Eligible",IF(AND(G5>=MinRating,Q5>=MinYrs,VALUE(MID(E5,2,1))<=MaxLvl),"Eligible","Not Eligible")) -> Not Eligible | S5: =IF(F5="Exited","Employee has exited",IF(R5="Eligible","Meets rating and time-in-level criteria",IF(VALUE(MID(E5,2,1))>MaxLvl,"Already at top level",IF(G5<MinRating,"Rating below "&MinRating,"Under "&MinYrs&" yrs in current level")))) -> Rating below 4 | T5: Completed
A6: EMP1005 | B6: =INDEX(M_Name,MATCH($A6,M_ID,0)) -> Gaurav Fernandes | C6: =INDEX(M_Mgr,MATCH($A6,M_ID,0)) -> Yamini Nair | D6: =INDEX(M_Dept,MATCH($A6,M_ID,0)) -> Engineering | E6: =INDEX(M_Level,MATCH($A6,M_ID,0)) -> L5 | F6: =INDEX(M_Status,MATCH($A6,M_ID,0)) -> Active | G6: 3 | H6: =INDEX(RatingLbl,MATCH(G6,RatingNo,0)) -> Meets Expectations | I6: 3 | J6: =IF(G6>I6,"Improved",IF(G6<I6,"Declined","Stable")) -> Stable | K6: 0.99 | L6: 2.9 | M6: Medium | N6: =IF(G6>=4,"High",IF(G6=3,"Mid","Low")) -> Mid | O6: =INDEX(NineBox,MATCH(N6,{"Low","Mid","High"},0),MATCH(M6,{"Low","Medium","High"},0)) -> Core Player | P6: 44549 | Q6: =(AsOf-P6)/365.25 -> 4.7802875 | R6: =IF(F6="Exited","Not Eligible",IF(AND(G6>=MinRating,Q6>=MinYrs,VALUE(MID(E6,2,1))<=MaxLvl),"Eligible","Not Eligible")) -> Not Eligible | S6: =IF(F6="Exited","Employee has exited",IF(R6="Eligible","Meets rating and time-in-level criteria",IF(VALUE(MID(E6,2,1))>MaxLvl,"Already at top level",IF(G6<MinRating,"Rating below "&MinRating,"Under "&MinYrs&" yrs in current level")))) -> Rating below 4 | T6: Completed
A7: EMP1006 | B7: =INDEX(M_Name,MATCH($A7,M_ID,0)) -> Yash Shah | C7: =INDEX(M_Mgr,MATCH($A7,M_ID,0)) -> Pallavi Shah | D7: =INDEX(M_Dept,MATCH($A7,M_ID,0)) -> Operations | E7: =INDEX(M_Level,MATCH($A7,M_ID,0)) -> L5 | F7: =INDEX(M_Status,MATCH($A7,M_ID,0)) -> Exited | G7: 4 | H7: =INDEX(RatingLbl,MATCH(G7,RatingNo,0)) -> Exceeds Expectations | I7: 4 | J7: =IF(G7>I7,"Improved",IF(G7<I7,"Declined","Stable")) -> Stable | K7: 0.95 | L7: 4 | M7: Medium | N7: =IF(G7>=4,"High",IF(G7=3,"Mid","Low")) -> High | O7: =INDEX(NineBox,MATCH(N7,{"Low","Mid","High"},0),MATCH(M7,{"Low","Medium","High"},0)) -> High Performer | P7: 43681 | Q7: =(AsOf-P7)/365.25 -> 7.156742 | R7: =IF(F7="Exited","Not Eligible",IF(AND(G7>=MinRating,Q7>=MinYrs,VALUE(MID(E7,2,1))<=MaxLvl),"Eligible","Not Eligible")) -> Not Eligible | S7: =IF(F7="Exited","Employee has exited",IF(R7="Eligible","Meets rating and time-in-level criteria",IF(VALUE(MID(E7,2,1))>MaxLvl,"Already at top level",IF(G7<MinRating,"Rating below "&MinRating,"Under "&MinYrs&" yrs in current level")))) -> Employee has exited | T7: Completed
A8: EMP1007 | B8: =INDEX(M_Name,MATCH($A8,M_ID,0)) -> Imran Tiwari | C8: =INDEX(M_Mgr,MATCH($A8,M_ID,0)) -> Nandini Iyer | D8: =INDEX(M_Dept,MATCH($A8,M_ID,0)) -> Marketing | E8: =INDEX(M_Level,MATCH($A8,M_ID,0)) -> L4 | F8: =INDEX(M_Status,MATCH($A8,M_ID,0)) -> Exited | G8: 1 | H8: =INDEX(RatingLbl,MATCH(G8,RatingNo,0)) -> Unsatisfactory | I8: 2 | J8: =IF(G8>I8,"Improved",IF(G8<I8,"Declined","Stable")) -> Declined | K8: 0.45 | L8: 1.2 | M8: Low | N8: =IF(G8>=4,"High",IF(G8=3,"Mid","Low")) -> Low | O8: =INDEX(NineBox,MATCH(N8,{"Low","Mid","High"},0),MATCH(M8,{"Low","Medium","High"},0)) -> Underperformer | P8: 44527 | Q8: =(AsOf-P8)/365.25 -> 4.8405202 | R8: =IF(F8="Exited","Not Eligible",IF(AND(G8>=MinRating,Q8>=MinYrs,VALUE(MID(E8,2,1))<=MaxLvl),"Eligible","Not Eligible")) -> Not Eligible | S8: =IF(F8="Exited","Employee has exited",IF(R8="Eligible","Meets rating and time-in-level criteria",IF(VALUE(MID(E8,2,1))>MaxLvl,"Already at top level",IF(G8<MinRating,"Rating below "&MinRating,"Under "&MinYrs&" yrs in current level")))) -> Employee has exited | T8: Completed
A9: EMP1008 | B9: =INDEX(M_Name,MATCH($A9,M_ID,0)) -> Aishwarya Khan | C9: =INDEX(M_Mgr,MATCH($A9,M_ID,0)) -> Arvind Rao (CEO) | D9: =INDEX(M_Dept,MATCH($A9,M_ID,0)) -> Engineering | E9: =INDEX(M_Level,MATCH($A9,M_ID,0)) -> L7 | F9: =INDEX(M_Status,MATCH($A9,M_ID,0)) -> Active | G9: 3 | H9: =INDEX(RatingLbl,MATCH(G9,RatingNo,0)) -> Meets Expectations | I9: 3 | J9: =IF(G9>I9,"Improved",IF(G9<I9,"Declined","Stable")) -> Stable | K9: 0.83 | L9: 3.4 | M9: Medium | N9: =IF(G9>=4,"High",IF(G9=3,"Mid","Low")) -> Mid | O9: =INDEX(NineBox,MATCH(N9,{"Low","Mid","High"},0),MATCH(M9,{"Low","Medium","High"},0)) -> Core Player | P9: 43771 | Q9: =(AsOf-P9)/365.25 -> 6.9103354 | R9: =IF(F9="Exited","Not Eligible",IF(AND(G9>=MinRating,Q9>=MinYrs,VALUE(MID(E9,2,1))<=MaxLvl),"Eligible","Not Eligible")) -> Not Eligible | S9: =IF(F9="Exited","Employee has exited",IF(R9="Eligible","Meets rating and time-in-level criteria",IF(VALUE(MID(E9,2,1))>MaxLvl,"Already at top level",IF(G9<MinRating,"Rating below "&MinRating,"Under "&MinYrs&" yrs in current level")))) -> Already at top level | T9: Completed
A10: EMP1009 | B10: =INDEX(M_Name,MATCH($A10,M_ID,0)) -> Ankit Khanna | C10: =INDEX(M_Mgr,MATCH($A10,M_ID,0)) -> Imran Mishra | D10: =INDEX(M_Dept,MATCH($A10,M_ID,0)) -> Operations | E10: =INDEX(M_Level,MATCH($A10,M_ID,0)) -> L5 | F10: =INDEX(M_Status,MATCH($A10,M_ID,0)) -> Active | G10: 3 | H10: =INDEX(RatingLbl,MATCH(G10,RatingNo,0)) -> Meets Expectations | I10: 3 | J10: =IF(G10>I10,"Improved",IF(G10<I10,"Declined","Stable")) -> Stable | K10: 0.84 | L10: 3.8 | M10: Medium | N10: =IF(G10>=4,"High",IF(G10=3,"Mid","Low")) -> Mid | O10: =INDEX(NineBox,MATCH(N10,{"Low","Mid","High"},0),MATCH(M10,{"Low","Medium","High"},0)) -> Core Player | P10: 43783 | Q10: =(AsOf-P10)/365.25 -> 6.8774812 | R10: =IF(F10="Exited","Not Eligible",IF(AND(G10>=MinRating,Q10>=MinYrs,VALUE(MID(E10,2,1))<=MaxLvl),"Eligible","Not Eligible")) -> Not Eligible | S10: =IF(F10="Exited","Employee has exited",IF(R10="Eligible","Meets rating and time-in-level criteria",IF(VALUE(MID(E10,2,1))>MaxLvl,"Already at top level",IF(G10<MinRating,"Rating below "&MinRating,"Under "&MinYrs&" yrs in current level")))) -> Rating below 4 | T10: Completed
A11: EMP1010 | B11: =INDEX(M_Name,MATCH($A11,M_ID,0)) -> Pooja Das | C11: =INDEX(M_Mgr,MATCH($A11,M_ID,0)) -> Arvind Rao (CEO) | D11: =INDEX(M_Dept,MATCH($A11,M_ID,0)) -> Finance | E11: =INDEX(M_Level,MATCH($A11,M_ID,0)) -> L7 | F11: =INDEX(M_Status,MATCH($A11,M_ID,0)) -> Active | G11: 2 | H11: =INDEX(RatingLbl,MATCH(G11,RatingNo,0)) -> Needs Improvement | I11: 2 | J11: =IF(G11>I11,"Improved",IF(G11<I11,"Declined","Stable")) -> Stable | K11: 0.81 | L11: 1.9 | M11: Medium | N11: =IF(G11>=4,"High",IF(G11=3,"Mid","Low")) -> Low | O11: =INDEX(NineBox,MATCH(N11,{"Low","Mid","High"},0),MATCH(M11,{"Low","Medium","High"},0)) -> Inconsistent Player | P11: 43793 | Q11: =(AsOf-P11)/365.25 -> 6.8501027 | R11: =IF(F11="Exited","Not Eligible",IF(AND(G11>=MinRating,Q11>=MinYrs,VALUE(MID(E11,2,1))<=MaxLvl),"Eligible","Not Eligible")) -> Not Eligible | S11: =IF(F11="Exited","Employee has exited",IF(R11="Eligible","Meets rating and time-in-level criteria",IF(VALUE(MID(E11,2,1))>MaxLvl,"Already at top level",IF(G11<MinRating,"Rating below "&MinRating,"Under "&MinYrs&" yrs in current level")))) -> Already at top level | T11: Completed
A12: EMP1011 | B12: =INDEX(M_Name,MATCH($A12,M_ID,0)) -> Trisha Patel | C12: =INDEX(M_Mgr,MATCH($A12,M_ID,0)) -> Dev Bose | D12: =INDEX(M_Dept,MATCH($A12,M_ID,0)) -> Product | E12: =INDEX(M_Level,MATCH($A12,M_ID,0)) -> L6 | F12: =INDEX(M_Status,MATCH($A12,M_ID,0)) -> Active | G12: 3 | H12: =INDEX(RatingLbl,MATCH(G12,RatingNo,0)) -> Meets Expectations | I12: 3 | J12: =IF(G12>I12,"Improved",IF(G12<I12,"Declined","Stable")) -> Stable | K12: 0.86 | L12: 3.8 | M12: Medium | N12: =IF(G12>=4,"High",IF(G12=3,"Mid","Low")) -> Mid | O12: =INDEX(NineBox,MATCH(N12,{"Low","Mid","High"},0),MATCH(M12,{"Low","Medium","High"},0)) -> Core Player | P12: 44193 | Q12: =(AsOf-P12)/365.25 -> 5.7549624 | R12: =IF(F12="Exited","Not Eligible",IF(AND(G12>=MinRating,Q12>=MinYrs,VALUE(MID(E12,2,1))<=MaxLvl),"Eligible","Not Eligible")) -> Not Eligible | S12: =IF(F12="Exited","Employee has exited",IF(R12="Eligible","Meets rating and time-in-level criteria",IF(VALUE(MID(E12,2,1))>MaxLvl,"Already at top level",IF(G12<MinRating,"Rating below "&MinRating,"Under "&MinYrs&" yrs in current level")))) -> Rating below 4 | T12: Completed
A13: EMP1012 | B13: =INDEX(M_Name,MATCH($A13,M_ID,0)) -> Krishna Kumar | C13: =INDEX(M_Mgr,MATCH($A13,M_ID,0)) -> Amit Kumar | D13: =INDEX(M_Dept,MATCH($A13,M_ID,0)) -> Operations | E13: =INDEX(M_Level,MATCH($A13,M_ID,0)) -> L4 | F13: =INDEX(M_Status,MATCH($A13,M_ID,0)) -> Active | G13: 3 | H13: =INDEX(RatingLbl,MATCH(G13,RatingNo,0)) -> Meets Expectations | I13: 4 | J13: =IF(G13>I13,"Improved",IF(G13<I13,"Declined","Stable")) -> Declined | K13: 0.74 | L13: 2.9 | M13: Medium | N13: =IF(G13>=4,"High",IF(G13=3,"Mid","Low")) -> Mid | O13: =INDEX(NineBox,MATCH(N13,{"Low","Mid","High"},0),MATCH(M13,{"Low","Medium","High"},0)) -> Core Player | P13: 45952 | Q13: =(AsOf-P13)/365.25 -> 0.93908282 | R13: =IF(F13="Exited","Not Eligible",IF(AND(G13>=MinRating,Q13>=MinYrs,VALUE(MID(E13,2,1))<=MaxLvl),"Eligible","Not Eligible")) -> Not Eligible | S13: =IF(F13="Exited","Employee has exited",IF(R13="Eligible","Meets rating and time-in-level criteria",IF(VALUE(MID(E13,2,1))>MaxLvl,"Already at top level",IF(G13<MinRating,"Rating below "&MinRating,"Under "&MinYrs&" yrs in current level")))) -> Rating below 4 | T13: Completed
... A501: EMP1500 | B501: =INDEX(M_Name,MATCH($A501,M_ID,0)) -> Sowmya Patel | C501: =INDEX(M_Mgr,MATCH($A501,M_ID,0)) -> Ramya Khanna | D501: =INDEX(M_Dept,MATCH($A501,M_ID,0)) -> Legal & Compliance | E501: =INDEX(M_Level,MATCH($A501,M_ID,0)) -> L2 | F501: =INDEX(M_Status,MATCH($A501,M_ID,0)) -> Active | G501: 2 | H501: =INDEX(RatingLbl,MATCH(G501,RatingNo,0)) -> Needs Improvement | I501: 1 | J501: =IF(G501>I501,"Improved",IF(G501<I501,"Declined","Stable")) -> Improved | K501: 0.66 | L501: 2.3 | M501: Low | N501: =IF(G501>=4,"High",IF(G501=3,"Mid","Low")) -> Low | O501: =INDEX(NineBox,MATCH(N501,{"Low","Mid","High"},0),MATCH(M501,{"Low","Medium","High"},0)) -> Underperformer | P501: 46289 | Q501: =(AsOf-P501)/365.25 -> 0.016427105 | R501: =IF(F501="Exited","Not Eligible",IF(AND(G501>=MinRating,Q501>=MinYrs,VALUE(MID(E501,2,1))<=MaxLvl),"Eligible","Not Eligible")) -> Not Eligible | S501: =IF(F501="Exited","Employee has exited",IF(R501="Eligible","Meets rating and time-in-level criteria",IF(VALUE(MID(E501,2,1))>MaxLvl,"Already at top level",IF(G501<MinRating,"Rating below "&MinRating,"Under "&MinYrs&" yrs in current level")))) -> Rating below 4 | T501: Completed

Sheet Compensation
A1: Emp ID | B1: Employee Name | C1: Department | D1: Level | E1: Status | F1: Annual CTC (₹) | G1: Band Min (₹) | H1: Band Mid (₹) | I1: Band Max (₹) | J1: Compa-Ratio | K1: Band Position | L1: Rating | M1: Increment % | N1: Revised CTC (₹) | O1: Variable Bonus % | P1: Bonus Amount (₹) | Q1: ESOP Eligible
A2: EMP1001 | B2: =INDEX(M_Name,MATCH($A2,M_ID,0)) -> Vidya Kulkarni | C2: =INDEX(M_Dept,MATCH($A2,M_ID,0)) -> Human Resources | D2: =INDEX(M_Level,MATCH($A2,M_ID,0)) -> L7 | E2: =INDEX(M_Status,MATCH($A2,M_ID,0)) -> Active | F2: 7632000 | G2: =INDEX(BandMin,MATCH(D2,BandLevels,0)) -> 5100000 | H2: =INDEX(BandMid,MATCH(D2,BandLevels,0)) -> 8250000 | I2: =INDEX(BandMax,MATCH(D2,BandLevels,0)) -> 11400000 | J2: =ROUND(F2/H2,2) -> 0.93 | K2: =IF(F2<G2,"Below Band",IF(F2>I2,"Above Band","Within Band")) -> Within Band | L2: =INDEX(P_Rating,MATCH($A2,M_ID,0)) -> 5 | M2: 0.161 | N2: =IF(E2="Exited",0,ROUND(F2*(1+M2),-2)) -> 8860800 | O2: 0.18 | P2: =IF(E2="Exited",0,ROUND(F2*O2,-2)) -> 1373800 | Q2: Yes
A3: EMP1002 | B3: =INDEX(M_Name,MATCH($A3,M_ID,0)) -> Vikas Singh | C3: =INDEX(M_Dept,MATCH($A3,M_ID,0)) -> Engineering | D3: =INDEX(M_Level,MATCH($A3,M_ID,0)) -> L5 | E3: =INDEX(M_Status,MATCH($A3,M_ID,0)) -> Active | F3: 4407000 | G3: =INDEX(BandMin,MATCH(D3,BandLevels,0)) -> 2295000 | H3: =INDEX(BandMid,MATCH(D3,BandLevels,0)) -> 3667500 | I3: =INDEX(BandMax,MATCH(D3,BandLevels,0)) -> 5040000 | J3: =ROUND(F3/H3,2) -> 1.2 | K3: =IF(F3<G3,"Below Band",IF(F3>I3,"Above Band","Within Band")) -> Within Band | L3: =INDEX(P_Rating,MATCH($A3,M_ID,0)) -> 4 | M3: 0.133 | N3: =IF(E3="Exited",0,ROUND(F3*(1+M3),-2)) -> 4993100 | O3: 0.12 | P3: =IF(E3="Exited",0,ROUND(F3*O3,-2)) -> 528800 | Q3: Yes
A4: EMP1003 | B4: =INDEX(M_Name,MATCH($A4,M_ID,0)) -> Prakash Das | C4: =INDEX(M_Dept,MATCH($A4,M_ID,0)) -> Human Resources | D4: =INDEX(M_Level,MATCH($A4,M_ID,0)) -> L6 | E4: =INDEX(M_Status,MATCH($A4,M_ID,0)) -> Active | F4: 5106000 | G4: =INDEX(BandMin,MATCH(D4,BandLevels,0)) -> 3570000 | H4: =INDEX(BandMid,MATCH(D4,BandLevels,0)) -> 5385000 | I4: =INDEX(BandMax,MATCH(D4,BandLevels,0)) -> 7200000 | J4: =ROUND(F4/H4,2) -> 0.95 | K4: =IF(F4<G4,"Below Band",IF(F4>I4,"Above Band","Within Band")) -> Within Band | L4: =INDEX(P_Rating,MATCH($A4,M_ID,0)) -> 2 | M4: 0.03 | N4: =IF(E4="Exited",0,ROUND(F4*(1+M4),-2)) -> 5259200 | O4: 0.03 | P4: =IF(E4="Exited",0,ROUND(F4*O4,-2)) -> 153200 | Q4: Yes
A5: EMP1004 | B5: =INDEX(M_Name,MATCH($A5,M_ID,0)) -> Fatima Choudhary | C5: =INDEX(M_Dept,MATCH($A5,M_ID,0)) -> Engineering | D5: =INDEX(M_Level,MATCH($A5,M_ID,0)) -> L5 | E5: =INDEX(M_Status,MATCH($A5,M_ID,0)) -> Active | F5: 4489000 | G5: =INDEX(BandMin,MATCH(D5,BandLevels,0)) -> 2295000 | H5: =INDEX(BandMid,MATCH(D5,BandLevels,0)) -> 3667500 | I5: =INDEX(BandMax,MATCH(D5,BandLevels,0)) -> 5040000 | J5: =ROUND(F5/H5,2) -> 1.22 | K5: =IF(F5<G5,"Below Band",IF(F5>I5,"Above Band","Within Band")) -> Within Band | L5: =INDEX(P_Rating,MATCH($A5,M_ID,0)) -> 2 | M5: 0.019 | N5: =IF(E5="Exited",0,ROUND(F5*(1+M5),-2)) -> 4574300 | O5: 0.03 | P5: =IF(E5="Exited",0,ROUND(F5*O5,-2)) -> 134700 | Q5: Yes
A6: EMP1005 | B6: =INDEX(M_Name,MATCH($A6,M_ID,0)) -> Gaurav Fernandes | C6: =INDEX(M_Dept,MATCH($A6,M_ID,0)) -> Engineering | D6: =INDEX(M_Level,MATCH($A6,M_ID,0)) -> L5 | E6: =INDEX(M_Status,MATCH($A6,M_ID,0)) -> Active | F6: 4938000 | G6: =INDEX(BandMin,MATCH(D6,BandLevels,0)) -> 2295000 | H6: =INDEX(BandMid,MATCH(D6,BandLevels,0)) -> 3667500 | I6: =INDEX(BandMax,MATCH(D6,BandLevels,0)) -> 5040000 | J6: =ROUND(F6/H6,2) -> 1.35 | K6: =IF(F6<G6,"Below Band",IF(F6>I6,"Above Band","Within Band")) -> Within Band | L6: =INDEX(P_Rating,MATCH($A6,M_ID,0)) -> 3 | M6: 0.07 | N6: =IF(E6="Exited",0,ROUND(F6*(1+M6),-2)) -> 5283700 | O6: 0.08 | P6: =IF(E6="Exited",0,ROUND(F6*O6,-2)) -> 395000 | Q6: Yes
A7: EMP1006 | B7: =INDEX(M_Name,MATCH($A7,M_ID,0)) -> Yash Shah | C7: =INDEX(M_Dept,MATCH($A7,M_ID,0)) -> Operations | D7: =INDEX(M_Level,MATCH($A7,M_ID,0)) -> L5 | E7: =INDEX(M_Status,MATCH($A7,M_ID,0)) -> Exited | F7: 2714000 | G7: =INDEX(BandMin,MATCH(D7,BandLevels,0)) -> 2295000 | H7: =INDEX(BandMid,MATCH(D7,BandLevels,0)) -> 3667500 | I7: =INDEX(BandMax,MATCH(D7,BandLevels,0)) -> 5040000 | J7: =ROUND(F7/H7,2) -> 0.74 | K7: =IF(F7<G7,"Below Band",IF(F7>I7,"Above Band","Within Band")) -> Within Band | L7: =INDEX(P_Rating,MATCH($A7,M_ID,0)) -> 4 | M7: 0.124 | N7: =IF(E7="Exited",0,ROUND(F7*(1+M7),-2)) -> 0 | O7: 0.12 | P7: =IF(E7="Exited",0,ROUND(F7*O7,-2)) -> 0 | Q7: Yes
A8: EMP1007 | B8: =INDEX(M_Name,MATCH($A8,M_ID,0)) -> Imran Tiwari | C8: =INDEX(M_Dept,MATCH($A8,M_ID,0)) -> Marketing | D8: =INDEX(M_Level,MATCH($A8,M_ID,0)) -> L4 | E8: =INDEX(M_Status,MATCH($A8,M_ID,0)) -> Exited | F8: 2229000 | G8: =INDEX(BandMin,MATCH(D8,BandLevels,0)) -> 1445000 | H8: =INDEX(BandMid,MATCH(D8,BandLevels,0)) -> 2342500 | I8: =INDEX(BandMax,MATCH(D8,BandLevels,0)) -> 3240000 | J8: =ROUND(F8/H8,2) -> 0.95 | K8: =IF(F8<G8,"Below Band",IF(F8>I8,"Above Band","Within Band")) -> Within Band | L8: =INDEX(P_Rating,MATCH($A8,M_ID,0)) -> 1 | M8: -0.004 | N8: =IF(E8="Exited",0,ROUND(F8*(1+M8),-2)) -> 0 | O8: 0 | P8: =IF(E8="Exited",0,ROUND(F8*O8,-2)) -> 0 | Q8: No
A9: EMP1008 | B9: =INDEX(M_Name,MATCH($A9,M_ID,0)) -> Aishwarya Khan | C9: =INDEX(M_Dept,MATCH($A9,M_ID,0)) -> Engineering | D9: =INDEX(M_Level,MATCH($A9,M_ID,0)) -> L7 | E9: =INDEX(M_Status,MATCH($A9,M_ID,0)) -> Active | F9: 9208000 | G9: =INDEX(BandMin,MATCH(D9,BandLevels,0)) -> 5100000 | H9: =INDEX(BandMid,MATCH(D9,BandLevels,0)) -> 8250000 | I9: =INDEX(BandMax,MATCH(D9,BandLevels,0)) -> 11400000 | J9: =ROUND(F9/H9,2) -> 1.12 | K9: =IF(F9<G9,"Below Band",IF(F9>I9,"Above Band","Within Band")) -> Within Band | L9: =INDEX(P_Rating,MATCH($A9,M_ID,0)) -> 3 | M9: 0.087 | N9: =IF(E9="Exited",0,ROUND(F9*(1+M9),-2)) -> 10009100 | O9: 0.08 | P9: =IF(E9="Exited",0,ROUND(F9*O9,-2)) -> 736600 | Q9: Yes
A10: EMP1009 | B10: =INDEX(M_Name,MATCH($A10,M_ID,0)) -> Ankit Khanna | C10: =INDEX(M_Dept,MATCH($A10,M_ID,0)) -> Operations | D10: =INDEX(M_Level,MATCH($A10,M_ID,0)) -> L5 | E10: =INDEX(M_Status,MATCH($A10,M_ID,0)) -> Active | F10: 3608000 | G10: =INDEX(BandMin,MATCH(D10,BandLevels,0)) -> 2295000 | H10: =INDEX(BandMid,MATCH(D10,BandLevels,0)) -> 3667500 | I10: =INDEX(BandMax,MATCH(D10,BandLevels,0)) -> 5040000 | J10: =ROUND(F10/H10,2) -> 0.98 | K10: =IF(F10<G10,"Below Band",IF(F10>I10,"Above Band","Within Band")) -> Within Band | L10: =INDEX(P_Rating,MATCH($A10,M_ID,0)) -> 3 | M10: 0.092 | N10: =IF(E10="Exited",0,ROUND(F10*(1+M10),-2)) -> 3939900 | O10: 0.08 | P10: =IF(E10="Exited",0,ROUND(F10*O10,-2)) -> 288600 | Q10: Yes
A11: EMP1010 | B11: =INDEX(M_Name,MATCH($A11,M_ID,0)) -> Pooja Das | C11: =INDEX(M_Dept,MATCH($A11,M_ID,0)) -> Finance | D11: =INDEX(M_Level,MATCH($A11,M_ID,0)) -> L7 | E11: =INDEX(M_Status,MATCH($A11,M_ID,0)) -> Active | F11: 8136000 | G11: =INDEX(BandMin,MATCH(D11,BandLevels,0)) -> 5100000 | H11: =INDEX(BandMid,MATCH(D11,BandLevels,0)) -> 8250000 | I11: =INDEX(BandMax,MATCH(D11,BandLevels,0)) -> 11400000 | J11: =ROUND(F11/H11,2) -> 0.99 | K11: =IF(F11<G11,"Below Band",IF(F11>I11,"Above Band","Within Band")) -> Within Band | L11: =INDEX(P_Rating,MATCH($A11,M_ID,0)) -> 2 | M11: 0.045 | N11: =IF(E11="Exited",0,ROUND(F11*(1+M11),-2)) -> 8502100 | O11: 0.03 | P11: =IF(E11="Exited",0,ROUND(F11*O11,-2)) -> 244100 | Q11: Yes
A12: EMP1011 | B12: =INDEX(M_Name,MATCH($A12,M_ID,0)) -> Trisha Patel | C12: =INDEX(M_Dept,MATCH($A12,M_ID,0)) -> Product | D12: =INDEX(M_Level,MATCH($A12,M_ID,0)) -> L6 | E12: =INDEX(M_Status,MATCH($A12,M_ID,0)) -> Active | F12: 5657000 | G12: =INDEX(BandMin,MATCH(D12,BandLevels,0)) -> 3570000 | H12: =INDEX(BandMid,MATCH(D12,BandLevels,0)) -> 5385000 | I12: =INDEX(BandMax,MATCH(D12,BandLevels,0)) -> 7200000 | J12: =ROUND(F12/H12,2) -> 1.05 | K12: =IF(F12<G12,"Below Band",IF(F12>I12,"Above Band","Within Band")) -> Within Band | L12: =INDEX(P_Rating,MATCH($A12,M_ID,0)) -> 3 | M12: 0.07 | N12: =IF(E12="Exited",0,ROUND(F12*(1+M12),-2)) -> 6053000 | O12: 0.08 | P12: =IF(E12="Exited",0,ROUND(F12*O12,-2)) -> 452600 | Q12: Yes
A13: EMP1012 | B13: =INDEX(M_Name,MATCH($A13,M_ID,0)) -> Krishna Kumar | C13: =INDEX(M_Dept,MATCH($A13,M_ID,0)) -> Operations | D13: =INDEX(M_Level,MATCH($A13,M_ID,0)) -> L4 | E13: =INDEX(M_Status,MATCH($A13,M_ID,0)) -> Active | F13: 1721000 | G13: =INDEX(BandMin,MATCH(D13,BandLevels,0)) -> 1445000 | H13: =INDEX(BandMid,MATCH(D13,BandLevels,0)) -> 2342500 | I13: =INDEX(BandMax,MATCH(D13,BandLevels,0)) -> 3240000 | J13: =ROUND(F13/H13,2) -> 0.73 | K13: =IF(F13<G13,"Below Band",IF(F13>I13,"Above Band","Within Band")) -> Within Band | L13: =INDEX(P_Rating,MATCH($A13,M_ID,0)) -> 3 | M13: 0.087 | N13: =IF(E13="Exited",0,ROUND(F13*(1+M13),-2)) -> 1870700 | O13: 0.08 | P13: =IF(E13="Exited",0,ROUND(F13*O13,-2)) -> 137700 | Q13: No
... A501: EMP1500 | B501: =INDEX(M_Name,MATCH($A501,M_ID,0)) -> Sowmya Patel | C501: =INDEX(M_Dept,MATCH($A501,M_ID,0)) -> Legal & Compliance | D501: =INDEX(M_Level,MATCH($A501,M_ID,0)) -> L2 | E501: =INDEX(M_Status,MATCH($A501,M_ID,0)) -> Active | F501: 926000 | G501: =INDEX(BandMin,MATCH(D501,BandLevels,0)) -> 510000 | H501: =INDEX(BandMid,MATCH(D501,BandLevels,0)) -> 855000 | I501: =INDEX(BandMax,MATCH(D501,BandLevels,0)) -> 1200000 | J501: =ROUND(F501/H501,2) -> 1.08 | K501: =IF(F501<G501,"Below Band",IF(F501>I501,"Above Band","Within Band")) -> Within Band | L501: =INDEX(P_Rating,MATCH($A501,M_ID,0)) -> 2 | M501: 0.016 | N501: =IF(E501="Exited",0,ROUND(F501*(1+M501),-2)) -> 940800 | O501: 0.03 | P501: =IF(E501="Exited",0,ROUND(F501*O501,-2)) -> 27800 | Q501: No

Sheet Attendance_Leave
A1: Emp ID | B1: Employee Name | C1: Department | D1: Status | E1: Working Days (12M) | F1: Planned Leave | G1: Sick Leave | H1: Unplanned Leave | I1: Total Leave | J1: Days Present | K1: Attendance % | L1: WFH Days | M1: Late Marks | N1: Overtime Hrs | O1: Absence Flag
A2: EMP1001 | B2: =INDEX(M_Name,MATCH($A2,M_ID,0)) -> Vidya Kulkarni | C2: =INDEX(M_Dept,MATCH($A2,M_ID,0)) -> Human Resources | D2: =INDEX(M_Status,MATCH($A2,M_ID,0)) -> Active | E2: 250 | F2: 13 | G2: 2 | H2: 3 | I2: =SUM(F2:H2) -> 18 | J2: =E2-I2 -> 232 | K2: =IFERROR(J2/E2,0) -> 0.928 | L2: 77 | M2: 14 | N2: 14 | O2: =IF(H2>=8,"High Unplanned",IF(K2<0.9,"Low Attendance","Normal")) -> Normal
A3: EMP1002 | B3: =INDEX(M_Name,MATCH($A3,M_ID,0)) -> Vikas Singh | C3: =INDEX(M_Dept,MATCH($A3,M_ID,0)) -> Engineering | D3: =INDEX(M_Status,MATCH($A3,M_ID,0)) -> Active | E3: 250 | F3: 8 | G3: 1 | H3: 1 | I3: =SUM(F3:H3) -> 10 | J3: =E3-I3 -> 240 | K3: =IFERROR(J3/E3,0) -> 0.96 | L3: 27 | M3: 8 | N3: 45 | O3: =IF(H3>=8,"High Unplanned",IF(K3<0.9,"Low Attendance","Normal")) -> Normal
A4: EMP1003 | B4: =INDEX(M_Name,MATCH($A4,M_ID,0)) -> Prakash Das | C4: =INDEX(M_Dept,MATCH($A4,M_ID,0)) -> Human Resources | D4: =INDEX(M_Status,MATCH($A4,M_ID,0)) -> Active | E4: 250 | F4: 6 | G4: 6 | H4: 5 | I4: =SUM(F4:H4) -> 17 | J4: =E4-I4 -> 233 | K4: =IFERROR(J4/E4,0) -> 0.932 | L4: 57 | M4: 1 | N4: 21 | O4: =IF(H4>=8,"High Unplanned",IF(K4<0.9,"Low Attendance","Normal")) -> Normal
A5: EMP1004 | B5: =INDEX(M_Name,MATCH($A5,M_ID,0)) -> Fatima Choudhary | C5: =INDEX(M_Dept,MATCH($A5,M_ID,0)) -> Engineering | D5: =INDEX(M_Status,MATCH($A5,M_ID,0)) -> Active | E5: 250 | F5: 20 | G5: 3 | H5: 7 | I5: =SUM(F5:H5) -> 30 | J5: =E5-I5 -> 220 | K5: =IFERROR(J5/E5,0) -> 0.88 | L5: 47 | M5: 4 | N5: 61 | O5: =IF(H5>=8,"High Unplanned",IF(K5<0.9,"Low Attendance","Normal")) -> Low Attendance
A6: EMP1005 | B6: =INDEX(M_Name,MATCH($A6,M_ID,0)) -> Gaurav Fernandes | C6: =INDEX(M_Dept,MATCH($A6,M_ID,0)) -> Engineering | D6: =INDEX(M_Status,MATCH($A6,M_ID,0)) -> Active | E6: 250 | F6: 10 | G6: 4 | H6: 1 | I6: =SUM(F6:H6) -> 15 | J6: =E6-I6 -> 235 | K6: =IFERROR(J6/E6,0) -> 0.94 | L6: 90 | M6: 9 | N6: 50 | O6: =IF(H6>=8,"High Unplanned",IF(K6<0.9,"Low Attendance","Normal")) -> Normal
A7: EMP1006 | B7: =INDEX(M_Name,MATCH($A7,M_ID,0)) -> Yash Shah | C7: =INDEX(M_Dept,MATCH($A7,M_ID,0)) -> Operations | D7: =INDEX(M_Status,MATCH($A7,M_ID,0)) -> Exited | E7: 211 | F7: 9 | G7: 4 | H7: 8 | I7: =SUM(F7:H7) -> 21 | J7: =E7-I7 -> 190 | K7: =IFERROR(J7/E7,0) -> 0.90047393 | L7: 20 | M7: 8 | N7: 105 | O7: =IF(H7>=8,"High Unplanned",IF(K7<0.9,"Low Attendance","Normal")) -> High Unplanned
A8: EMP1007 | B8: =INDEX(M_Name,MATCH($A8,M_ID,0)) -> Imran Tiwari | C8: =INDEX(M_Dept,MATCH($A8,M_ID,0)) -> Marketing | D8: =INDEX(M_Status,MATCH($A8,M_ID,0)) -> Exited | E8: 116 | F8: 11 | G8: 0 | H8: 14 | I8: =SUM(F8:H8) -> 25 | J8: =E8-I8 -> 91 | K8: =IFERROR(J8/E8,0) -> 0.78448276 | L8: 72 | M8: 0 | N8: 22 | O8: =IF(H8>=8,"High Unplanned",IF(K8<0.9,"Low Attendance","Normal")) -> High Unplanned
A9: EMP1008 | B9: =INDEX(M_Name,MATCH($A9,M_ID,0)) -> Aishwarya Khan | C9: =INDEX(M_Dept,MATCH($A9,M_ID,0)) -> Engineering | D9: =INDEX(M_Status,MATCH($A9,M_ID,0)) -> Active | E9: 250 | F9: 6 | G9: 7 | H9: 1 | I9: =SUM(F9:H9) -> 14 | J9: =E9-I9 -> 236 | K9: =IFERROR(J9/E9,0) -> 0.944 | L9: 55 | M9: 1 | N9: 0 | O9: =IF(H9>=8,"High Unplanned",IF(K9<0.9,"Low Attendance","Normal")) -> Normal
A10: EMP1009 | B10: =INDEX(M_Name,MATCH($A10,M_ID,0)) -> Ankit Khanna | C10: =INDEX(M_Dept,MATCH($A10,M_ID,0)) -> Operations | D10: =INDEX(M_Status,MATCH($A10,M_ID,0)) -> Active | E10: 250 | F10: 11 | G10: 2 | H10: 1 | I10: =SUM(F10:H10) -> 14 | J10: =E10-I10 -> 236 | K10: =IFERROR(J10/E10,0) -> 0.944 | L10: 0 | M10: 1 | N10: 55 | O10: =IF(H10>=8,"High Unplanned",IF(K10<0.9,"Low Attendance","Normal")) -> Normal
A11: EMP1010 | B11: =INDEX(M_Name,MATCH($A11,M_ID,0)) -> Pooja Das | C11: =INDEX(M_Dept,MATCH($A11,M_ID,0)) -> Finance | D11: =INDEX(M_Status,MATCH($A11,M_ID,0)) -> Active | E11: 250 | F11: 13 | G11: 3 | H11: 6 | I11: =SUM(F11:H11) -> 22 | J11: =E11-I11 -> 228 | K11: =IFERROR(J11/E11,0) -> 0.912 | L11: 29 | M11: 6 | N11: 7 | O11: =IF(H11>=8,"High Unplanned",IF(K11<0.9,"Low Attendance","Normal")) -> Normal
A12: EMP1011 | B12: =INDEX(M_Name,MATCH($A12,M_ID,0)) -> Trisha Patel | C12: =INDEX(M_Dept,MATCH($A12,M_ID,0)) -> Product | D12: =INDEX(M_Status,MATCH($A12,M_ID,0)) -> Active | E12: 250 | F12: 20 | G12: 7 | H12: 0 | I12: =SUM(F12:H12) -> 27 | J12: =E12-I12 -> 223 | K12: =IFERROR(J12/E12,0) -> 0.892 | L12: 42 | M12: 3 | N12: 30 | O12: =IF(H12>=8,"High Unplanned",IF(K12<0.9,"Low Attendance","Normal")) -> Low Attendance
A13: EMP1012 | B13: =INDEX(M_Name,MATCH($A13,M_ID,0)) -> Krishna Kumar | C13: =INDEX(M_Dept,MATCH($A13,M_ID,0)) -> Operations | D13: =INDEX(M_Status,MATCH($A13,M_ID,0)) -> Active | E13: 250 | F13: 12 | G13: 5 | H13: 1 | I13: =SUM(F13:H13) -> 18 | J13: =E13-I13 -> 232 | K13: =IFERROR(J13/E13,0) -> 0.928 | L13: 13 | M13: 14 | N13: 23 | O13: =IF(H13>=8,"High Unplanned",IF(K13<0.9,"Low Attendance","Normal")) -> Normal
... A501: EMP1500 | B501: =INDEX(M_Name,MATCH($A501,M_ID,0)) -> Sowmya Patel | C501: =INDEX(M_Dept,MATCH($A501,M_ID,0)) -> Legal & Compliance | D501: =INDEX(M_Status,MATCH($A501,M_ID,0)) -> Active | E501: 20 | F501: 2 | G501: 3 | H501: 9 | I501: =SUM(F501:H501) -> 14 | J501: =E501-I501 -> 6 | K501: =IFERROR(J501/E501,0) -> 0.3 | L501: 68 | M501: 5 | N501: 6 | O501: =IF(H501>=8,"High Unplanned",IF(K501<0.9,"Low Attendance","Normal")) -> High Unplanned

Sheet Training
A1: Emp ID | B1: Employee Name | C1: Department | D1: Level | E1: Status | F1: Key Program Attended | G1: Courses Completed | H1: Training Hours | I1: Training Cost (₹) | J1: Assessment Score | K1: POSH Training Done | L1: InfoSec Training Done | M1: Compliance Status | N1: Certification Earned
A2: EMP1001 | B2: =INDEX(M_Name,MATCH($A2,M_ID,0)) -> Vidya Kulkarni | C2: =INDEX(M_Dept,MATCH($A2,M_ID,0)) -> Human Resources | D2: =INDEX(M_Level,MATCH($A2,M_ID,0)) -> L7 | E2: =INDEX(M_Status,MATCH($A2,M_ID,0)) -> Active | F2: Customer Centricity | G2: 1 | H2: 7 | I2: 7000 | J2: 80 | K2: Yes | L2: Yes | M2: =IF(AND(K2="Yes",L2="Yes"),"Compliant","Pending") -> Compliant | N2: No
A3: EMP1002 | B3: =INDEX(M_Name,MATCH($A3,M_ID,0)) -> Vikas Singh | C3: =INDEX(M_Dept,MATCH($A3,M_ID,0)) -> Engineering | D3: =INDEX(M_Level,MATCH($A3,M_ID,0)) -> L5 | E3: =INDEX(M_Status,MATCH($A3,M_ID,0)) -> Active | F3: Agile Ways of Working | G3: 1 | H3: 4 | I3: 3200 | J3: 81 | K3: Yes | L3: No | M3: =IF(AND(K3="Yes",L3="Yes"),"Compliant","Pending") -> Pending | N3: No
A4: EMP1003 | B4: =INDEX(M_Name,MATCH($A4,M_ID,0)) -> Prakash Das | C4: =INDEX(M_Dept,MATCH($A4,M_ID,0)) -> Human Resources | D4: =INDEX(M_Level,MATCH($A4,M_ID,0)) -> L6 | E4: =INDEX(M_Status,MATCH($A4,M_ID,0)) -> Active | F4: Agile Ways of Working | G4: 7 | H4: 35 | I4: 21000 | J4: 69 | K4: Yes | L4: Yes | M4: =IF(AND(K4="Yes",L4="Yes"),"Compliant","Pending") -> Compliant | N4: No
A5: EMP1004 | B5: =INDEX(M_Name,MATCH($A5,M_ID,0)) -> Fatima Choudhary | C5: =INDEX(M_Dept,MATCH($A5,M_ID,0)) -> Engineering | D5: =INDEX(M_Level,MATCH($A5,M_ID,0)) -> L5 | E5: =INDEX(M_Status,MATCH($A5,M_ID,0)) -> Active | F5: Negotiation Skills | G5: 5 | H5: 35 | I5: 15750 | J5: 79 | K5: Yes | L5: Yes | M5: =IF(AND(K5="Yes",L5="Yes"),"Compliant","Pending") -> Compliant | N5: No
A6: EMP1005 | B6: =INDEX(M_Name,MATCH($A6,M_ID,0)) -> Gaurav Fernandes | C6: =INDEX(M_Dept,MATCH($A6,M_ID,0)) -> Engineering | D6: =INDEX(M_Level,MATCH($A6,M_ID,0)) -> L5 | E6: =INDEX(M_Status,MATCH($A6,M_ID,0)) -> Active | F6: Customer Centricity | G6: 5 | H6: 40 | I6: 40000 | J6: 63 | K6: Yes | L6: Yes | M6: =IF(AND(K6="Yes",L6="Yes"),"Compliant","Pending") -> Compliant | N6: Yes
A7: EMP1006 | B7: =INDEX(M_Name,MATCH($A7,M_ID,0)) -> Yash Shah | C7: =INDEX(M_Dept,MATCH($A7,M_ID,0)) -> Operations | D7: =INDEX(M_Level,MATCH($A7,M_ID,0)) -> L5 | E7: =INDEX(M_Status,MATCH($A7,M_ID,0)) -> Exited | F7: Leadership Essentials | G7: 3 | H7: 12 | I7: 7200 | J7: 66 | K7: Yes | L7: Yes | M7: =IF(AND(K7="Yes",L7="Yes"),"Compliant","Pending") -> Compliant | N7: Yes
A8: EMP1007 | B8: =INDEX(M_Name,MATCH($A8,M_ID,0)) -> Imran Tiwari | C8: =INDEX(M_Dept,MATCH($A8,M_ID,0)) -> Marketing | D8: =INDEX(M_Level,MATCH($A8,M_ID,0)) -> L4 | E8: =INDEX(M_Status,MATCH($A8,M_ID,0)) -> Exited | F8: Data Literacy | G8: 9 | H8: 54 | I8: 54000 | J8: 73 | K8: Yes | L8: Yes | M8: =IF(AND(K8="Yes",L8="Yes"),"Compliant","Pending") -> Compliant | N8: No
A9: EMP1008 | B9: =INDEX(M_Name,MATCH($A9,M_ID,0)) -> Aishwarya Khan | C9: =INDEX(M_Dept,MATCH($A9,M_ID,0)) -> Engineering | D9: =INDEX(M_Level,MATCH($A9,M_ID,0)) -> L7 | E9: =INDEX(M_Status,MATCH($A9,M_ID,0)) -> Active | F9: Managerial Excellence | G9: 9 | H9: 54 | I9: 54000 | J9: 78 | K9: Yes | L9: Yes | M9: =IF(AND(K9="Yes",L9="Yes"),"Compliant","Pending") -> Compliant | N9: No
A10: EMP1009 | B10: =INDEX(M_Name,MATCH($A10,M_ID,0)) -> Ankit Khanna | C10: =INDEX(M_Dept,MATCH($A10,M_ID,0)) -> Operations | D10: =INDEX(M_Level,MATCH($A10,M_ID,0)) -> L5 | E10: =INDEX(M_Status,MATCH($A10,M_ID,0)) -> Active | F10: Advanced Excel | G10: 9 | H10: 27 | I10: 16200 | J10: 85 | K10: No | L10: No | M10: =IF(AND(K10="Yes",L10="Yes"),"Compliant","Pending") -> Pending | N10: No
A11: EMP1010 | B11: =INDEX(M_Name,MATCH($A11,M_ID,0)) -> Pooja Das | C11: =INDEX(M_Dept,MATCH($A11,M_ID,0)) -> Finance | D11: =INDEX(M_Level,MATCH($A11,M_ID,0)) -> L7 | E11: =INDEX(M_Status,MATCH($A11,M_ID,0)) -> Active | F11: Negotiation Skills | G11: 9 | H11: 54 | I11: 54000 | J11: 80 | K11: Yes | L11: Yes | M11: =IF(AND(K11="Yes",L11="Yes"),"Compliant","Pending") -> Compliant | N11: Yes
A12: EMP1011 | B12: =INDEX(M_Name,MATCH($A12,M_ID,0)) -> Trisha Patel | C12: =INDEX(M_Dept,MATCH($A12,M_ID,0)) -> Product | D12: =INDEX(M_Level,MATCH($A12,M_ID,0)) -> L6 | E12: =INDEX(M_Status,MATCH($A12,M_ID,0)) -> Active | F12: Negotiation Skills | G12: 3 | H12: 9 | I12: 7200 | J12: 71 | K12: Yes | L12: Yes | M12: =IF(AND(K12="Yes",L12="Yes"),"Compliant","Pending") -> Compliant | N12: Yes
A13: EMP1012 | B13: =INDEX(M_Name,MATCH($A13,M_ID,0)) -> Krishna Kumar | C13: =INDEX(M_Dept,MATCH($A13,M_ID,0)) -> Operations | D13: =INDEX(M_Level,MATCH($A13,M_ID,0)) -> L4 | E13: =INDEX(M_Status,MATCH($A13,M_ID,0)) -> Active | F13: Customer Centricity | G13: 9 | H13: 36 | I13: 36000 | J13: 86 | K13: Yes | L13: No | M13: =IF(AND(K13="Yes",L13="Yes"),"Compliant","Pending") -> Pending | N13: No
... A501: EMP1500 | B501: =INDEX(M_Name,MATCH($A501,M_ID,0)) -> Sowmya Patel | C501: =INDEX(M_Dept,MATCH($A501,M_ID,0)) -> Legal & Compliance | D501: =INDEX(M_Level,MATCH($A501,M_ID,0)) -> L2 | E501: =INDEX(M_Status,MATCH($A501,M_ID,0)) -> Active | F501: Managerial Excellence | G501: 2 | H501: 8 | I501: 3600 | J501: 63 | K501: Yes | L501: Yes | M501: =IF(AND(K501="Yes",L501="Yes"),"Compliant","Pending") -> Compliant | N501: No

Sheet Engagement
A1: Emp ID | B1: Employee Name | C1: Department | D1: Manager | E1: Status | F1: Survey Participated | G1: Manager Support | H1: Career Growth | I1: Work-Life Balance | J1: Recognition | K1: Culture & Belonging | L1: Pay Fairness | M1: Overall Engagement (1-5) | N1: eNPS Score (0-10) | O1: eNPS Category | P1: Rating | Q1: Compa-Ratio | R1: Risk Points | S1: Flight Risk
A2: EMP1001 | B2: =INDEX(M_Name,MATCH($A2,M_ID,0)) -> Vidya Kulkarni | C2: =INDEX(M_Dept,MATCH($A2,M_ID,0)) -> Human Resources | D2: =INDEX(M_Mgr,MATCH($A2,M_ID,0)) -> Arvind Rao (CEO) | E2: =INDEX(M_Status,MATCH($A2,M_ID,0)) -> Active | F2: Yes | G2: 3.5 | H2: 3.4 | I2: 3.7 | J2: 3.8 | K2: 4.3 | L2: 3.7 | M2: =ROUND(AVERAGE(G2:L2),2) -> 3.73 | N2: 10 | O2: =IF(N2>=9,"Promoter",IF(N2>=7,"Passive","Detractor")) -> Promoter | P2: =INDEX(P_Rating,MATCH($A2,M_ID,0)) -> 5 | Q2: =INDEX(C_Compa,MATCH($A2,M_ID,0)) -> 0.93 | R2: =(M2<EngThreshold)+(N2<=6)+(Q2<CompaThreshold)+(P2>=4) -> 1 | S2: =IF(E2="Exited","Exited",IF(R2>=3,"High",IF(R2=2,"Medium","Low"))) -> Low
A3: EMP1002 | B3: =INDEX(M_Name,MATCH($A3,M_ID,0)) -> Vikas Singh | C3: =INDEX(M_Dept,MATCH($A3,M_ID,0)) -> Engineering | D3: =INDEX(M_Mgr,MATCH($A3,M_ID,0)) -> Yamini Nair | E3: =INDEX(M_Status,MATCH($A3,M_ID,0)) -> Active | F3: Yes | G3: 4.6 | H3: 4 | I3: 4.7 | J3: 4.4 | K3: 4.5 | L3: 5 | M3: =ROUND(AVERAGE(G3:L3),2) -> 4.53 | N3: 10 | O3: =IF(N3>=9,"Promoter",IF(N3>=7,"Passive","Detractor")) -> Promoter | P3: =INDEX(P_Rating,MATCH($A3,M_ID,0)) -> 4 | Q3: =INDEX(C_Compa,MATCH($A3,M_ID,0)) -> 1.2 | R3: =(M3<EngThreshold)+(N3<=6)+(Q3<CompaThreshold)+(P3>=4) -> 1 | S3: =IF(E3="Exited","Exited",IF(R3>=3,"High",IF(R3=2,"Medium","Low"))) -> Low
A4: EMP1003 | B4: =INDEX(M_Name,MATCH($A4,M_ID,0)) -> Prakash Das | C4: =INDEX(M_Dept,MATCH($A4,M_ID,0)) -> Human Resources | D4: =INDEX(M_Mgr,MATCH($A4,M_ID,0)) -> Vidya Kulkarni | E4: =INDEX(M_Status,MATCH($A4,M_ID,0)) -> Active | F4: Yes | G4: 3.6 | H4: 3 | I4: 3.4 | J4: 3.1 | K4: 3.3 | L4: 3 | M4: =ROUND(AVERAGE(G4:L4),2) -> 3.23 | N4: 7 | O4: =IF(N4>=9,"Promoter",IF(N4>=7,"Passive","Detractor")) -> Passive | P4: =INDEX(P_Rating,MATCH($A4,M_ID,0)) -> 2 | Q4: =INDEX(C_Compa,MATCH($A4,M_ID,0)) -> 0.95 | R4: =(M4<EngThreshold)+(N4<=6)+(Q4<CompaThreshold)+(P4>=4) -> 0 | S4: =IF(E4="Exited","Exited",IF(R4>=3,"High",IF(R4=2,"Medium","Low"))) -> Low
A5: EMP1004 | B5: =INDEX(M_Name,MATCH($A5,M_ID,0)) -> Fatima Choudhary | C5: =INDEX(M_Dept,MATCH($A5,M_ID,0)) -> Engineering | D5: =INDEX(M_Mgr,MATCH($A5,M_ID,0)) -> Yamini Nair | E5: =INDEX(M_Status,MATCH($A5,M_ID,0)) -> Active | F5: Yes | G5: 3.3 | H5: 2.9 | I5: 2.8 | J5: 3.5 | K5: 2.8 | L5: 3.4 | M5: =ROUND(AVERAGE(G5:L5),2) -> 3.12 | N5: 8 | O5: =IF(N5>=9,"Promoter",IF(N5>=7,"Passive","Detractor")) -> Passive | P5: =INDEX(P_Rating,MATCH($A5,M_ID,0)) -> 2 | Q5: =INDEX(C_Compa,MATCH($A5,M_ID,0)) -> 1.22 | R5: =(M5<EngThreshold)+(N5<=6)+(Q5<CompaThreshold)+(P5>=4) -> 0 | S5: =IF(E5="Exited","Exited",IF(R5>=3,"High",IF(R5=2,"Medium","Low"))) -> Low
A6: EMP1005 | B6: =INDEX(M_Name,MATCH($A6,M_ID,0)) -> Gaurav Fernandes | C6: =INDEX(M_Dept,MATCH($A6,M_ID,0)) -> Engineering | D6: =INDEX(M_Mgr,MATCH($A6,M_ID,0)) -> Yamini Nair | E6: =INDEX(M_Status,MATCH($A6,M_ID,0)) -> Active | F6: Yes | G6: 4.5 | H6: 4 | I6: 3.4 | J6: 3.8 | K6: 3.7 | L6: 3.5 | M6: =ROUND(AVERAGE(G6:L6),2) -> 3.82 | N6: 9 | O6: =IF(N6>=9,"Promoter",IF(N6>=7,"Passive","Detractor")) -> Promoter | P6: =INDEX(P_Rating,MATCH($A6,M_ID,0)) -> 3 | Q6: =INDEX(C_Compa,MATCH($A6,M_ID,0)) -> 1.35 | R6: =(M6<EngThreshold)+(N6<=6)+(Q6<CompaThreshold)+(P6>=4) -> 0 | S6: =IF(E6="Exited","Exited",IF(R6>=3,"High",IF(R6=2,"Medium","Low"))) -> Low
A7: EMP1006 | B7: =INDEX(M_Name,MATCH($A7,M_ID,0)) -> Yash Shah | C7: =INDEX(M_Dept,MATCH($A7,M_ID,0)) -> Operations | D7: =INDEX(M_Mgr,MATCH($A7,M_ID,0)) -> Pallavi Shah | E7: =INDEX(M_Status,MATCH($A7,M_ID,0)) -> Exited | F7: Yes | G7: 2.7 | H7: 2.8 | I7: 2.9 | J7: 3 | K7: 3.4 | L7: 3 | M7: =ROUND(AVERAGE(G7:L7),2) -> 2.97 | N7: 9 | O7: =IF(N7>=9,"Promoter",IF(N7>=7,"Passive","Detractor")) -> Promoter | P7: =INDEX(P_Rating,MATCH($A7,M_ID,0)) -> 4 | Q7: =INDEX(C_Compa,MATCH($A7,M_ID,0)) -> 0.74 | R7: =(M7<EngThreshold)+(N7<=6)+(Q7<CompaThreshold)+(P7>=4) -> 3 | S7: =IF(E7="Exited","Exited",IF(R7>=3,"High",IF(R7=2,"Medium","Low"))) -> Exited
A8: EMP1007 | B8: =INDEX(M_Name,MATCH($A8,M_ID,0)) -> Imran Tiwari | C8: =INDEX(M_Dept,MATCH($A8,M_ID,0)) -> Marketing | D8: =INDEX(M_Mgr,MATCH($A8,M_ID,0)) -> Nandini Iyer | E8: =INDEX(M_Status,MATCH($A8,M_ID,0)) -> Exited | F8: Yes | G8: 2.5 | H8: 2.4 | I8: 2.1 | J8: 2.2 | K8: 2.9 | L8: 2.5 | M8: =ROUND(AVERAGE(G8:L8),2) -> 2.43 | N8: 7 | O8: =IF(N8>=9,"Promoter",IF(N8>=7,"Passive","Detractor")) -> Passive | P8: =INDEX(P_Rating,MATCH($A8,M_ID,0)) -> 1 | Q8: =INDEX(C_Compa,MATCH($A8,M_ID,0)) -> 0.95 | R8: =(M8<EngThreshold)+(N8<=6)+(Q8<CompaThreshold)+(P8>=4) -> 1 | S8: =IF(E8="Exited","Exited",IF(R8>=3,"High",IF(R8=2,"Medium","Low"))) -> Exited
A9: EMP1008 | B9: =INDEX(M_Name,MATCH($A9,M_ID,0)) -> Aishwarya Khan | C9: =INDEX(M_Dept,MATCH($A9,M_ID,0)) -> Engineering | D9: =INDEX(M_Mgr,MATCH($A9,M_ID,0)) -> Arvind Rao (CEO) | E9: =INDEX(M_Status,MATCH($A9,M_ID,0)) -> Active | F9: Yes | G9: 2 | H9: 1.8 | I9: 2.1 | J9: 2 | K9: 2.1 | L9: 2.2 | M9: =ROUND(AVERAGE(G9:L9),2) -> 2.03 | N9: 7 | O9: =IF(N9>=9,"Promoter",IF(N9>=7,"Passive","Detractor")) -> Passive | P9: =INDEX(P_Rating,MATCH($A9,M_ID,0)) -> 3 | Q9: =INDEX(C_Compa,MATCH($A9,M_ID,0)) -> 1.12 | R9: =(M9<EngThreshold)+(N9<=6)+(Q9<CompaThreshold)+(P9>=4) -> 1 | S9: =IF(E9="Exited","Exited",IF(R9>=3,"High",IF(R9=2,"Medium","Low"))) -> Low
A10: EMP1009 | B10: =INDEX(M_Name,MATCH($A10,M_ID,0)) -> Ankit Khanna | C10: =INDEX(M_Dept,MATCH($A10,M_ID,0)) -> Operations | D10: =INDEX(M_Mgr,MATCH($A10,M_ID,0)) -> Imran Mishra | E10: =INDEX(M_Status,MATCH($A10,M_ID,0)) -> Active | F10: Yes | G10: 2.9 | H10: 4.3 | I10: 3.4 | J10: 3.1 | K10: 2.5 | L10: 3 | M10: =ROUND(AVERAGE(G10:L10),2) -> 3.2 | N10: 7 | O10: =IF(N10>=9,"Promoter",IF(N10>=7,"Passive","Detractor")) -> Passive | P10: =INDEX(P_Rating,MATCH($A10,M_ID,0)) -> 3 | Q10: =INDEX(C_Compa,MATCH($A10,M_ID,0)) -> 0.98 | R10: =(M10<EngThreshold)+(N10<=6)+(Q10<CompaThreshold)+(P10>=4) -> 0 | S10: =IF(E10="Exited","Exited",IF(R10>=3,"High",IF(R10=2,"Medium","Low"))) -> Low
A11: EMP1010 | B11: =INDEX(M_Name,MATCH($A11,M_ID,0)) -> Pooja Das | C11: =INDEX(M_Dept,MATCH($A11,M_ID,0)) -> Finance | D11: =INDEX(M_Mgr,MATCH($A11,M_ID,0)) -> Arvind Rao (CEO) | E11: =INDEX(M_Status,MATCH($A11,M_ID,0)) -> Active | F11: Yes | G11: 3.4 | H11: 3.2 | I11: 3.1 | J11: 3.5 | K11: 3.5 | L11: 3.7 | M11: =ROUND(AVERAGE(G11:L11),2) -> 3.4 | N11: 9 | O11: =IF(N11>=9,"Promoter",IF(N11>=7,"Passive","Detractor")) -> Promoter | P11: =INDEX(P_Rating,MATCH($A11,M_ID,0)) -> 2 | Q11: =INDEX(C_Compa,MATCH($A11,M_ID,0)) -> 0.99 | R11: =(M11<EngThreshold)+(N11<=6)+(Q11<CompaThreshold)+(P11>=4) -> 0 | S11: =IF(E11="Exited","Exited",IF(R11>=3,"High",IF(R11=2,"Medium","Low"))) -> Low
A12: EMP1011 | B12: =INDEX(M_Name,MATCH($A12,M_ID,0)) -> Trisha Patel | C12: =INDEX(M_Dept,MATCH($A12,M_ID,0)) -> Product | D12: =INDEX(M_Mgr,MATCH($A12,M_ID,0)) -> Dev Bose | E12: =INDEX(M_Status,MATCH($A12,M_ID,0)) -> Active | F12: Yes | G12: 2.5 | H12: 3.3 | I12: 2.8 | J12: 2.6 | K12: 3.3 | L12: 2.9 | M12: =ROUND(AVERAGE(G12:L12),2) -> 2.9 | N12: 6 | O12: =IF(N12>=9,"Promoter",IF(N12>=7,"Passive","Detractor")) -> Detractor | P12: =INDEX(P_Rating,MATCH($A12,M_ID,0)) -> 3 | Q12: =INDEX(C_Compa,MATCH($A12,M_ID,0)) -> 1.05 | R12: =(M12<EngThreshold)+(N12<=6)+(Q12<CompaThreshold)+(P12>=4) -> 2 | S12: =IF(E12="Exited","Exited",IF(R12>=3,"High",IF(R12=2,"Medium","Low"))) -> Medium
A13: EMP1012 | B13: =INDEX(M_Name,MATCH($A13,M_ID,0)) -> Krishna Kumar | C13: =INDEX(M_Dept,MATCH($A13,M_ID,0)) -> Operations | D13: =INDEX(M_Mgr,MATCH($A13,M_ID,0)) -> Amit Kumar | E13: =INDEX(M_Status,MATCH($A13,M_ID,0)) -> Active | F13: Yes | G13: 2.8 | H13: 2.6 | I13: 3.6 | J13: 3.3 | K13: 2.6 | L13: 2.1 | M13: =ROUND(AVERAGE(G13:L13),2) -> 2.83 | N13: 8 | O13: =IF(N13>=9,"Promoter",IF(N13>=7,"Passive","Detractor")) -> Passive | P13: =INDEX(P_Rating,MATCH($A13,M_ID,0)) -> 3 | Q13: =INDEX(C_Compa,MATCH($A13,M_ID,0)) -> 0.73 | R13: =(M13<EngThreshold)+(N13<=6)+(Q13<CompaThreshold)+(P13>=4) -> 2 | S13: =IF(E13="Exited","Exited",IF(R13>=3,"High",IF(R13=2,"Medium","Low"))) -> Medium
... A501: EMP1500 | B501: =INDEX(M_Name,MATCH($A501,M_ID,0)) -> Sowmya Patel | C501: =INDEX(M_Dept,MATCH($A501,M_ID,0)) -> Legal & Compliance | D501: =INDEX(M_Mgr,MATCH($A501,M_ID,0)) -> Ramya Khanna | E501: =INDEX(M_Status,MATCH($A501,M_ID,0)) -> Active | F501: Yes | G501: 3 | H501: 2.6 | I501: 3 | J501: 2.3 | K501: 3 | L501: 2.7 | M501: =ROUND(AVERAGE(G501:L501),2) -> 2.77 | N501: 6 | O501: =IF(N501>=9,"Promoter",IF(N501>=7,"Passive","Detractor")) -> Detractor | P501: =INDEX(P_Rating,MATCH($A501,M_ID,0)) -> 2 | Q501: =INDEX(C_Compa,MATCH($A501,M_ID,0)) -> 1.08 | R501: =(M501<EngThreshold)+(N501<=6)+(Q501<CompaThreshold)+(P501>=4) -> 2 | S501: =IF(E501="Exited","Exited",IF(R501>=3,"High",IF(R501=2,"Medium","Low"))) -> Medium

Sheet Exits_Attrition
A1: Emp ID | B1: Employee Name | C1: Department | D1: Designation | E1: Level | F1: Manager | G1: Date of Joining | H1: Exit Date | I1: Tenure at Exit (Yrs) | J1: Exit Type | K1: Primary Reason | L1: Regrettable Loss | M1: Notice Served (Days) | N1: Eligible for Rehire | O1: Exit Interview | P1: Exit Month | Q1: Last Rating
A2: EMP1160 | B2: =INDEX(M_Name,MATCH($A2,M_ID,0)) -> Bhavana Varghese | C2: =INDEX(M_Dept,MATCH($A2,M_ID,0)) -> Customer Support | D2: =INDEX(M_Title,MATCH($A2,M_ID,0)) -> Support Team Lead | E2: =INDEX(M_Level,MATCH($A2,M_ID,0)) -> L4 | F2: =INDEX(M_Mgr,MATCH($A2,M_ID,0)) -> Isha Verma | G2: =INDEX(M_DOJ,MATCH($A2,M_ID,0)) -> 45049 | H2: 45949 | I2: =ROUND((H2-G2)/365.25,1) -> 2.5 | J2: Voluntary | K2: Relocation | L2: No | M2: 90 | N2: Yes | O2: Completed | P2: =TEXT(H2,"mmm-yy") -> Oct-25 | Q2: =INDEX(P_Rating,MATCH($A2,M_ID,0)) -> 3
A3: EMP1365 | B3: =INDEX(M_Name,MATCH($A3,M_ID,0)) -> Rashmi Mishra | C3: =INDEX(M_Dept,MATCH($A3,M_ID,0)) -> Engineering | D3: =INDEX(M_Title,MATCH($A3,M_ID,0)) -> Associate Software Engineer | E3: =INDEX(M_Level,MATCH($A3,M_ID,0)) -> L1 | F3: =INDEX(M_Mgr,MATCH($A3,M_ID,0)) -> Fatima Choudhary | G3: =INDEX(M_DOJ,MATCH($A3,M_ID,0)) -> 45859 | H3: 45952 | I3: =ROUND((H3-G3)/365.25,1) -> 0.3 | J3: Voluntary | K3: Better Compensation | L3: Yes | M3: 45 | N3: Yes | O3: Completed | P3: =TEXT(H3,"mmm-yy") -> Oct-25 | Q3: =INDEX(P_Rating,MATCH($A3,M_ID,0)) -> 4
A4: EMP1341 | B4: =INDEX(M_Name,MATCH($A4,M_ID,0)) -> Gayatri Naidu | C4: =INDEX(M_Dept,MATCH($A4,M_ID,0)) -> Customer Support | D4: =INDEX(M_Title,MATCH($A4,M_ID,0)) -> Support Team Lead | E4: =INDEX(M_Level,MATCH($A4,M_ID,0)) -> L4 | F4: =INDEX(M_Mgr,MATCH($A4,M_ID,0)) -> Ashish Varghese | G4: =INDEX(M_DOJ,MATCH($A4,M_ID,0)) -> 45763 | H4: 45953 | I4: =ROUND((H4-G4)/365.25,1) -> 0.5 | J4: Voluntary | K4: Career Growth | L4: No | M4: 90 | N4: Yes | O4: Completed | P4: =TEXT(H4,"mmm-yy") -> Oct-25 | Q4: =INDEX(P_Rating,MATCH($A4,M_ID,0)) -> 4
A5: EMP1283 | B5: =INDEX(M_Name,MATCH($A5,M_ID,0)) -> Isha Khanna | C5: =INDEX(M_Dept,MATCH($A5,M_ID,0)) -> Product | D5: =INDEX(M_Title,MATCH($A5,M_ID,0)) -> Product Analyst | E5: =INDEX(M_Level,MATCH($A5,M_ID,0)) -> L2 | F5: =INDEX(M_Mgr,MATCH($A5,M_ID,0)) -> Sachin Shetty | G5: =INDEX(M_DOJ,MATCH($A5,M_ID,0)) -> 45554 | H5: 45954 | I5: =ROUND((H5-G5)/365.25,1) -> 1.1 | J5: Involuntary | K5: Role Redundancy | L5: No | M5: 0 | N5: No | O5: Completed | P5: =TEXT(H5,"mmm-yy") -> Oct-25 | Q5: =INDEX(P_Rating,MATCH($A5,M_ID,0)) -> 3
A6: EMP1284 | B6: =INDEX(M_Name,MATCH($A6,M_ID,0)) -> Kunal Fernandes | C6: =INDEX(M_Dept,MATCH($A6,M_ID,0)) -> Customer Support | D6: =INDEX(M_Title,MATCH($A6,M_ID,0)) -> Support Team Lead | E6: =INDEX(M_Level,MATCH($A6,M_ID,0)) -> L4 | F6: =INDEX(M_Mgr,MATCH($A6,M_ID,0)) -> Imran Joshi | G6: =INDEX(M_DOJ,MATCH($A6,M_ID,0)) -> 45567 | H6: 45977 | I6: =ROUND((H6-G6)/365.25,1) -> 1.1 | J6: Voluntary | K6: Relocation | L6: No | M6: 45 | N6: Yes | O6: Completed | P6: =TEXT(H6,"mmm-yy") -> Nov-25 | Q6: =INDEX(P_Rating,MATCH($A6,M_ID,0)) -> 3
A7: EMP1245 | B7: =INDEX(M_Name,MATCH($A7,M_ID,0)) -> Rajesh Raghavan | C7: =INDEX(M_Dept,MATCH($A7,M_ID,0)) -> Legal & Compliance | D7: =INDEX(M_Title,MATCH($A7,M_ID,0)) -> Legal Counsel | E7: =INDEX(M_Level,MATCH($A7,M_ID,0)) -> L3 | F7: =INDEX(M_Mgr,MATCH($A7,M_ID,0)) -> Ramya Khanna | G7: =INDEX(M_DOJ,MATCH($A7,M_ID,0)) -> 45423 | H7: 45985 | I7: =ROUND((H7-G7)/365.25,1) -> 1.5 | J7: Voluntary | K7: Manager Relationship | L7: No | M7: 60 | N7: Yes | O7: Completed | P7: =TEXT(H7,"mmm-yy") -> Nov-25 | Q7: =INDEX(P_Rating,MATCH($A7,M_ID,0)) -> 3
A8: EMP1295 | B8: =INDEX(M_Name,MATCH($A8,M_ID,0)) -> Sindhu Gowda | C8: =INDEX(M_Dept,MATCH($A8,M_ID,0)) -> Customer Support | D8: =INDEX(M_Title,MATCH($A8,M_ID,0)) -> Support Executive | E8: =INDEX(M_Level,MATCH($A8,M_ID,0)) -> L2 | F8: =INDEX(M_Mgr,MATCH($A8,M_ID,0)) -> Ashish Varghese | G8: =INDEX(M_DOJ,MATCH($A8,M_ID,0)) -> 45613 | H8: 45986 | I8: =ROUND((H8-G8)/365.25,1) -> 1 | J8: Involuntary | K8: Role Redundancy | L8: No | M8: 0 | N8: No | O8: Completed | P8: =TEXT(H8,"mmm-yy") -> Nov-25 | Q8: =INDEX(P_Rating,MATCH($A8,M_ID,0)) -> 3
A9: EMP1296 | B9: =INDEX(M_Name,MATCH($A9,M_ID,0)) -> Farhan Shetty | C9: =INDEX(M_Dept,MATCH($A9,M_ID,0)) -> Engineering | D9: =INDEX(M_Title,MATCH($A9,M_ID,0)) -> Software Engineer | E9: =INDEX(M_Level,MATCH($A9,M_ID,0)) -> L2 | F9: =INDEX(M_Mgr,MATCH($A9,M_ID,0)) -> Vikas Singh | G9: =INDEX(M_DOJ,MATCH($A9,M_ID,0)) -> 45614 | H9: 46002 | I9: =ROUND((H9-G9)/365.25,1) -> 1.1 | J9: Voluntary | K9: Better Compensation | L9: No | M9: 30 | N9: Yes | O9: Pending | P9: =TEXT(H9,"mmm-yy") -> Dec-25 | Q9: =INDEX(P_Rating,MATCH($A9,M_ID,0)) -> 3
A10: EMP1028 | B10: =INDEX(M_Name,MATCH($A10,M_ID,0)) -> Gayatri Krishnan | C10: =INDEX(M_Dept,MATCH($A10,M_ID,0)) -> Operations | D10: =INDEX(M_Title,MATCH($A10,M_ID,0)) -> Operations Lead | E10: =INDEX(M_Level,MATCH($A10,M_ID,0)) -> L4 | F10: =INDEX(M_Mgr,MATCH($A10,M_ID,0)) -> Ajay Kumar | G10: =INDEX(M_DOJ,MATCH($A10,M_ID,0)) -> 44137 | H10: 46002 | I10: =ROUND((H10-G10)/365.25,1) -> 5.1 | J10: Voluntary | K10: Better Compensation | L10: Yes | M10: 60 | N10: Yes | O10: Completed | P10: =TEXT(H10,"mmm-yy") -> Dec-25 | Q10: =INDEX(P_Rating,MATCH($A10,M_ID,0)) -> 3
A11: EMP1293 | B11: =INDEX(M_Name,MATCH($A11,M_ID,0)) -> Ajay Jain | C11: =INDEX(M_Dept,MATCH($A11,M_ID,0)) -> Customer Support | D11: =INDEX(M_Title,MATCH($A11,M_ID,0)) -> Support Executive | E11: =INDEX(M_Level,MATCH($A11,M_ID,0)) -> L2 | F11: =INDEX(M_Mgr,MATCH($A11,M_ID,0)) -> Anand Naidu | G11: =INDEX(M_DOJ,MATCH($A11,M_ID,0)) -> 45612 | H11: 46021 | I11: =ROUND((H11-G11)/365.25,1) -> 1.1 | J11: Voluntary | K11: Higher Studies | L11: Yes | M11: 30 | N11: Yes | O11: Completed | P11: =TEXT(H11,"mmm-yy") -> Dec-25 | Q11: =INDEX(P_Rating,MATCH($A11,M_ID,0)) -> 1
A12: EMP1052 | B12: =INDEX(M_Name,MATCH($A12,M_ID,0)) -> Siddharth Mehta | C12: =INDEX(M_Dept,MATCH($A12,M_ID,0)) -> Engineering | D12: =INDEX(M_Title,MATCH($A12,M_ID,0)) -> Senior Software Engineer | E12: =INDEX(M_Level,MATCH($A12,M_ID,0)) -> L3 | F12: =INDEX(M_Mgr,MATCH($A12,M_ID,0)) -> Vikas Singh | G12: =INDEX(M_DOJ,MATCH($A12,M_ID,0)) -> 44337 | H12: 46023 | I12: =ROUND((H12-G12)/365.25,1) -> 4.6 | J12: Voluntary | K12: Career Growth | L12: No | M12: 30 | N12: No | O12: Completed | P12: =TEXT(H12,"mmm-yy") -> Jan-26 | Q12: =INDEX(P_Rating,MATCH($A12,M_ID,0)) -> 3
A13: EMP1211 | B13: =INDEX(M_Name,MATCH($A13,M_ID,0)) -> Tarun Das | C13: =INDEX(M_Dept,MATCH($A13,M_ID,0)) -> Customer Support | D13: =INDEX(M_Title,MATCH($A13,M_ID,0)) -> Support Executive | E13: =INDEX(M_Level,MATCH($A13,M_ID,0)) -> L2 | F13: =INDEX(M_Mgr,MATCH($A13,M_ID,0)) -> Imran Joshi | G13: =INDEX(M_DOJ,MATCH($A13,M_ID,0)) -> 45295 | H13: 46030 | I13: =ROUND((H13-G13)/365.25,1) -> 2 | J13: Voluntary | K13: Career Growth | L13: No | M13: 60 | N13: Yes | O13: Completed | P13: =TEXT(H13,"mmm-yy") -> Jan-26 | Q13: =INDEX(P_Rating,MATCH($A13,M_ID,0)) -> 5
... A65: EMP1383 | B65: =INDEX(M_Name,MATCH($A65,M_ID,0)) -> Keerthi Kamath | C65: =INDEX(M_Dept,MATCH($A65,M_ID,0)) -> Sales | D65: =INDEX(M_Title,MATCH($A65,M_ID,0)) -> Sales Associate | E65: =INDEX(M_Level,MATCH($A65,M_ID,0)) -> L1 | F65: =INDEX(M_Mgr,MATCH($A65,M_ID,0)) -> Kavya Krishnan | G65: =INDEX(M_DOJ,MATCH($A65,M_ID,0)) -> 45941 | H65: 46292 | I65: =ROUND((H65-G65)/365.25,1) -> 1 | J65: Voluntary | K65: Better Compensation | L65: Yes | M65: 30 | N65: Yes | O65: Completed | P65: =TEXT(H65,"mmm-yy") -> Sep-26 | Q65: =INDEX(P_Rating,MATCH($A65,M_ID,0)) -> 3

Sheet Recruitment
A1: Req ID | B1: Department | C1: Position | D1: Level | E1: Priority | F1: Recruiter | G1: Open Date | H1: Close Date | I1: Status | J1: Hire Source | K1: Applicants | L1: Shortlisted | M1: Interviews | N1: Offers Made | O1: Offers Accepted | P1: Offer Acceptance % | Q1: Time to Fill / Days Open | R1: Cost per Hire (₹)
A2: REQ2054 | B2: Customer Support | C2: Senior Support Manager | D2: L6 | E2: Low | F2: Sonali K | G2: 45939 | H2: 45987 | I2: Filled | J2: LinkedIn | K2: 141 | L2: 23 | M2: 12 | N2: 1 | O2: 1 | P2: =IF(N2=0,"",O2/N2) -> 1 | Q2: =IF(I2="Filled",H2-G2,IF(I2="Open",AsOf-G2,"")) -> 48 | R2: 18000
A3: REQ2091 | B3: Operations | C3: Operations Executive | D3: L2 | E3: Medium | F3: Rakesh Nair | G3: 45939 | H3: 45992 | I3: Filled | J3: LinkedIn | K3: 111 | L3: 23 | M3: 14 | N3: 1 | O3: 1 | P3: =IF(N3=0,"",O3/N3) -> 1 | Q3: =IF(I3="Filled",H3-G3,IF(I3="Open",AsOf-G3,"")) -> 53 | R3: 18000
A4: REQ2120 | B4: Data & Analytics | C4: Analytics Manager | D4: L5 | E4: High | F4: Sonali K | G4: 45939 | H4: 45994 | I4: Filled | J4: Campus | K4: 70 | L4: 10 | M4: 6 | N4: 2 | O4: 1 | P4: =IF(N4=0,"",O4/N4) -> 0.5 | Q4: =IF(I4="Filled",H4-G4,IF(I4="Open",AsOf-G4,"")) -> 55 | R4: 15000
A5: REQ2045 | B5: Operations | C5: Operations Lead | D5: L4 | E5: High | F5: Sonali K | G5: 45941 | H5: 45980 | I5: Filled | J5: Employee Referral | K5: 217 | L5: 56 | M5: 33 | N5: 1 | O5: 1 | P5: =IF(N5=0,"",O5/N5) -> 1 | Q5: =IF(I5="Filled",H5-G5,IF(I5="Open",AsOf-G5,"")) -> 39 | R5: 25000
A6: REQ2088 | B6: Data & Analytics | C6: Data Analyst I | D6: L1 | E6: Medium | F6: Farhan Siddiqui | G6: 45941 | H6: 45969 | I6: Filled | J6: Careers Page | K6: 146 | L6: 38 | M6: 17 | N6: 2 | O6: 1 | P6: =IF(N6=0,"",O6/N6) -> 0.5 | Q6: =IF(I6="Filled",H6-G6,IF(I6="Open",AsOf-G6,"")) -> 28 | R6: 5000
A7: REQ2035 | B7: Operations | C7: Operations Executive | D7: L2 | E7: High | F7: Divya Menon | G7: 45942 | I7: Open | K7: 179 | L7: 21 | M7: 14 | N7: 1 | O7: 0 | P7: =IF(N7=0,"",O7/N7) -> 0 | Q7: =IF(I7="Filled",H7-G7,IF(I7="Open",AsOf-G7,"")) -> 353
A8: REQ2049 | B8: Engineering | C8: Senior Software Engineer | D8: L3 | E8: Medium | F8: Sonali K | G8: 45942 | H8: 45992 | I8: Filled | J8: LinkedIn | K8: 46 | L8: 6 | M8: 3 | N8: 3 | O8: 1 | P8: =IF(N8=0,"",O8/N8) -> 0.33333333 | Q8: =IF(I8="Filled",H8-G8,IF(I8="Open",AsOf-G8,"")) -> 50 | R8: 18000
A9: REQ2082 | B9: Operations | C9: Operations Lead | D9: L4 | E9: Medium | F9: Sonali K | G9: 45943 | I9: Cancelled | K9: 193 | L9: 47 | M9: 30 | N9: 0 | O9: 0 | P9: =IF(N9=0,"",O9/N9) | Q9: =IF(I9="Filled",H9-G9,IF(I9="Open",AsOf-G9,""))
A10: REQ2103 | B10: Engineering | C10: Associate Software Engineer | D10: L1 | E10: Low | F10: Farhan Siddiqui | G10: 45943 | I10: Open | K10: 152 | L10: 29 | M10: 18 | N10: 0 | O10: 0 | P10: =IF(N10=0,"",O10/N10) | Q10: =IF(I10="Filled",H10-G10,IF(I10="Open",AsOf-G10,"")) -> 352
A11: REQ2085 | B11: Legal & Compliance | C11: Compliance Executive | D11: L2 | E11: High | F11: Divya Menon | G11: 45944 | H11: 45983 | I11: Filled | J11: Employee Referral | K11: 48 | L11: 7 | M11: 4 | N11: 1 | O11: 1 | P11: =IF(N11=0,"",O11/N11) -> 1 | Q11: =IF(I11="Filled",H11-G11,IF(I11="Open",AsOf-G11,"")) -> 39 | R11: 25000
A12: REQ2036 | B12: Data & Analytics | C12: Lead Data Scientist | D12: L4 | E12: High | F12: Divya Menon | G12: 45946 | H12: 46003 | I12: Filled | J12: Employee Referral | K12: 59 | L12: 10 | M12: 6 | N12: 3 | O12: 1 | P12: =IF(N12=0,"",O12/N12) -> 0.33333333 | Q12: =IF(I12="Filled",H12-G12,IF(I12="Open",AsOf-G12,"")) -> 57 | R12: 25000
A13: REQ2060 | B13: Engineering | C13: Tech Lead | D13: L4 | E13: High | F13: Rakesh Nair | G13: 45946 | H13: 46008 | I13: Filled | J13: Campus | K13: 48 | L13: 9 | M13: 5 | N13: 1 | O13: 1 | P13: =IF(N13=0,"",O13/N13) -> 1 | Q13: =IF(I13="Filled",H13-G13,IF(I13="Open",AsOf-G13,"")) -> 62 | R13: 15000
A14: REQ2128 | B14: Marketing | C14: Senior Marketing Executive | D14: L3 | E14: Low | F14: Farhan Siddiqui | G14: 45946 | H14: 45993 | I14: Filled | J14: Employee Referral | K14: 244 | L14: 53 | M14: 25 | N14: 1 | O14: 1 | P14: =IF(N14=0,"",O14/N14) -> 1 | Q14: =IF(I14="Filled",H14-G14,IF(I14="Open",AsOf-G14,"")) -> 47 | R14: 25000
A15: REQ2129 | B15: Marketing | C15: Marketing Lead | D15: L4 | E15: High | F15: Rakesh Nair | G15: 45946 | H15: 45984 | I15: Filled | J15: Careers Page | K15: 169 | L15: 49 | M15: 32 | N15: 1 | O15: 1 | P15: =IF(N15=0,"",O15/N15) -> 1 | Q15: =IF(I15="Filled",H15-G15,IF(I15="Open",AsOf-G15,"")) -> 38 | R15: 5000
A16: REQ2139 | B16: Engineering | C16: Engineering Manager | D16: L5 | E16: Medium | F16: Divya Menon | G16: 45948 | I16: On Hold | K16: 221 | L16: 35 | M16: 14 | N16: 0 | O16: 0 | P16: =IF(N16=0,"",O16/N16) | Q16: =IF(I16="Filled",H16-G16,IF(I16="Open",AsOf-G16,""))
A17: REQ2008 | B17: Sales | C17: Senior Sales Executive | D17: L3 | E17: Medium | F17: Rakesh Nair | G17: 45949 | I17: Open | K17: 53 | L17: 6 | M17: 3 | N17: 0 | O17: 0 | P17: =IF(N17=0,"",O17/N17) | Q17: =IF(I17="Filled",H17-G17,IF(I17="Open",AsOf-G17,"")) -> 346
A18: REQ2093 | B18: Human Resources | C18: HR Associate | D18: L1 | E18: High | F18: Farhan Siddiqui | G18: 45949 | H18: 45964 | I18: Filled | J18: Job Portals | K18: 238 | L18: 35 | M18: 23 | N18: 1 | O18: 1 | P18: =IF(N18=0,"",O18/N18) -> 1 | Q18: =IF(I18="Filled",H18-G18,IF(I18="Open",AsOf-G18,"")) -> 15 | R18: 12000
A19: REQ2072 | B19: Customer Support | C19: Support Executive | D19: L2 | E19: High | F19: Farhan Siddiqui | G19: 45950 | H19: 45987 | I19: Filled | J19: Careers Page | K19: 257 | L19: 38 | M19: 26 | N19: 1 | O19: 1 | P19: =IF(N19=0,"",O19/N19) -> 1 | Q19: =IF(I19="Filled",H19-G19,IF(I19="Open",AsOf-G19,"")) -> 37 | R19: 5000
A20: REQ2086 | B20: Product | C20: Product Analyst | D20: L2 | E20: Medium | F20: Rakesh Nair | G20: 45950 | H20: 45988 | I20: Filled | J20: LinkedIn | K20: 104 | L20: 23 | M20: 15 | N20: 1 | O20: 1 | P20: =IF(N20=0,"",O20/N20) -> 1 | Q20: =IF(I20="Filled",H20-G20,IF(I20="Open",AsOf-G20,"")) -> 38 | R20: 18000
A21: REQ2113 | B21: Customer Support | C21: Senior Support Executive | D21: L3 | E21: Medium | F21: Divya Menon | G21: 45950 | I21: Open | K21: 125 | L21: 28 | M21: 13 | N21: 0 | O21: 0 | P21: =IF(N21=0,"",O21/N21) | Q21: =IF(I21="Filled",H21-G21,IF(I21="Open",AsOf-G21,"")) -> 345
A22: REQ2027 | B22: Product | C22: Product Analyst | D22: L2 | E22: Medium | F22: Divya Menon | G22: 45952 | I22: On Hold | K22: 107 | L22: 25 | M22: 11 | N22: 0 | O22: 0 | P22: =IF(N22=0,"",O22/N22) | Q22: =IF(I22="Filled",H22-G22,IF(I22="Open",AsOf-G22,""))
A23: REQ2025 | B23: Operations | C23: Senior Operations Executive | D23: L3 | E23: Low | F23: Farhan Siddiqui | G23: 45956 | H23: 46008 | I23: Filled | J23: Job Portals | K23: 71 | L23: 14 | M23: 9 | N23: 1 | O23: 1 | P23: =IF(N23=0,"",O23/N23) -> 1 | Q23: =IF(I23="Filled",H23-G23,IF(I23="Open",AsOf-G23,"")) -> 52 | R23: 12000
A24: REQ2046 | B24: Sales | C24: Sales Executive | D24: L2 | E24: High | F24: Rakesh Nair | G24: 45956 | I24: Open | K24: 145 | L24: 40 | M24: 23 | N24: 0 | O24: 0 | P24: =IF(N24=0,"",O24/N24) | Q24: =IF(I24="Filled",H24-G24,IF(I24="Open",AsOf-G24,"")) -> 339
A25: REQ2090 | B25: Sales | C25: Senior Sales Executive | D25: L3 | E25: Low | F25: Farhan Siddiqui | G25: 45961 | I25: Open | K25: 91 | L25: 12 | M25: 7 | N25: 1 | O25: 0 | P25: =IF(N25=0,"",O25/N25) -> 0 | Q25: =IF(I25="Filled",H25-G25,IF(I25="Open",AsOf-G25,"")) -> 334
A26: REQ2066 | B26: Customer Support | C26: Support Associate | D26: L1 | E26: Medium | F26: Sonali K | G26: 45962 | H26: 45992 | I26: Filled | J26: Job Portals | K26: 93 | L26: 25 | M26: 15 | N26: 2 | O26: 1 | P26: =IF(N26=0,"",O26/N26) -> 0.5 | Q26: =IF(I26="Filled",H26-G26,IF(I26="Open",AsOf-G26,"")) -> 30 | R26: 12000
A27: REQ2135 | B27: Engineering | C27: Tech Lead | D27: L4 | E27: High | F27: Sonali K | G27: 45964 | H27: 46008 | I27: Filled | J27: LinkedIn | K27: 248 | L27: 57 | M27: 33 | N27: 3 | O27: 1 | P27: =IF(N27=0,"",O27/N27) -> 0.33333333 | Q27: =IF(I27="Filled",H27-G27,IF(I27="Open",AsOf-G27,"")) -> 44 | R27: 18000
A28: REQ2109 | B28: Finance | C28: Accounts Executive | D28: L2 | E28: Medium | F28: Rakesh Nair | G28: 45972 | I28: Open | K28: 142 | L28: 34 | M28: 17 | N28: 0 | O28: 0 | P28: =IF(N28=0,"",O28/N28) | Q28: =IF(I28="Filled",H28-G28,IF(I28="Open",AsOf-G28,"")) -> 323
A29: REQ2039 | B29: Operations | C29: Senior Operations Executive | D29: L3 | E29: High | F29: Farhan Siddiqui | G29: 45973 | H29: 46004 | I29: Filled | J29: Employee Referral | K29: 187 | L29: 53 | M29: 23 | N29: 1 | O29: 1 | P29: =IF(N29=0,"",O29/N29) -> 1 | Q29: =IF(I29="Filled",H29-G29,IF(I29="Open",AsOf-G29,"")) -> 31 | R29: 25000
A30: REQ2101 | B30: Marketing | C30: Senior Marketing Executive | D30: L3 | E30: Medium | F30: Divya Menon | G30: 45973 | I30: Open | K30: 62 | L30: 8 | M30: 5 | N30: 0 | O30: 0 | P30: =IF(N30=0,"",O30/N30) | Q30: =IF(I30="Filled",H30-G30,IF(I30="Open",AsOf-G30,"")) -> 322
A31: REQ2136 | B31: Legal & Compliance | C31: Compliance Executive | D31: L2 | E31: Medium | F31: Rakesh Nair | G31: 45973 | H31: 46018 | I31: Filled | J31: LinkedIn | K31: 120 | L31: 20 | M31: 8 | N31: 1 | O31: 1 | P31: =IF(N31=0,"",O31/N31) -> 1 | Q31: =IF(I31="Filled",H31-G31,IF(I31="Open",AsOf-G31,"")) -> 45 | R31: 18000
A32: REQ2078 | B32: Finance | C32: Accounts Executive | D32: L2 | E32: Medium | F32: Farhan Siddiqui | G32: 45974 | I32: Cancelled | K32: 184 | L32: 51 | M32: 33 | N32: 0 | O32: 0 | P32: =IF(N32=0,"",O32/N32) | Q32: =IF(I32="Filled",H32-G32,IF(I32="Open",AsOf-G32,""))
A33: REQ2015 | B33: Operations | C33: Senior Operations Executive | D33: L3 | E33: Medium | F33: Sonali K | G33: 45977 | H33: 46020 | I33: Filled | J33: Job Portals | K33: 112 | L33: 28 | M33: 18 | N33: 1 | O33: 1 | P33: =IF(N33=0,"",O33/N33) -> 1 | Q33: =IF(I33="Filled",H33-G33,IF(I33="Open",AsOf-G33,"")) -> 43 | R33: 12000
A34: REQ2063 | B34: Operations | C34: Operations Associate | D34: L1 | E34: Medium | F34: Divya Menon | G34: 45984 | I34: Open | K34: 49 | L34: 10 | M34: 4 | N34: 0 | O34: 0 | P34: =IF(N34=0,"",O34/N34) | Q34: =IF(I34="Filled",H34-G34,IF(I34="Open",AsOf-G34,"")) -> 311
A35: REQ2014 | B35: Operations | C35: Operations Executive | D35: L2 | E35: Medium | F35: Rakesh Nair | G35: 45985 | I35: Open | K35: 228 | L35: 65 | M35: 34 | N35: 0 | O35: 0 | P35: =IF(N35=0,"",O35/N35) | Q35: =IF(I35="Filled",H35-G35,IF(I35="Open",AsOf-G35,"")) -> 310
A36: REQ2042 | B36: Operations | C36: Senior Operations Executive | D36: L3 | E36: Medium | F36: Farhan Siddiqui | G36: 45985 | I36: Open | K36: 80 | L36: 10 | M36: 4 | N36: 0 | O36: 0 | P36: =IF(N36=0,"",O36/N36) | Q36: =IF(I36="Filled",H36-G36,IF(I36="Open",AsOf-G36,"")) -> 310
A37: REQ2033 | B37: Legal & Compliance | C37: Senior Legal Manager | D37: L6 | E37: Medium | F37: Rakesh Nair | G37: 45989 | I37: Open | K37: 223 | L37: 55 | M37: 35 | N37: 0 | O37: 0 | P37: =IF(N37=0,"",O37/N37) | Q37: =IF(I37="Filled",H37-G37,IF(I37="Open",AsOf-G37,"")) -> 306
A38: REQ2052 | B38: Operations | C38: Senior Operations Executive | D38: L3 | E38: High | F38: Sonali K | G38: 45992 | H38: 46038 | I38: Filled | J38: Employee Referral | K38: 52 | L38: 11 | M38: 4 | N38: 3 | O38: 1 | P38: =IF(N38=0,"",O38/N38) -> 0.33333333 | Q38: =IF(I38="Filled",H38-G38,IF(I38="Open",AsOf-G38,"")) -> 46 | R38: 25000
A39: REQ2126 | B39: Engineering | C39: Tech Lead | D39: L4 | E39: High | F39: Farhan Siddiqui | G39: 45995 | I39: Open | K39: 81 | L39: 14 | M39: 5 | N39: 1 | O39: 0 | P39: =IF(N39=0,"",O39/N39) -> 0 | Q39: =IF(I39="Filled",H39-G39,IF(I39="Open",AsOf-G39,"")) -> 300
A40: REQ2028 | B40: Operations | C40: Senior Operations Manager | D40: L6 | E40: High | F40: Divya Menon | G40: 45998 | H40: 46053 | I40: Filled | J40: Consultancy | K40: 164 | L40: 19 | M40: 10 | N40: 1 | O40: 1 | P40: =IF(N40=0,"",O40/N40) -> 1 | Q40: =IF(I40="Filled",H40-G40,IF(I40="Open",AsOf-G40,"")) -> 55 | R40: 349860
A41: REQ2138 | B41: Operations | C41: Senior Operations Executive | D41: L3 | E41: High | F41: Farhan Siddiqui | G41: 46000 | I41: On Hold | K41: 243 | L41: 70 | M41: 37 | N41: 0 | O41: 0 | P41: =IF(N41=0,"",O41/N41) | Q41: =IF(I41="Filled",H41-G41,IF(I41="Open",AsOf-G41,""))
A42: REQ2098 | B42: Legal & Compliance | C42: Compliance Manager | D42: L5 | E42: High | F42: Farhan Siddiqui | G42: 46007 | H42: 46069 | I42: Filled | J42: Employee Referral | K42: 54 | L42: 14 | M42: 9 | N42: 2 | O42: 1 | P42: =IF(N42=0,"",O42/N42) -> 0.5 | Q42: =IF(I42="Filled",H42-G42,IF(I42="Open",AsOf-G42,"")) -> 62 | R42: 25000
A43: REQ2107 | B43: Customer Support | C43: Support Executive | D43: L2 | E43: Medium | F43: Divya Menon | G43: 46007 | H43: 46046 | I43: Filled | J43: Job Portals | K43: 40 | L43: 10 | M43: 5 | N43: 1 | O43: 1 | P43: =IF(N43=0,"",O43/N43) -> 1 | Q43: =IF(I43="Filled",H43-G43,IF(I43="Open",AsOf-G43,"")) -> 39 | R43: 12000
